Workbook
Name Administrador_SARLAFT: OFFSET(INDIRECT('OTRAS 1'!A$29),0,0,COUNTIF(OtrasApp[[#All],[App]],'OTRAS 1'!$B$22 & "-" &'OTRAS 1'!A$33))
Name AppIseries: Tabla11[App Iseries]
Name AppIseries: Tabla11[App Iseries]
Name AppIseries: Tabla11[App Iseries]
Name AppLaserfiche: Tabla3[AppLaserfiche]
Name AppLaserfiche: Tabla3[AppLaserfiche]
Name AppSalud: 'SALUD 1'!$O$252:$P$254
Name AppSalud2: 'SALUD 1'!$R$252:$T$271
Name Area_Eflow: SharePoint!$BS$2:$BS$27
Name ciudad: '[1]PERSONAL MEDICO'!$AU$1000008:$AV$1001048
Name COD_ESP: '[1]PERSONAL MEDICO'!$AM$1000008:$AN$1000108
Name Deposito: Tabla32587[[DEPOSITO ]]
Name ECredisystem: SharePoint!$AS$2:$AS$23
Name ESPECIALIDAD: '[1]PERSONAL MEDICO'!$AM$1000008:$AM$1000109
Name EstadoCivil: Tabla12[EstadoCivil]
Name EstadoCivil: Tabla12[EstadoCivil]
Name FacturadorSAC: SharePoint!$U$2:$U$4
Name Fosfec: SharePoint!$O$2:$O$4
Name FuncTPNET1: OFFSET(INDIRECT('MEDICAMENTOS 1'!A$23),0,0,COUNTIF('MEDICAMENTOS 1'!$R$250:$R$279,'MEDICAMENTOS 1'!A$26))
Name FuncTPNET2: OFFSET(INDIRECT('MEDICAMENTOS 1'!A$24),0,0,COUNTIF('MEDICAMENTOS 1'!$M$250:$M$303,'MEDICAMENTOS 1'!A$27))
Name Grup_Eflow: Tabla2[GRUPO-EFLOW]
Name Grup_Eflow: Tabla2[GRUPO-EFLOW]
Name GrupSeven: SharePoint!$BC$2:$BC$83
Name IPS_Salud: 'SALUD 1'!$L$252:$M$288
Name Jedox: SharePoint!$S$2:$S$7
Name LinkAppFinanciera: Navegación!$B$62
Name LinkAppMedicamentos: Navegación!$B$41
Name LinkAppOtras: Navegación!$B$77
Name LinkAppPrivilegiados: Navegación!$A$100
Name LinkAppRecreacion: Navegación!$B$55
Name LinkAppSalud: Navegación!$A$35
Name LinkAppSAP: Navegación!$B$36
Name LinkAppVivienda: Navegación!$B$72
Name LinkAppWindows: Navegación!$A$24
Name LinkMasivos: Navegación!$C$102
Name lista1: 'SALUD 1'!$M$128:$M$146
Name Ofc_Eflow: SharePoint!$BO$2:$BO$25
Name P_Enterprise: SharePoint!$Y$2:$Y$8
Name P_EvenTeatro: Tabla13[Perfil Ev Teatro]
Name P_EvenTeatro: Tabla13[Perfil Ev Teatro]
Name P_EvenTeatro: Tabla13[Perfil Ev Teatro]
Name P_Hercules: OFFSET(INDIRECT('RECREACION 1'!#REF!),0,0,COUNTIF(RolesNew[#All],'RECREACION 1'!#REF!))
Name P_Hercules: OFFSET(INDIRECT('RECREACION 5'!$D$23),0,0,COUNTIF(RolesNew117118119[#All],'RECREACION 5'!$B$22))
Name P_Hercules: OFFSET(INDIRECT('RECREACION 1'!#REF!),0,0,COUNTIF(RolesNew[#All],'RECREACION 1'!#REF!))
Name P_Iseries: SharePoint!$BM$2:$BM$43
Name P_LASERFICHE: OFFSET(INDIRECT('OTRAS 10'!A$23),0,0,COUNTIF(OtrasApp141142143144145146147148149150151[[#All],[App]],'OTRAS 10'!$B$22 & "-" & 'OTRAS 10'!A$27))
Name P_LASERFICHE: OFFSET(INDIRECT('OTRAS 1'!A$78),0,0,COUNTIF(OtrasApp141142[[#All],[App]],'OTRAS 1'!$B$76 & "-" & 'OTRAS 1'!A$82))
Name P_LASERFICHE: OFFSET(INDIRECT('OTRAS 1'!A$78),0,0,COUNTIF(OtrasApp[[#All],[App]],'OTRAS 1'!#REF! & "-" & 'OTRAS 1'!A$82))
Name P_Q10: OFFSET(INDIRECT('OTRAS 13'!A$23),0,0,COUNTIF(OtrasApp141142143144145146147148149150151152153154[[#All],[App]],'OTRAS 13'!$B$22 & "-" & 'OTRAS 13'!A$33))
Name P_Q10: OFFSET(INDIRECT('OTRAS 1'!A$97),0,0,COUNTIF(OtrasApp141142[[#All],[App]],'OTRAS 1'!$B$95 & "-" & 'OTRAS 1'!A$107))
Name P_Q10: OFFSET(INDIRECT('OTRAS 1'!A$97),0,0,COUNTIF(OtrasApp[[#All],[App]],'OTRAS 1'!#REF! & "-" & 'OTRAS 1'!A$107))
Name P_Recreacion: 'RECREACION 1'!$L$250:$M$322
Name P_SAS: SharePoint!$BE$2:$BE$4
Name P_SEVEN: SharePoint!$BA$2:$BA$7
Name P_TM1: SharePoint!$BG$2:$BG$4
Name P_WebFamisanar: SharePoint!$AE$2:$AE$11
Name PagosTIC: Tabla65[Pagos TIC]
Name PagosTIC: Tabla65[Pagos TIC]
Name PagosTIC: Tabla65[Pagos TIC]
Name Perfil_NAPSE_Director: OFFSET(INDIRECT('MEDICAMENTOS 10'!A$28),0,0,COUNTIF(P_NAPSE[],'MEDICAMENTOS 10'!$D$31))

Sheet Perfiles ISERIES
A6: Medicamentos SIGED | C6: SALUD
A7: Unidad Reaprovisionamiento | C7: Cajero
A8: Auxiliar Compras Costo Promedio | C8: Recaudos
A9: Master Siged | C9: Reservas CC
A10: Analista Almacenamiento | C10: Grupo de Apoyo
A11: Analista Centro Distribución Medicamentos
A12: Auxiliar Recibo Inventario
A13: Auxiliar Recibo Inventario Costo Promedio
A14: Jefe Sección Almacenamiento
A15: Revisor Documentos Cendis
A16: Supervisores Bodega
A17: Analista Compras Medicamentos
A18: Jefe Producto Medicamentos
A19: Departamento Técnico
A20: Consulta Ventas
A21: Monitor Droguerías (Regente)
A22: Supervisores Punto De Venta
... A26: Revisor Movimiento Mercancias

Sheet Menu

Sheet INFORME
A1: Grupo | B1: App | C1: Cant. Novedades
A2: Windows | B2: Windows | C2: ='WINDOWS 1'!$DZ$22 -> 1
B3: Share point | C3: ='WINDOWS 1'!$DZ$31 -> 0
B4: Buzon Personal | C4: ='WINDOWS 1'!$DZ$38 -> 0
B5: Buzon de Area | C5: ='WINDOWS 1'!$DZ$41 -> 0
A6: Salud | B6: Integra - BreakPoint Famisanar | C6: ='SALUD 1'!$DZ$26 -> 0
B7: PANA - NEPS | C7: ='SALUD 1'!$DZ$42 -> #REF!
B8: RETHUS | C8: ='SALUD 1'!$DZ$51 -> #REF!
B9: ZERO | C9: ='SALUD 1'!$DZ$62 -> #REF!
B10: Enterprise | C10: ='SALUD 1'!$DZ$72 -> #REF!
B11: Sycyproh | C11: ='SALUD 1'!$DZ$82 -> #REF!
B12: SIGESA | C12: ='SALUD 1'!$DZ$96 -> #REF!
B13: ISERIES | C13: ='SALUD 1'!$DZ$102 -> #REF!
B14: Web Famisanar en Linea | C14: ='SALUD 1'!$DZ$106 -> #REF!
B15: RUAF | C15: ='SALUD 1'!$DZ$110 -> #REF!
A16: SAP | B16: SAP | C16: ='SAP 1'!$DZ$22 -> 0
B17: Solucion WEB Roles SAP | C17: ='SAP 1'!$DZ$30 -> #REF!
B18: Cash Journal | C18: ='SAP 1'!$DZ$34 -> #REF!
B19: Facturador SD | C19: ='SAP 1'!$DZ$40 -> #REF!
B20: Liberacion Pedidos | C20: ='SAP 1'!$DZ$43 -> #REF!
A21: Medicamentos | B21: TPNET | C21: ='MEDICAMENTOS 1'!$DZ$30+'MEDICAMENTOS 1'!$DZ$32+'MEDICAMENTOS 1'!$DZ$34+'MEDICAMENTOS 1'!$DZ$36+'MEDICAMENTOS 1'!$DZ$38+'MEDICAMENTOS 1'!$DZ$40 -> 0
B22: WMS | C22: ='MEDICAMENTOS 1'!$DZ$42 -> 0
B23: SIGED | C23: ='MEDICAMENTOS 1'!$DZ$50 -> #REF!
B24: Medicar | C24: ='MEDICAMENTOS 1'!$DZ$54 -> #REF!
B25: MULTICANAL | C25: ='MEDICAMENTOS 1'!$DZ$56 -> 0
B26: POS IBM | C26: ='MEDICAMENTOS 1'!$DZ$58 -> #REF!
B27: Web Famisanar en Linea | C27: ='MEDICAMENTOS 1'!$DZ$60 -> 0
A28: Recreación | B28: New Plan | C28: ='RECREACION 1'!$DZ$24 -> 0
B29: New Hotel | C29: ='RECREACION 1'!$DZ$29 -> 0
B30: New POS | C30: ='RECREACION 1'!$DZ$34 -> 0
B31: New Stock | C31: ='RECREACION 1'!$DZ$39 -> 0
B32: New Caja | C32: ='RECREACION 1'!$DZ$44 -> 0
B33: SAC | C33: ='RECREACION 1'!$DZ$49 -> 0
B34: Silvernest | C34: ='RECREACION 1'!$DZ$55 -> #REF!
B35: Zeus Online | C35: ='RECREACION 1'!$DZ$60 -> #REF!
B36: Hercules | C36: ='RECREACION 1'!$DZ$65 -> #REF!
A37: Financiera | B37: E-credisystem | C37: ='FINANCIERA 1'!$DZ$23 -> 0
B38: SEVEN | C38: ='FINANCIERA 1'!$DZ$27 -> #REF!
B39: SAS | C39: ='FINANCIERA 1'!$DZ$39 -> #REF!
B40: TM1 | C40: ='FINANCIERA 1'!$DZ$43 -> #REF!
B41: Jedox | C41: ='FINANCIERA 1'!$DZ$50 -> #REF!
B42: Pasarela PAYU | C42: ='FINANCIERA 1'!$DZ$54 -> #REF!
B43: Pasarela Place to Pay | C43: ='FINANCIERA 1'!$DZ$59 -> #REF!
A44: Vivienda | B44: Fovis (SEVEN) | C44: ='VIVIENDA 1'!$DZ$23 -> 0
B45: VIMALL | C45: ='VIVIENDA 1'!$DW$35 -> #REF!
B46: ISERIES | C46: ='VIVIENDA 1'!$DW$42 -> #REF!
A47: Otras | B47: SIGA | C47: ='OTRAS 1'!$DH$30 -> 0
B48: CRM Dynamics | C48: ='OTRAS 1'!$DH$36 -> #REF!
B49: ZEUS POS | C49: ='OTRAS 1'!$DH$40 -> #REF!
B50: New Pos A&B Bta. | C50: ='OTRAS 1'!$DH$47 -> #REF!
B51: Kactus | C51: ='OTRAS 1'!$DH$51 -> #REF!
B52: TIC | C52: ='OTRAS 1'!$DH$55 -> #REF!
B53: QuickScore | C53: ='OTRAS 1'!$DH$59 -> #REF!
B54: Fosfec | C54: ='OTRAS 1'!$DH$63 -> #REF!
B55: Zenith | C55: ='OTRAS 1'!$DH$67 -> #REF!
B56: GLPI (Zenith) | C56: ='OTRAS 1'!$DH$70 -> #REF!
B57: E-Flow | C57: ='OTRAS 1'!$DH$72 -> #REF!
B58: Laserfiche | C58: ='OTRAS 1'!$DH$79 -> #REF!
B59: PQRSF | C59: ='OTRAS 1'!$DH$86 -> #REF!
B60: Eventos Teatro | C60: ='OTRAS 1'!$DH$91 -> #REF!
B61: Q10 | C61: ='OTRAS 1'!$DH$98 -> #REF!
B62: Modulo Pagos TIC | C62: ='OTRAS 1'!$DH$110 -> #REF!
B63: Otras App | C63: ='OTRAS 1'!$DH$115 -> #REF!
B64: ISERIES | C64: ='OTRAS 1'!$DH$123 -> #REF!
A65: Privilegiados | B65: Base de Datos | C65: ='FGI-PRIVILEGIADOS'!$DZ$32 -> 0
B66: Windows | C66: ='FGI-PRIVILEGIADOS'!$DZ$37 -> 0
B67: AIX | C67: ='FGI-PRIVILEGIADOS'!$DZ$42 -> 0
B68: Linux | C68: ='FGI-PRIVILEGIADOS'!$DZ$47 -> 0
B69: ISERIES | C69: ='FGI-PRIVILEGIADOS'!$DZ$52 -> 0

Sheet WINDOWS 1
K1: 2958465
C2: FORMATO: GESTIÓN DE IDENTIDADES
F3: DOCUMENTO USO INTERNO
B5: Las celdas resaltadas en Naranja son campos obligatorios del Formato.
B6: Información Usuarios | D6: Usuario 1 | E6: Usuario 2 | F6: Usuario 3 | G6: Usuario 4 | H6: Usuario 5 | I6: Usuario 6
B7: Tipo de documento | D7: =IF(Navegación!D7<>"",Navegación!D7,"") -> Cédula Ciudadanía | E7: =IF(Navegación!E7<>"",Navegación!E7,"") | F7: =IF(Navegación!F7<>"",Navegación!F7,"") | G7: =IF(Navegación!G7<>"",Navegación!G7,"") | H7: =IF(Navegación!H7<>"",Navegación!H7,"") | I7: =IF(Navegación!I7<>"",Navegación!I7,"")
B8: Identificación | D8: =IF(Navegación!D8<>"",Navegación!D8,"") -> 1001089595 | E8: =IF(Navegación!E8<>"",Navegación!E8,"") | F8: =IF(Navegación!F8<>"",Navegación!F8,"") | G8: =IF(Navegación!G8<>"",Navegación!G8,"") | H8: =IF(Navegación!H8<>"",Navegación!H8,"") | I8: =IF(Navegación!I8<>"",Navegación!I8,"")
B9: Nombres completos | D9: =IF(Navegación!D9<>"",Navegación!D9,"") -> JUAN PABLO | E9: =IF(Navegación!E9<>"",Navegación!E9,"") | F9: =IF(Navegación!F9<>"",Navegación!F9,"") | G9: =IF(Navegación!G9<>"",Navegación!G9,"") | H9: =IF(Navegación!H9<>"",Navegación!H9,"") | I9: =IF(Navegación!I9<>"",Navegación!I9,"")
B10: Apellidos completos | D10: =IF(Navegación!D10<>"",Navegación!D10,"") -> CAMPO TELLEZ | E10: =IF(Navegación!E10<>"",Navegación!E10,"") | F10: =IF(Navegación!F10<>"",Navegación!F10,"") | G10: =IF(Navegación!G10<>"",Navegación!G10,"") | H10: =IF(Navegación!H10<>"",Navegación!H10,"") | I10: =IF(Navegación!I10<>"",Navegación!I10,"")
B11: Centro de costo | D11: =IF(Navegación!D11<>"",Navegación!D11,"") -> 856 | E11: =IF(Navegación!E11<>"",Navegación!E11,"") | F11: =IF(Navegación!F11<>"",Navegación!F11,"") | G11: =IF(Navegación!G11<>"",Navegación!G11,"") | H11: =IF(Navegación!H11<>"",Navegación!H11,"") | I11: =IF(Navegación!I11<>"",Navegación!I11,"")
B12: Teléfono/Extensión de contacto del usuario | D12: =IF(Navegación!D12<>"",Navegación!D12,"") | E12: =IF(Navegación!E12<>"",Navegación!E12,"") | F12: =IF(Navegación!F12<>"",Navegación!F12,"") | G12: =IF(Navegación!G12<>"",Navegación!G12,"") | H12: =IF(Navegación!H12<>"",Navegación!H12,"") | I12: =IF(Navegación!I12<>"",Navegación!I12,"")
B13: Celular | D13: =IF(Navegación!D13<>"",Navegación!D13,"") -> 3150727969 | E13: =IF(Navegación!E13<>"",Navegación!E13,"") | F13: =IF(Navegación!F13<>"",Navegación!F13,"") | G13: =IF(Navegación!G13<>"",Navegación!G13,"") | H13: =IF(Navegación!H13<>"",Navegación!H13,"") | I13: =IF(Navegación!I13<>"",Navegación!I13,"")
B14: Dependencia | D14: =IF(Navegación!D14<>"",Navegación!D14,"") -> Gobierno | E14: =IF(Navegación!E14<>"",Navegación!E14,"") | F14: =IF(Navegación!F14<>"",Navegación!F14,"") | G14: =IF(Navegación!G14<>"",Navegación!G14,"") | H14: =IF(Navegación!H14<>"",Navegación!H14,"") | I14: =IF(Navegación!I14<>"",Navegación!I14,"")
B15: Cargo | D15: =IF(Navegación!D15<>"",Navegación!D15,"") -> Aprendiz Universitario | E15: =IF(Navegación!E15<>"",Navegación!E15,"") | F15: =IF(Navegación!F15<>"",Navegación!F15,"") | G15: =IF(Navegación!G15<>"",Navegación!G15,"") | H15: =IF(Navegación!H15<>"",Navegación!H15,"") | I15: =IF(Navegación!I15<>"",Navegación!I15,"")
B16: Empleado Cafam o Externo | D16: =IF(Navegación!D16<>"",Navegación!D16,"") -> Empleado CAFAM | E16: =IF(Navegación!E16<>"",Navegación!E16,"") | F16: =IF(Navegación!F16<>"",Navegación!F16,"") | G16: =IF(Navegación!G16<>"",Navegación!G16,"") | H16: =IF(Navegación!H16<>"",Navegación!H16,"") | I16: =IF(Navegación!I16<>"",Navegación!I16,"")
B17: Nombre de la empresa cuando es Externo | D17: =IF(Navegación!D17<>"",Navegación!D17,"") | E17: =IF(Navegación!E17<>"",Navegación!E17,"") | F17: =IF(Navegación!F17<>"",Navegación!F17,"") | G17: =IF(Navegación!G17<>"",Navegación!G17,"") | H17: =IF(Navegación!H17<>"",Navegación!H17,"") | I17: =IF(Navegación!I17<>"",Navegación!I17,"")
B18: Fecha inicio contrato: | D18: =IF(Navegación!D18<>"",Navegación!D18,"") -> 45849 | E18: =IF(Navegación!E18<>"",Navegación!E18,"") | F18: =IF(Navegación!F18<>"",Navegación!F18,"") | G18: =IF(Navegación!G18<>"",Navegación!G18,"") | H18: =IF(Navegación!H18<>"",Navegación!H18,"") | I18: =IF(Navegación!I18<>"",Navegación!I18,"")
B19: Fecha finalización contrato: (Si es indefinido escribir 31/12/9999) | D19: =IF(Navegación!D19<>"",Navegación!D19,"") | E19: =IF(Navegación!E19<>"",Navegación!E19,"") | F19: =IF(Navegación!F19<>"",Navegación!F19,"") | G19: =IF(Navegación!G19<>"",Navegación!G19,"") | H19: =IF(Navegación!H19<>"",Navegación!H19,"") | I19: =IF(Navegación!I19<>"",Navegación!I19,"")
B21: Requerimientos Plataforma Windows | D21: =IF(DZ22>0,Navegación!$E$21,"") -> Esta aplicación solo requiere VoBo de su Jefatura
B22: Novedad Windows (Crear/Modificar/Baja) | D22: Crear | DZ22: =COUNTIF(D22:I22,"<>") -> 1
B23: Alias del Usuario Windows (a modificar o dar de baja)
B24: Accesos adicionales Windows
B25: Accesos VPN | D25: Aplicaciones
B26: Detalle Acceso a VPN (Aplicaciones) Nombre de Equipo (Escritorio Remoto) | D26: wso2/aro
B27: Acceso a recursos compartidos (\\nombre_servidor\nombre_recurso)
B28: Permisos a Almacenamiento Externo (relacionar los sitios especificos en fila "Permisos y accesos adicionales") - Adjunte autorizacion de Oficial de Seguridad
B29: Permisos y accesos adicionales
B31: Observaciones | C31: Grupo de recursos por suscripción: az-trv-prod-suscripcion - az-trv-prd-rg-apim az-hub-devqa-suscripcion - az-hub-devqa-rg-security-00
B37: APROBADOR POR: Jefe Dpto. Servicios Compartidos | F37: ='Control de cambios'!$A$14 -> V20 de 26/09/2023 | I37: ="Pág. " &Navegación!B21 & " de " &Navegación!$B$102 -> Pág. 1 de 54

Sheet Instructivo
A1: Instructivo Formato Gestión de Identidades
A3: Es un único formato que debe ser utilizado para realizar los requerimientos de usuarios y accesos a los diferentes sistemas de información. Este formato deberá ser remitido a la mesa de servicio con las autorizaciones correspondientes. NO es aceptable la copia de perfiles, es decir que las solicitudes se remitan bajo el parámetro "con los mismos perfiles de una persona", se debe partir del mínimo privilegio.
A5: Definiciones
A6: Alta: Crear usuario
A7: Modificación: Modificar un usuario
A8: Bloqueo - Baja: Deshabilitar usuario / Eliminar usuario (En algunos aplicativos por buenas practicas no se elimina el usuario, solo se bloquea)
A9: Ampliación Vigencia: El usuario tenia una fecha de contrato y se requiere ampliar esta fecha
A11: Información Solicitante
A12: Información obligatoria. Todo requerimiento debe ser remitido a la mesa de servicio con el visto bueno de la jefatura de la Unidad Estratégica de Servicio que requiere el acceso, de acuerdo al Orden Jerárquico del artículo 56 del Reglamento interno de trabajo, es decir (DIRECTOR ADMINISTRATIVO, SUBDIRECTORES, JEFES DEPARTAMENTO, JEFES SECCION – ADMINISTRADORES, JEFES DE AREA, SUPERVISORES – COORDINADORES).
A14: Información Usuarios
A15: Información obligatoria. La identificación es un campo numérico que debe llenarse sin puntos ni comas. Los nombres y apellidos deben ser completos y escritos como figuran en el documento de identificación. El centro de costo y dependencia del funcionario o de la dependencia para la cual trabaja la persona externa, de igual manera indicar el cargo. Indicar un número de contacto del usuario a quien se le va a asignar los privilegios El campo empleado Cafam o Externo, cuando el usuario es Externo se debe escribir el nombre de la empresa o proveedor Se debe definir fecha inicio de contrato y fecha fin, cuando se tenga contrato indefinido coloque 31/12/9999. Ningun funcionario externo puede tener vigencia Indefinida. Si require incluir mas usuarios, proceda a copiar la ultima columna y utiice la opcion "Insertar celdas copiadas".
A17: Requerimientos Plataforma Windows
... A32: CashJornal es la caja de SAP que se utiliza para pagos de subsidio y educación, a este modulo tienen acceso únicamente las centrales de servicio (Supervisores, revisores y cajeros). Cajas para asignar: En estos campos se debe indicar si el acceso se requiere para Educación, Subsidio o Ambas. Función a desempeñar: Indique el rol o función que va a desempeñar, es decir si es Cajero o Revisor. Corresponde a reemplazo o asignacion nueva: seleccione la opcion identificando la que corresponda. Nombre Sucursal: Describa el nombre de la sucursal a la cual estara asignado el usuario. Si se trata de un traslado por favor indicar el número y nombre de la caja que tenía asignada. Esto con el fin de facilitar la asignacion de la caja

Sheet WINDOWS 2
K1: 2958465
C2: FORMATO: GESTIÓN DE IDENTIDADES
F3: DOCUMENTO USO INTERNO
B5: Las celdas resaltadas en Naranja son campos obligatorios del Formato.
B6: Información Usuarios | D6: Usuario 1 | E6: Usuario 2 | F6: Usuario 3 | G6: Usuario 4 | H6: Usuario 5 | I6: Usuario 6
B7: Tipo de documento | D7: =IF(Navegación!D7<>"",Navegación!D7,"") -> Cédula Ciudadanía | E7: =IF(Navegación!E7<>"",Navegación!E7,"") | F7: =IF(Navegación!F7<>"",Navegación!F7,"") | G7: =IF(Navegación!G7<>"",Navegación!G7,"") | H7: =IF(Navegación!H7<>"",Navegación!H7,"") | I7: =IF(Navegación!I7<>"",Navegación!I7,"")
B8: Identificación | D8: =IF(Navegación!D8<>"",Navegación!D8,"") -> 1001089595 | E8: =IF(Navegación!E8<>"",Navegación!E8,"") | F8: =IF(Navegación!F8<>"",Navegación!F8,"") | G8: =IF(Navegación!G8<>"",Navegación!G8,"") | H8: =IF(Navegación!H8<>"",Navegación!H8,"") | I8: =IF(Navegación!I8<>"",Navegación!I8,"")
B9: Nombres completos | D9: =IF(Navegación!D9<>"",Navegación!D9,"") -> JUAN PABLO | E9: =IF(Navegación!E9<>"",Navegación!E9,"") | F9: =IF(Navegación!F9<>"",Navegación!F9,"") | G9: =IF(Navegación!G9<>"",Navegación!G9,"") | H9: =IF(Navegación!H9<>"",Navegación!H9,"") | I9: =IF(Navegación!I9<>"",Navegación!I9,"")
B10: Apellidos completos | D10: =IF(Navegación!D10<>"",Navegación!D10,"") -> CAMPO TELLEZ | E10: =IF(Navegación!E10<>"",Navegación!E10,"") | F10: =IF(Navegación!F10<>"",Navegación!F10,"") | G10: =IF(Navegación!G10<>"",Navegación!G10,"") | H10: =IF(Navegación!H10<>"",Navegación!H10,"") | I10: =IF(Navegación!I10<>"",Navegación!I10,"")
B11: Centro de costo | D11: =IF(Navegación!D11<>"",Navegación!D11,"") -> 856 | E11: =IF(Navegación!E11<>"",Navegación!E11,"") | F11: =IF(Navegación!F11<>"",Navegación!F11,"") | G11: =IF(Navegación!G11<>"",Navegación!G11,"") | H11: =IF(Navegación!H11<>"",Navegación!H11,"") | I11: =IF(Navegación!I11<>"",Navegación!I11,"")
B12: Teléfono/Extensión de contacto del usuario | D12: =IF(Navegación!D12<>"",Navegación!D12,"") | E12: =IF(Navegación!E12<>"",Navegación!E12,"") | F12: =IF(Navegación!F12<>"",Navegación!F12,"") | G12: =IF(Navegación!G12<>"",Navegación!G12,"") | H12: =IF(Navegación!H12<>"",Navegación!H12,"") | I12: =IF(Navegación!I12<>"",Navegación!I12,"")
B13: Celular | D13: =IF(Navegación!D13<>"",Navegación!D13,"") -> 3150727969 | E13: =IF(Navegación!E13<>"",Navegación!E13,"") | F13: =IF(Navegación!F13<>"",Navegación!F13,"") | G13: =IF(Navegación!G13<>"",Navegación!G13,"") | H13: =IF(Navegación!H13<>"",Navegación!H13,"") | I13: =IF(Navegación!I13<>"",Navegación!I13,"")
B14: Dependencia | D14: =IF(Navegación!D14<>"",Navegación!D14,"") -> Gobierno | E14: =IF(Navegación!E14<>"",Navegación!E14,"") | F14: =IF(Navegación!F14<>"",Navegación!F14,"") | G14: =IF(Navegación!G14<>"",Navegación!G14,"") | H14: =IF(Navegación!H14<>"",Navegación!H14,"") | I14: =IF(Navegación!I14<>"",Navegación!I14,"")
B15: Cargo | D15: =IF(Navegación!D15<>"",Navegación!D15,"") -> Aprendiz Universitario | E15: =IF(Navegación!E15<>"",Navegación!E15,"") | F15: =IF(Navegación!F15<>"",Navegación!F15,"") | G15: =IF(Navegación!G15<>"",Navegación!G15,"") | H15: =IF(Navegación!H15<>"",Navegación!H15,"") | I15: =IF(Navegación!I15<>"",Navegación!I15,"")
B16: Empleado Cafam o Externo | D16: =IF(Navegación!D16<>"",Navegación!D16,"") -> Empleado CAFAM | E16: =IF(Navegación!E16<>"",Navegación!E16,"") | F16: =IF(Navegación!F16<>"",Navegación!F16,"") | G16: =IF(Navegación!G16<>"",Navegación!G16,"") | H16: =IF(Navegación!H16<>"",Navegación!H16,"") | I16: =IF(Navegación!I16<>"",Navegación!I16,"")
B17: Nombre de la empresa cuando es Externo | D17: =IF(Navegación!D17<>"",Navegación!D17,"") | E17: =IF(Navegación!E17<>"",Navegación!E17,"") | F17: =IF(Navegación!F17<>"",Navegación!F17,"") | G17: =IF(Navegación!G17<>"",Navegación!G17,"") | H17: =IF(Navegación!H17<>"",Navegación!H17,"") | I17: =IF(Navegación!I17<>"",Navegación!I17,"")
B18: Fecha inicio contrato: | D18: =IF(Navegación!D18<>"",Navegación!D18,"") -> 45849 | E18: =IF(Navegación!E18<>"",Navegación!E18,"") | F18: =IF(Navegación!F18<>"",Navegación!F18,"") | G18: =IF(Navegación!G18<>"",Navegación!G18,"") | H18: =IF(Navegación!H18<>"",Navegación!H18,"") | I18: =IF(Navegación!I18<>"",Navegación!I18,"")
B19: Fecha finalización contrato: (Si es indefinido escribir 31/12/9999) | D19: =IF(Navegación!D19<>"",Navegación!D19,"") | E19: =IF(Navegación!E19<>"",Navegación!E19,"") | F19: =IF(Navegación!F19<>"",Navegación!F19,"") | G19: =IF(Navegación!G19<>"",Navegación!G19,"") | H19: =IF(Navegación!H19<>"",Navegación!H19,"") | I19: =IF(Navegación!I19<>"",Navegación!I19,"")
B21: Requerimientos Share Point | D21: =IF(DZ22>0,Navegación!$E$22,"") -> Esta aplicación solo requiere VoBo de su Jefatura
B22: Novedad Windows (Crear/Modificar/Baja) | D22: Crear | DZ22: =COUNTIF(D22:I22,"<>") -> 1
B23: Alias del Usuario Windows
B24: URL | D24: https://cafamonline.sharepoint.com/sites/Sub_TID/Gestion%20de%20proyectos%20TI/Formatos%20Base/Forms/AllItems.aspx?id=%2Fsites%2FSub%5FTID%2FGestion%20de%20proyectos%20TI%2FFormatos%20Base%2FBuenas%20practicas%20Desarrollo%20%20Gobierno%20TI&viewid=12aefa60%2D5848%2D4042%2D8abb%2D1af8493c56f2
B25: Biblioteca
B26: Tipo permiso | D26: Lectura
B28: Observaciones | C28: Grupo de recursos por suscripción: az-trv-prod-suscripcion - az-trv-prd-rg-apim az-hub-devqa-suscripcion - az-hub-devqa-rg-security-00
B33: ='WINDOWS 1'!$B$37 -> APROBADOR POR: Jefe Dpto. Servicios Compartidos | F33: ='WINDOWS 1'!F37 -> V20 de 26/09/2023 | I33: ="Pág. " &Navegación!B22 & " de " &Navegación!$B$102 -> Pág. 2 de 54
DZ37: =COUNTIF(D22:I22,"<>") -> 1
DZ44: =COUNTIF(#REF!,"<>") -> #REF!
DZ47: =COUNTIF(#REF!,"<>") -> #REF!

Sheet WINDOWS 3
K1: 2958465
C2: FORMATO: GESTIÓN DE IDENTIDADES
F3: DOCUMENTO USO INTERNO
B5: Las celdas resaltadas en Naranja son campos obligatorios del Formato.
B6: Información Usuarios | D6: Usuario 1 | E6: Usuario 2 | F6: Usuario 3 | G6: Usuario 4 | H6: Usuario 5 | I6: Usuario 6
B7: Tipo de documento | D7: =IF(Navegación!D7<>"",Navegación!D7,"") -> Cédula Ciudadanía | E7: =IF(Navegación!E7<>"",Navegación!E7,"") | F7: =IF(Navegación!F7<>"",Navegación!F7,"") | G7: =IF(Navegación!G7<>"",Navegación!G7,"") | H7: =IF(Navegación!H7<>"",Navegación!H7,"") | I7: =IF(Navegación!I7<>"",Navegación!I7,"")
B8: Identificación | D8: =IF(Navegación!D8<>"",Navegación!D8,"") -> 1001089595 | E8: =IF(Navegación!E8<>"",Navegación!E8,"") | F8: =IF(Navegación!F8<>"",Navegación!F8,"") | G8: =IF(Navegación!G8<>"",Navegación!G8,"") | H8: =IF(Navegación!H8<>"",Navegación!H8,"") | I8: =IF(Navegación!I8<>"",Navegación!I8,"")
B9: Nombres completos | D9: =IF(Navegación!D9<>"",Navegación!D9,"") -> JUAN PABLO | E9: =IF(Navegación!E9<>"",Navegación!E9,"") | F9: =IF(Navegación!F9<>"",Navegación!F9,"") | G9: =IF(Navegación!G9<>"",Navegación!G9,"") | H9: =IF(Navegación!H9<>"",Navegación!H9,"") | I9: =IF(Navegación!I9<>"",Navegación!I9,"")
B10: Apellidos completos | D10: =IF(Navegación!D10<>"",Navegación!D10,"") -> CAMPO TELLEZ | E10: =IF(Navegación!E10<>"",Navegación!E10,"") | F10: =IF(Navegación!F10<>"",Navegación!F10,"") | G10: =IF(Navegación!G10<>"",Navegación!G10,"") | H10: =IF(Navegación!H10<>"",Navegación!H10,"") | I10: =IF(Navegación!I10<>"",Navegación!I10,"")
B11: Centro de costo | D11: =IF(Navegación!D11<>"",Navegación!D11,"") -> 856 | E11: =IF(Navegación!E11<>"",Navegación!E11,"") | F11: =IF(Navegación!F11<>"",Navegación!F11,"") | G11: =IF(Navegación!G11<>"",Navegación!G11,"") | H11: =IF(Navegación!H11<>"",Navegación!H11,"") | I11: =IF(Navegación!I11<>"",Navegación!I11,"")
B12: Teléfono/Extensión de contacto del usuario | D12: =IF(Navegación!D12<>"",Navegación!D12,"") | E12: =IF(Navegación!E12<>"",Navegación!E12,"") | F12: =IF(Navegación!F12<>"",Navegación!F12,"") | G12: =IF(Navegación!G12<>"",Navegación!G12,"") | H12: =IF(Navegación!H12<>"",Navegación!H12,"") | I12: =IF(Navegación!I12<>"",Navegación!I12,"")
B13: Celular | D13: =IF(Navegación!D13<>"",Navegación!D13,"") -> 3150727969 | E13: =IF(Navegación!E13<>"",Navegación!E13,"") | F13: =IF(Navegación!F13<>"",Navegación!F13,"") | G13: =IF(Navegación!G13<>"",Navegación!G13,"") | H13: =IF(Navegación!H13<>"",Navegación!H13,"") | I13: =IF(Navegación!I13<>"",Navegación!I13,"")
B14: Dependencia | D14: =IF(Navegación!D14<>"",Navegación!D14,"") -> Gobierno | E14: =IF(Navegación!E14<>"",Navegación!E14,"") | F14: =IF(Navegación!F14<>"",Navegación!F14,"") | G14: =IF(Navegación!G14<>"",Navegación!G14,"") | H14: =IF(Navegación!H14<>"",Navegación!H14,"") | I14: =IF(Navegación!I14<>"",Navegación!I14,"")
B15: Cargo | D15: =IF(Navegación!D15<>"",Navegación!D15,"") -> Aprendiz Universitario | E15: =IF(Navegación!E15<>"",Navegación!E15,"") | F15: =IF(Navegación!F15<>"",Navegación!F15,"") | G15: =IF(Navegación!G15<>"",Navegación!G15,"") | H15: =IF(Navegación!H15<>"",Navegación!H15,"") | I15: =IF(Navegación!I15<>"",Navegación!I15,"")
B16: Empleado Cafam o Externo | D16: =IF(Navegación!D16<>"",Navegación!D16,"") -> Empleado CAFAM | E16: =IF(Navegación!E16<>"",Navegación!E16,"") | F16: =IF(Navegación!F16<>"",Navegación!F16,"") | G16: =IF(Navegación!G16<>"",Navegación!G16,"") | H16: =IF(Navegación!H16<>"",Navegación!H16,"") | I16: =IF(Navegación!I16<>"",Navegación!I16,"")
B17: Nombre de la empresa cuando es Externo | D17: =IF(Navegación!D17<>"",Navegación!D17,"") | E17: =IF(Navegación!E17<>"",Navegación!E17,"") | F17: =IF(Navegación!F17<>"",Navegación!F17,"") | G17: =IF(Navegación!G17<>"",Navegación!G17,"") | H17: =IF(Navegación!H17<>"",Navegación!H17,"") | I17: =IF(Navegación!I17<>"",Navegación!I17,"")
B18: Fecha inicio contrato: | D18: =IF(Navegación!D18<>"",Navegación!D18,"") -> 45849 | E18: =IF(Navegación!E18<>"",Navegación!E18,"") | F18: =IF(Navegación!F18<>"",Navegación!F18,"") | G18: =IF(Navegación!G18<>"",Navegación!G18,"") | H18: =IF(Navegación!H18<>"",Navegación!H18,"") | I18: =IF(Navegación!I18<>"",Navegación!I18,"")
B19: Fecha finalización contrato: (Si es indefinido escribir 31/12/9999) | D19: =IF(Navegación!D19<>"",Navegación!D19,"") | E19: =IF(Navegación!E19<>"",Navegación!E19,"") | F19: =IF(Navegación!F19<>"",Navegación!F19,"") | G19: =IF(Navegación!G19<>"",Navegación!G19,"") | H19: =IF(Navegación!H19<>"",Navegación!H19,"") | I19: =IF(Navegación!I19<>"",Navegación!I19,"")
B21: Requerimientos Office 365 | D21: =IF(OR(DZ23>0,DZ26>0),Navegación!$E$23,"")
B22: Sr. Usuario. Tenga en cuenta que la asignación de Licencia Office 365 puede acarrear costos adicionales para su CeCo. Si se trata de un reemplazo, indique el nombre de la persona que esta reemplazando, de lo contrario confirme con su jefatura la disponibilidad de licencia.
B23: Buzón de correo personal (Crear/Modificar/Baja) | DZ23: =COUNTIF(D23:I23,"<>") -> 0
B24: Tipo Licencia Office 365
B25: Nombre del buzón a modificar o dar de baja
B26: Buzón de correo del área (Crear/Modificar/Baja) | DZ26: =COUNTIF(D26:I26,"<>") -> 0
B27: Detalle del buzón de correo del área
B28: Power BI-Pro | DZ28: =COUNTIF(D28:I28,"<>") -> 0
B29: Generar Backup de la cuenta Office? | C29: Cuenta Origen | DZ29: =COUNTIF(D29:I30,"<>") -> 0
C30: Cuenta Destino
B32: Observaciones
B37: ='WINDOWS 1'!$B$37 -> APROBADOR POR: Jefe Dpto. Servicios Compartidos | F37: ='WINDOWS 1'!F37 -> V20 de 26/09/2023 | I37: ="Pág. " &Navegación!B23 & " de " &Navegación!$B$102 -> Pág. 3 de 54
DZ44: =COUNTIF(D23:I23,"<>") -> 0
DZ47: =COUNTIF(D26:I26,"<>") -> 0

Sheet SALUD 1
K1: 2958465
C2: FORMATO: GESTIÓN DE IDENTIDADES
F3: DOCUMENTO USO INTERNO
B5: Las celdas resaltadas en Naranja son campos obligatorios del Formato.
B6: Información Usuarios | D6: Usuario 1 | E6: Usuario 2 | F6: Usuario 3 | G6: Usuario 4 | H6: Usuario 5 | I6: Usuario 6
B7: Tipo de documento | D7: =IF(Navegación!D7<>"",Navegación!D7,"") -> Cédula Ciudadanía | E7: =IF(Navegación!E7<>"",Navegación!E7,"") | F7: =IF(Navegación!F7<>"",Navegación!F7,"") | G7: =IF(Navegación!G7<>"",Navegación!G7,"") | H7: =IF(Navegación!H7<>"",Navegación!H7,"") | I7: =IF(Navegación!I7<>"",Navegación!I7,"")
B8: Identificación | D8: =IF(Navegación!D8<>"",Navegación!D8,"") -> 1001089595 | E8: =IF(Navegación!E8<>"",Navegación!E8,"") | F8: =IF(Navegación!F8<>"",Navegación!F8,"") | G8: =IF(Navegación!G8<>"",Navegación!G8,"") | H8: =IF(Navegación!H8<>"",Navegación!H8,"") | I8: =IF(Navegación!I8<>"",Navegación!I8,"")
B9: Nombres completos | D9: =IF(Navegación!D9<>"",Navegación!D9,"") -> JUAN PABLO | E9: =IF(Navegación!E9<>"",Navegación!E9,"") | F9: =IF(Navegación!F9<>"",Navegación!F9,"") | G9: =IF(Navegación!G9<>"",Navegación!G9,"") | H9: =IF(Navegación!H9<>"",Navegación!H9,"") | I9: =IF(Navegación!I9<>"",Navegación!I9,"")
B10: Apellidos completos | D10: =IF(Navegación!D10<>"",Navegación!D10,"") -> CAMPO TELLEZ | E10: =IF(Navegación!E10<>"",Navegación!E10,"") | F10: =IF(Navegación!F10<>"",Navegación!F10,"") | G10: =IF(Navegación!G10<>"",Navegación!G10,"") | H10: =IF(Navegación!H10<>"",Navegación!H10,"") | I10: =IF(Navegación!I10<>"",Navegación!I10,"")
B11: Centro de costo | D11: =IF(Navegación!D11<>"",Navegación!D11,"") -> 856 | E11: =IF(Navegación!E11<>"",Navegación!E11,"") | F11: =IF(Navegación!F11<>"",Navegación!F11,"") | G11: =IF(Navegación!G11<>"",Navegación!G11,"") | H11: =IF(Navegación!H11<>"",Navegación!H11,"") | I11: =IF(Navegación!I11<>"",Navegación!I11,"")
B12: Teléfono/Extensión de contacto del usuario | D12: =IF(Navegación!D12<>"",Navegación!D12,"") | E12: =IF(Navegación!E12<>"",Navegación!E12,"") | F12: =IF(Navegación!F12<>"",Navegación!F12,"") | G12: =IF(Navegación!G12<>"",Navegación!G12,"") | H12: =IF(Navegación!H12<>"",Navegación!H12,"") | I12: =IF(Navegación!I12<>"",Navegación!I12,"")
B13: Celular | D13: =IF(Navegación!D13<>"",Navegación!D13,"") -> 3150727969 | E13: =IF(Navegación!E13<>"",Navegación!E13,"") | F13: =IF(Navegación!F13<>"",Navegación!F13,"") | G13: =IF(Navegación!G13<>"",Navegación!G13,"") | H13: =IF(Navegación!H13<>"",Navegación!H13,"") | I13: =IF(Navegación!I13<>"",Navegación!I13,"")
B14: Dependencia | D14: =IF(Navegación!D14<>"",Navegación!D14,"") -> Gobierno | E14: =IF(Navegación!E14<>"",Navegación!E14,"") | F14: =IF(Navegación!F14<>"",Navegación!F14,"") | G14: =IF(Navegación!G14<>"",Navegación!G14,"") | H14: =IF(Navegación!H14<>"",Navegación!H14,"") | I14: =IF(Navegación!I14<>"",Navegación!I14,"")
B15: Cargo | D15: =IF(Navegación!D15<>"",Navegación!D15,"") -> Aprendiz Universitario | E15: =IF(Navegación!E15<>"",Navegación!E15,"") | F15: =IF(Navegación!F15<>"",Navegación!F15,"") | G15: =IF(Navegación!G15<>"",Navegación!G15,"") | H15: =IF(Navegación!H15<>"",Navegación!H15,"") | I15: =IF(Navegación!I15<>"",Navegación!I15,"")
B16: Empleado Cafam o Externo | D16: =IF(Navegación!D16<>"",Navegación!D16,"") -> Empleado CAFAM | E16: =IF(Navegación!E16<>"",Navegación!E16,"") | F16: =IF(Navegación!F16<>"",Navegación!F16,"") | G16: =IF(Navegación!G16<>"",Navegación!G16,"") | H16: =IF(Navegación!H16<>"",Navegación!H16,"") | I16: =IF(Navegación!I16<>"",Navegación!I16,"")
B17: Nombre de la empresa cuando es Externo | D17: =IF(Navegación!D17<>"",Navegación!D17,"") | E17: =IF(Navegación!E17<>"",Navegación!E17,"") | F17: =IF(Navegación!F17<>"",Navegación!F17,"") | G17: =IF(Navegación!G17<>"",Navegación!G17,"") | H17: =IF(Navegación!H17<>"",Navegación!H17,"") | I17: =IF(Navegación!I17<>"",Navegación!I17,"")
B18: Fecha inicio contrato: | D18: =IF(Navegación!D18<>"",Navegación!D18,"") -> 45849 | E18: =IF(Navegación!E18<>"",Navegación!E18,"") | F18: =IF(Navegación!F18<>"",Navegación!F18,"") | G18: =IF(Navegación!G18<>"",Navegación!G18,"") | H18: =IF(Navegación!H18<>"",Navegación!H18,"") | I18: =IF(Navegación!I18<>"",Navegación!I18,"")
B19: Fecha finalización contrato: (Si es indefinido escribir 31.12.9999) | D19: =IF(Navegación!D19<>"",Navegación!D19,"") | E19: =IF(Navegación!E19<>"",Navegación!E19,"") | F19: =IF(Navegación!F19<>"",Navegación!F19,"") | G19: =IF(Navegación!G19<>"",Navegación!G19,"") | H19: =IF(Navegación!H19<>"",Navegación!H19,"") | I19: =IF(Navegación!I19<>"",Navegación!I19,"")
B21: PANA - FAMISANAR | D21: =IF(DZ26>0,Navegación!$E$26,"")
D22: =ADDRESS(MATCH(D$28,SaludSedes1[[#All],[EPS]],0)+252,13,1) -> $M$254 | E22: =ADDRESS(MATCH(E$28,SaludSedes1[[#All],[EPS]],0)+252,13,1) -> $M$254 | F22: =ADDRESS(MATCH(F$28,SaludSedes1[[#All],[EPS]],0)+252,13,1) -> $M$254 | G22: =ADDRESS(MATCH(G$28,SaludSedes1[[#All],[EPS]],0)+252,13,1) -> $M$254 | H22: =ADDRESS(MATCH(H$28,SaludSedes1[[#All],[EPS]],0)+252,13,1) -> $M$254 | I22: =ADDRESS(MATCH(I$28,SaludSedes1[[#All],[EPS]],0)+252,13,1) -> $M$254
D23: =ADDRESS(MATCH(D$28,SaludTipoPerfil1[[#All],[Aplicacion]],0)+252,16,1) -> $P$254 | E23: =ADDRESS(MATCH(E$28,SaludTipoPerfil1[[#All],[Aplicacion]],0)+252,16,1) -> $P$254 | F23: =ADDRESS(MATCH(F$28,SaludTipoPerfil1[[#All],[Aplicacion]],0)+252,16,1) -> $P$254 | G23: =ADDRESS(MATCH(G$28,SaludTipoPerfil1[[#All],[Aplicacion]],0)+252,16,1) -> $P$254 | H23: =ADDRESS(MATCH(H$28,SaludTipoPerfil1[[#All],[Aplicacion]],0)+252,16,1) -> $P$254 | I23: =ADDRESS(MATCH(I$28,SaludTipoPerfil1[[#All],[Aplicacion]],0)+252,16,1) -> $P$254
D24: =ADDRESS(MATCH(D$27,SaludPerfiles1[[#All],[TipoPerfil]],0)+251,20,1) -> #N/A | E24: =ADDRESS(MATCH(E$27,SaludPerfiles1[[#All],[TipoPerfil]],0)+251,20,1) -> #N/A | F24: =ADDRESS(MATCH(F$27,SaludPerfiles1[[#All],[TipoPerfil]],0)+251,20,1) -> #N/A | G24: =ADDRESS(MATCH(G$27,SaludPerfiles1[[#All],[TipoPerfil]],0)+251,20,1) -> #N/A | H24: =ADDRESS(MATCH(H$27,SaludPerfiles1[[#All],[TipoPerfil]],0)+251,20,1) -> #N/A | I24: =ADDRESS(MATCH(I$27,SaludPerfiles1[[#All],[TipoPerfil]],0)+251,20,1) -> #N/A
D25: =ADDRESS(MATCH(D$28&" "&D$32,SaludEspecialidades1[[#All],[Sistema]],0)+251,23,1) -> #N/A | E25: =ADDRESS(MATCH(E$28&" "&E$32,SaludEspecialidades1[[#All],[Sistema]],0)+251,23,1) -> #N/A | F25: =ADDRESS(MATCH(F$28&" "&F$32,SaludEspecialidades1[[#All],[Sistema]],0)+251,23,1) -> #N/A | G25: =ADDRESS(MATCH(G$28&" "&G$32,SaludEspecialidades1[[#All],[Sistema]],0)+251,23,1) -> #N/A | H25: =ADDRESS(MATCH(H$28&" "&H$32,SaludEspecialidades1[[#All],[Sistema]],0)+251,23,1) -> #N/A | I25: =ADDRESS(MATCH(I$28&" "&I$32,SaludEspecialidades1[[#All],[Sistema]],0)+251,23,1) -> #N/A
B26: Novedad (Crear/Inactivar): | DZ26: =COUNTIF(D26:I26,"<>") -> 0
B27: Tipo de Perfil
B28: EPS | D28: PANA-FAMISANAR | E28: PANA-FAMISANAR | F28: PANA-FAMISANAR | G28: PANA-FAMISANAR | H28: PANA-FAMISANAR | I28: PANA-FAMISANAR
B29: Sede
B30: Alias usuario
B31: Registro profesional
B32: Perfil
B33: Especialidad
B34: Dirección
B35: Celular/Telefono
B36: Información RETHUS
B37: Tipo Programa
B38: Origen Obtención
B39: Titulo Profesional
B40: Entidad Reportadora
B41: Fecha consulta RETHUS
DZ42: =COUNTIF(#REF!,"<>") -> #REF!
B43: Observaciones
B48: ='WINDOWS 1'!$B$37 -> APROBADOR POR: Jefe Dpto. Servicios Compartidos | F48: ='WINDOWS 1'!F37 -> V20 de 26/09/2023 | I48: ="Pág. " &Navegación!B26 & " de " &Navegación!$B$102 -> Pág. 4 de 54
DZ51: =COUNTIF(#REF!,"<>") -> #REF!
DZ58: =COUNTIF(#REF!,"<>") -> #REF!
DZ62: =COUNTIF(#REF!,"<>") -> #REF!
DZ72: =COUNTIF(#REF!,"<>") -> #REF!
DZ82: =COUNTIF(#REF!,"<>") -> #REF!
DZ88: =COUNTIF(#REF!,"<>") -> #REF!
DZ92: =COUNTIF(#REF!,"<>") -> #REF!
DZ96: =COUNTIF(#REF!,"<>") -> #REF!
DZ102: =COUNTIF(#REF!,"<>") -> #REF!
DZ106: =COUNTIF(#REF!,"<>") -> #REF!
DZ110: =COUNTIF(#REF!,"<>") -> #REF!
L252: EPS | M252: IPS | O252: Aplicacion | P252: TipoPerfil | R252: Aplicacion | S252: TipoPerfil | T252: Perfil | V252: Sistema | W252: Especialidad
L253: PANA-FAMISANAR | M253: Barranquilla | O253: PANA-FAMISANAR | P253: Administrativo | R253: PANA-FAMISANAR | S253: Administrativo | T253: AG - AGENDAMIENTO | V253: PANA-FAMISANAR Medico Especialista | W253: Alergologia (5)
L254: PANA-FAMISANAR | M254: Cajicá | O254: PANA-FAMISANAR | P254: Profesional | R254: PANA-FAMISANAR | S254: Administrativo | T254: CB - CUADRE DE CAJA | V254: PANA-FAMISANAR Medico Especialista | W254: Anestesiologia (10)
L255: PANA-FAMISANAR | M255: Calle 127 | R255: PANA-FAMISANAR | S255: Administrativo | T255: CC - CALL CENTER | V255: PANA-FAMISANAR Medico Especialista | W255: Cardiologia (20)
L256: PANA-FAMISANAR | M256: Calle 48 | R256: PANA-FAMISANAR | S256: Administrativo | T256: CM - COORDINACIÓN MEDICA | V256: PANA-FAMISANAR Medico Especialista | W256: Cardiologia Pediatrica (25)
L257: PANA-FAMISANAR | M257: Calle 51 | R257: PANA-FAMISANAR | S257: Administrativo | T257: CT - CONTRATACION | V257: PANA-FAMISANAR Medico Especialista | W257: Cirugia Cardiovascular (30)
L258: PANA-FAMISANAR | M258: Calle 90 | R258: PANA-FAMISANAR | S258: Administrativo | T258: DI - DIRECTOR IPS AMBULATORIO | V258: PANA-FAMISANAR Medico Especialista | W258: Cirugia Cardiovascular Pediatrica (32)
L259: PANA-FAMISANAR | M259: Cartagena - Arsenal | R259: PANA-FAMISANAR | S259: Administrativo | T259: EM-ADMINISTRACION EQUIPOS MEDICOS | V259: PANA-FAMISANAR Medico Especialista | W259: Cirugia de Cabeza Y Cuello (27)
L260: PANA-FAMISANAR | M260: Cartagena - Cuatro Vientos | R260: PANA-FAMISANAR | S260: Administrativo | T260: ES - ESTADÍSTICA | V260: PANA-FAMISANAR Medico Especialista | W260: Cirugia de la Mano (67)
L261: PANA-FAMISANAR | M261: CC Gran Estacion | R261: PANA-FAMISANAR | S261: Administrativo | T261: RE - Servicio al Cliente (Recaudo) | V261: PANA-FAMISANAR Medico Especialista | W261: Cirugia de Mama y Tumores de Tejido (64)
L262: PANA-FAMISANAR | M262: Centenario | R262: PANA-FAMISANAR | S262: Administrativo | T262: SC - SERVICIO AL CLIENTE | V262: PANA-FAMISANAR Medico Especialista | W262: Cirugia de Torax (40)
L263: PANA-FAMISANAR | M263: Centro | R263: PANA-FAMISANAR | S263: Profesional | T263: Auditoria Medica | V263: PANA-FAMISANAR Medico Especialista | W263: Cirugia General (50)
L264: PANA-FAMISANAR | M264: Chía | R264: PANA-FAMISANAR | S264: Profesional | T264: Auxiliar Enfermeria | V264: PANA-FAMISANAR Medico Especialista | W264: Cirugia Infantil o Pediatrica (60)
L265: PANA-FAMISANAR | M265: Clínica Cafam | R265: PANA-FAMISANAR | S265: Profesional | T265: Enfermera | V265: PANA-FAMISANAR Medico Especialista | W265: Cirugia Oncologica (350)
L266: PANA-FAMISANAR | M266: Clínica Cafam Calle 93 | R266: PANA-FAMISANAR | S266: Profesional | T266: Higiene Oral / Auxiliar | V266: PANA-FAMISANAR Medico Especialista | W266: Cirugia Oral (827)
... L271: PANA-FAMISANAR | M271: Facatativá | R271: PANA-FAMISANAR | S271: Profesional | T271: Otros Profesionales | V271: PANA-FAMISANAR Medico Especialista | W271: Dermatología Pediatrica (82)
L272: PANA-FAMISANAR | M272: Floresta | V272: PANA-FAMISANAR Medico Especialista | W272: Dolor y Cuidados Paliativos (400)
L273: PANA-FAMISANAR | M273: Fund. Univ. Cafam FLORESTA | V273: PANA-FAMISANAR Medico Especialista | W273: Electrofisiología (85)
L274: PANA-FAMISANAR | M274: Girardot | V274: PANA-FAMISANAR Medico Especialista | W274: Endocrinología (90)
L275: PANA-FAMISANAR | M275: Kennedy | V275: PANA-FAMISANAR Medico Especialista | W275: Endocrinología Pediatrica (92)
L276: PANA-FAMISANAR | M276: La Castellana | V276: PANA-FAMISANAR Medico Especialista | W276: Epidemiologia (100)
L277: PANA-FAMISANAR | M277: Madrid | V277: PANA-FAMISANAR Medico Especialista | W277: Estomatologia (105)
L278: PANA-FAMISANAR | M278: Melgar | V278: PANA-FAMISANAR Medico Especialista | W278: Gastroenterologia (110)
L279: PANA-FAMISANAR | M279: Neiva Centro | V279: PANA-FAMISANAR Medico Especialista | W279: Gastroenterologia Oncologica (115)
L280: PANA-FAMISANAR | M280: Neiva San Jorge | V280: PANA-FAMISANAR Medico Especialista | W280: Gastroenterologia Pediatrica (112)
L281: PANA-FAMISANAR | M281: Prioritaria Floresta | V281: PANA-FAMISANAR Medico Especialista | W281: Genetica (118)
L282: PANA-FAMISANAR | M282: Prioritaria Suba | V282: PANA-FAMISANAR Medico Especialista | W282: Geriatrica Clinica (120)
L283: PANA-FAMISANAR | M283: Quirigua | V283: PANA-FAMISANAR Medico Especialista | W283: Gerontologia (125)
... L288: PANA-FAMISANAR | M288: Valledupar | V288: PANA-FAMISANAR Medico Especialista | W288: Hematologia Pediatrica (332)
V289: PANA-FAMISANAR Medico Especialista | W289: Hepatologia (137)
V290: PANA-FAMISANAR Medico Especialista | W290: Infectologia (135)
V291: PANA-FAMISANAR Medico Especialista | W291: Infectologia Pediatrica (136)
V292: PANA-FAMISANAR Medico Especialista | W292: Inmunologia (139)
V293: PANA-FAMISANAR Medico Especialista | W293: Medicina Alternativa (750)
V294: PANA-FAMISANAR Medico Especialista | W294: Medicina Alternativa (Ayurveda)
V295: PANA-FAMISANAR Medico Especialista | W295: Medicina Alternativa (Homeopatica)
V296: PANA-FAMISANAR Medico Especialista | W296: Medicina Alternativa (Naturopatia)
V297: PANA-FAMISANAR Medico Especialista | W297: Medicina Alternativa (Neuralerapeutica)
V298: PANA-FAMISANAR Medico Especialista | W298: Medicina Alternativa (Osteopatica)
V299: PANA-FAMISANAR Medico Especialista | W299: Medicina Alternativa (radicional China)
V300: PANA-FAMISANAR Medico Especialista | W300: Medicina del Ejercicio (140)
... V357: PANA-FAMISANAR Otros Profesionales | W357: Trabajo Social

Sheet SALUD 2
K1: 2958465
C2: FORMATO: GESTIÓN DE IDENTIDADES
F3: DOCUMENTO USO INTERNO
B5: Las celdas resaltadas en Naranja son campos obligatorios del Formato.
B6: Información Usuarios | D6: Usuario 1 | E6: Usuario 2 | F6: Usuario 3 | G6: Usuario 4 | H6: Usuario 5 | I6: Usuario 6
B7: Tipo de documento | D7: =IF(Navegación!D7<>"",Navegación!D7,"") -> Cédula Ciudadanía | E7: =IF(Navegación!E7<>"",Navegación!E7,"") | F7: =IF(Navegación!F7<>"",Navegación!F7,"") | G7: =IF(Navegación!G7<>"",Navegación!G7,"") | H7: =IF(Navegación!H7<>"",Navegación!H7,"") | I7: =IF(Navegación!I7<>"",Navegación!I7,"")
B8: Identificación | D8: =IF(Navegación!D8<>"",Navegación!D8,"") -> 1001089595 | E8: =IF(Navegación!E8<>"",Navegación!E8,"") | F8: =IF(Navegación!F8<>"",Navegación!F8,"") | G8: =IF(Navegación!G8<>"",Navegación!G8,"") | H8: =IF(Navegación!H8<>"",Navegación!H8,"") | I8: =IF(Navegación!I8<>"",Navegación!I8,"")
B9: Nombres completos | D9: =IF(Navegación!D9<>"",Navegación!D9,"") -> JUAN PABLO | E9: =IF(Navegación!E9<>"",Navegación!E9,"") | F9: =IF(Navegación!F9<>"",Navegación!F9,"") | G9: =IF(Navegación!G9<>"",Navegación!G9,"") | H9: =IF(Navegación!H9<>"",Navegación!H9,"") | I9: =IF(Navegación!I9<>"",Navegación!I9,"")
B10: Apellidos completos | D10: =IF(Navegación!D10<>"",Navegación!D10,"") -> CAMPO TELLEZ | E10: =IF(Navegación!E10<>"",Navegación!E10,"") | F10: =IF(Navegación!F10<>"",Navegación!F10,"") | G10: =IF(Navegación!G10<>"",Navegación!G10,"") | H10: =IF(Navegación!H10<>"",Navegación!H10,"") | I10: =IF(Navegación!I10<>"",Navegación!I10,"")
B11: Centro de costo | D11: =IF(Navegación!D11<>"",Navegación!D11,"") -> 856 | E11: =IF(Navegación!E11<>"",Navegación!E11,"") | F11: =IF(Navegación!F11<>"",Navegación!F11,"") | G11: =IF(Navegación!G11<>"",Navegación!G11,"") | H11: =IF(Navegación!H11<>"",Navegación!H11,"") | I11: =IF(Navegación!I11<>"",Navegación!I11,"")
B12: Teléfono/Extensión de contacto del usuario | D12: =IF(Navegación!D12<>"",Navegación!D12,"") | E12: =IF(Navegación!E12<>"",Navegación!E12,"") | F12: =IF(Navegación!F12<>"",Navegación!F12,"") | G12: =IF(Navegación!G12<>"",Navegación!G12,"") | H12: =IF(Navegación!H12<>"",Navegación!H12,"") | I12: =IF(Navegación!I12<>"",Navegación!I12,"")
B13: Celular | D13: =IF(Navegación!D13<>"",Navegación!D13,"") -> 3150727969 | E13: =IF(Navegación!E13<>"",Navegación!E13,"") | F13: =IF(Navegación!F13<>"",Navegación!F13,"") | G13: =IF(Navegación!G13<>"",Navegación!G13,"") | H13: =IF(Navegación!H13<>"",Navegación!H13,"") | I13: =IF(Navegación!I13<>"",Navegación!I13,"")
B14: Dependencia | D14: =IF(Navegación!D14<>"",Navegación!D14,"") -> Gobierno | E14: =IF(Navegación!E14<>"",Navegación!E14,"") | F14: =IF(Navegación!F14<>"",Navegación!F14,"") | G14: =IF(Navegación!G14<>"",Navegación!G14,"") | H14: =IF(Navegación!H14<>"",Navegación!H14,"") | I14: =IF(Navegación!I14<>"",Navegación!I14,"")
B15: Cargo | D15: =IF(Navegación!D15<>"",Navegación!D15,"") -> Aprendiz Universitario | E15: =IF(Navegación!E15<>"",Navegación!E15,"") | F15: =IF(Navegación!F15<>"",Navegación!F15,"") | G15: =IF(Navegación!G15<>"",Navegación!G15,"") | H15: =IF(Navegación!H15<>"",Navegación!H15,"") | I15: =IF(Navegación!I15<>"",Navegación!I15,"")
B16: Empleado Cafam o Externo | D16: =IF(Navegación!D16<>"",Navegación!D16,"") -> Empleado CAFAM | E16: =IF(Navegación!E16<>"",Navegación!E16,"") | F16: =IF(Navegación!F16<>"",Navegación!F16,"") | G16: =IF(Navegación!G16<>"",Navegación!G16,"") | H16: =IF(Navegación!H16<>"",Navegación!H16,"") | I16: =IF(Navegación!I16<>"",Navegación!I16,"")
B17: Nombre de la empresa cuando es Externo | D17: =IF(Navegación!D17<>"",Navegación!D17,"") | E17: =IF(Navegación!E17<>"",Navegación!E17,"") | F17: =IF(Navegación!F17<>"",Navegación!F17,"") | G17: =IF(Navegación!G17<>"",Navegación!G17,"") | H17: =IF(Navegación!H17<>"",Navegación!H17,"") | I17: =IF(Navegación!I17<>"",Navegación!I17,"")
B18: Fecha inicio contrato: | D18: =IF(Navegación!D18<>"",Navegación!D18,"") -> 45849 | E18: =IF(Navegación!E18<>"",Navegación!E18,"") | F18: =IF(Navegación!F18<>"",Navegación!F18,"") | G18: =IF(Navegación!G18<>"",Navegación!G18,"") | H18: =IF(Navegación!H18<>"",Navegación!H18,"") | I18: =IF(Navegación!I18<>"",Navegación!I18,"")
B19: Fecha finalización contrato: (Si es indefinido escribir 31.12.9999) | D19: =IF(Navegación!D19<>"",Navegación!D19,"") | E19: =IF(Navegación!E19<>"",Navegación!E19,"") | F19: =IF(Navegación!F19<>"",Navegación!F19,"") | G19: =IF(Navegación!G19<>"",Navegación!G19,"") | H19: =IF(Navegación!H19<>"",Navegación!H19,"") | I19: =IF(Navegación!I19<>"",Navegación!I19,"")
B21: PANA - NEPS | D21: =IF(DZ25>0,Navegación!$E$27,"")
D22: =ADDRESS(MATCH(D$28,SaludSedes2[[#All],[EPS]],0)+252,13,1) -> #N/A | E22: =ADDRESS(MATCH(E$28,SaludSedes2[[#All],[EPS]],0)+252,13,1) -> #N/A | F22: =ADDRESS(MATCH(F$28,SaludSedes2[[#All],[EPS]],0)+252,13,1) -> #N/A | G22: =ADDRESS(MATCH(G$28,SaludSedes2[[#All],[EPS]],0)+252,13,1) -> #N/A | H22: =ADDRESS(MATCH(H$28,SaludSedes2[[#All],[EPS]],0)+252,13,1) -> #N/A | I22: =ADDRESS(MATCH(I$28,SaludSedes2[[#All],[EPS]],0)+252,13,1) -> #N/A
D23: =ADDRESS(MATCH(D$28,SaludTipoPerfil2[[#All],[Aplicacion]],0)+252,16,1) -> #N/A | E23: =ADDRESS(MATCH(E$28,SaludTipoPerfil2[[#All],[Aplicacion]],0)+252,16,1) -> #N/A | F23: =ADDRESS(MATCH(F$28,SaludTipoPerfil2[[#All],[Aplicacion]],0)+252,16,1) -> #N/A | G23: =ADDRESS(MATCH(G$28,SaludTipoPerfil2[[#All],[Aplicacion]],0)+252,16,1) -> #N/A | H23: =ADDRESS(MATCH(H$28,SaludTipoPerfil2[[#All],[Aplicacion]],0)+252,16,1) -> #N/A | I23: =ADDRESS(MATCH(I$28,SaludTipoPerfil2[[#All],[Aplicacion]],0)+252,16,1) -> #N/A
D24: =ADDRESS(MATCH(D$27,SaludPerfiles2[[#All],[TipoPerfil]],0)+251,20,1) -> #N/A | E24: =ADDRESS(MATCH(E$27,SaludPerfiles2[[#All],[TipoPerfil]],0)+251,20,1) -> #N/A | F24: =ADDRESS(MATCH(F$27,SaludPerfiles2[[#All],[TipoPerfil]],0)+251,20,1) -> #N/A | G24: =ADDRESS(MATCH(G$27,SaludPerfiles2[[#All],[TipoPerfil]],0)+251,20,1) -> #N/A | H24: =ADDRESS(MATCH(H$27,SaludPerfiles2[[#All],[TipoPerfil]],0)+251,20,1) -> #N/A | I24: =ADDRESS(MATCH(I$27,SaludPerfiles2[[#All],[TipoPerfil]],0)+251,20,1) -> #N/A
D25: =ADDRESS(MATCH(D$28&" "&D$32,SaludEspecialidades2[[#All],[Sistema]],0)+251,23,1) -> #N/A | E25: =ADDRESS(MATCH(E$28&" "&E$32,SaludEspecialidades2[[#All],[Sistema]],0)+251,23,1) -> #N/A | F25: =ADDRESS(MATCH(F$28&" "&F$32,SaludEspecialidades2[[#All],[Sistema]],0)+251,23,1) -> #N/A | G25: =ADDRESS(MATCH(G$28&" "&G$32,SaludEspecialidades2[[#All],[Sistema]],0)+251,23,1) -> #N/A | H25: =ADDRESS(MATCH(H$28&" "&H$32,SaludEspecialidades2[[#All],[Sistema]],0)+251,23,1) -> #N/A | I25: =ADDRESS(MATCH(I$28&" "&I$32,SaludEspecialidades2[[#All],[Sistema]],0)+251,23,1) -> #N/A | DZ25: =COUNTIF(D26:I26,"<>") -> 0
B26: Novedad (Crear/Inactivar): | DZ26: =COUNTIF(#REF!,"<>") -> #REF!
B27: Tipo de Perfil
B28: EPS
B29: Sede
B30: Alias usuario
B31: Registro profesional
B32: Perfil
B33: Especialidad
B34: Información RETHUS
B35: Tipo Programa
B36: Origen Obtención
B37: Titulo Profesional
B38: Entidad Reportadora
... B41: Observaciones
B46: ='WINDOWS 1'!$B$37 -> APROBADOR POR: Jefe Dpto. Servicios Compartidos | F46: ='WINDOWS 1'!F37 -> V20 de 26/09/2023 | I46: ="Pág. " &Navegación!B27 & " de " &Navegación!$B$102 -> Pág. 5 de 54
DZ51: =COUNTIF(D35:I35,"<>") -> 0
DZ58: =COUNTIF(#REF!,"<>") -> #REF!
DZ62: =COUNTIF(#REF!,"<>") -> #REF!
DZ72: =COUNTIF(#REF!,"<>") -> #REF!
DZ82: =COUNTIF(#REF!,"<>") -> #REF!
DZ88: =COUNTIF(#REF!,"<>") -> #REF!
DZ92: =COUNTIF(#REF!,"<>") -> #REF!
DZ96: =COUNTIF(#REF!,"<>") -> #REF!
DZ102: =COUNTIF(#REF!,"<>") -> #REF!
DZ106: =COUNTIF(#REF!,"<>") -> #REF!
DZ110: =COUNTIF(#REF!,"<>") -> #REF!
L252: EPS | M252: IPS | O252: Aplicacion | P252: TipoPerfil | R252: Aplicacion | S252: TipoPerfil | T252: Perfil | V252: Sistema | W252: Especialidad
L253: PANA-NEPS | M253: Calle 51 | O253: PANA-NEPS | P253: Administrativo | R253: PANA-NEPS | S253: Administrativo | T253: AG - Usuarios Agendamiento | V253: PANA-NEPS Medico Especialista | W253: Alergologia
L254: PANA-NEPS | M254: Calle 90 | O254: PANA-NEPS | P254: Profesional | R254: PANA-NEPS | S254: Administrativo | T254: AS - CT Asegurador | V254: PANA-NEPS Medico Especialista | W254: Anestesiologia
L255: PANA-NEPS | M255: Calle48 | R255: PANA-NEPS | S255: Administrativo | T255: CB - Cuadre de Caja | V255: PANA-NEPS Medico Especialista | W255: Cardiologia
L256: PANA-NEPS | M256: Centenario | R256: PANA-NEPS | S256: Administrativo | T256: CC -Call Center | V256: PANA-NEPS Medico Especialista | W256: Cardiologia Pediatrica
L257: PANA-NEPS | M257: Floresta | R257: PANA-NEPS | S257: Administrativo | T257: CM - Coordinación Medica | V257: PANA-NEPS Medico Especialista | W257: Cirugia Cardiovascular
L258: PANA-NEPS | M258: Granada Hills | R258: PANA-NEPS | S258: Administrativo | T258: CT - Contratación | V258: PANA-NEPS Medico Especialista | W258: Cirugia Cardiovascular Pediatrica
L259: PANA-NEPS | M259: La Castellana | R259: PANA-NEPS | S259: Administrativo | T259: EM - Admin Equipos Medicos | V259: PANA-NEPS Medico Especialista | W259: Cirugia de Cabeza Y Cuello
R260: PANA-NEPS | S260: Administrativo | T260: ES - Estadistica | V260: PANA-NEPS Medico Especialista | W260: Cirugia de la Mano
R261: PANA-NEPS | S261: Administrativo | T261: SC - Servicio al Cliente | V261: PANA-NEPS Medico Especialista | W261: Cirugia de Mama y Tumores de Tejido
R262: PANA-NEPS | S262: Administrativo | T262: DI - Directori IPS Ambulatorio | V262: PANA-NEPS Medico Especialista | W262: Cirugia de Torax
R263: PANA-NEPS | S263: Administrativo | T263: RE - Servicio al Cliente (Recaudo) | V263: PANA-NEPS Medico Especialista | W263: Cirugia General
R264: PANA-NEPS | S264: Profesional | T264: Auxiliar Enfermeria | V264: PANA-NEPS Medico Especialista | W264: Cirugia Infantil o Pediatrica
R265: PANA-NEPS | S265: Profesional | T265: Enfermera | V265: PANA-NEPS Medico Especialista | W265: Cirugia Oncologica
R266: PANA-NEPS | S266: Profesional | T266: Higienista Oral /Auxiliar | V266: PANA-NEPS Medico Especialista | W266: Cirugia Plastica
R267: PANA-NEPS | S267: Profesional | T267: Impresion | V267: PANA-NEPS Medico Especialista | W267: Cirugia Vascular Periferica
R268: PANA-NEPS | S268: Profesional | T268: Medico General | V268: PANA-NEPS Medico Especialista | W268: Dermatología
R269: PANA-NEPS | S269: Profesional | T269: Medico Especialista | V269: PANA-NEPS Medico Especialista | W269: Dermatología Pediatrica
R270: PANA-NEPS | S270: Profesional | T270: Odontologo | V270: PANA-NEPS Medico Especialista | W270: Dolor y Cuidados Paliativos
R271: PANA-NEPS | S271: Profesional | T271: Otros Profesionales | V271: PANA-NEPS Medico Especialista | W271: Electrofisiología
V272: PANA-NEPS Medico Especialista | W272: Endocrinología
V273: PANA-NEPS Medico Especialista | W273: Endocrinología Pediatrica
V274: PANA-NEPS Medico Especialista | W274: Epidemiologia
V275: PANA-NEPS Medico Especialista | W275: Estomatologia
V276: PANA-NEPS Medico Especialista | W276: Gastroenterologia
V277: PANA-NEPS Medico Especialista | W277: Gastroenterologia Oncologica
V278: PANA-NEPS Medico Especialista | W278: Gastroenterologia Pediatrica
V279: PANA-NEPS Medico Especialista | W279: Genetica
V280: PANA-NEPS Medico Especialista | W280: Geriatrica Clinica
V281: PANA-NEPS Medico Especialista | W281: Gerontologia
V282: PANA-NEPS Medico Especialista | W282: Ginecologia Oncologica
V283: PANA-NEPS Medico Especialista | W283: Ginecologia y Obstetricia
... V354: PANA-NEPS Otros Profesionales | W354: Trabajo Social

Sheet SALUD 3
K1: 2958465
C2: FORMATO: GESTIÓN DE IDENTIDADES
F3: DOCUMENTO USO INTERNO
B5: Las celdas resaltadas en Naranja son campos obligatorios del Formato.
B6: Información Usuarios | D6: Usuario 1 | E6: Usuario 2 | F6: Usuario 3 | G6: Usuario 4 | H6: Usuario 5 | I6: Usuario 6
B7: Tipo de documento | D7: =IF(Navegación!D7<>"",Navegación!D7,"") -> Cédula Ciudadanía | E7: =IF(Navegación!E7<>"",Navegación!E7,"") | F7: =IF(Navegación!F7<>"",Navegación!F7,"") | G7: =IF(Navegación!G7<>"",Navegación!G7,"") | H7: =IF(Navegación!H7<>"",Navegación!H7,"") | I7: =IF(Navegación!I7<>"",Navegación!I7,"")
B8: Identificación | D8: =IF(Navegación!D8<>"",Navegación!D8,"") -> 1001089595 | E8: =IF(Navegación!E8<>"",Navegación!E8,"") | F8: =IF(Navegación!F8<>"",Navegación!F8,"") | G8: =IF(Navegación!G8<>"",Navegación!G8,"") | H8: =IF(Navegación!H8<>"",Navegación!H8,"") | I8: =IF(Navegación!I8<>"",Navegación!I8,"")
B9: Nombres completos | D9: =IF(Navegación!D9<>"",Navegación!D9,"") -> JUAN PABLO | E9: =IF(Navegación!E9<>"",Navegación!E9,"") | F9: =IF(Navegación!F9<>"",Navegación!F9,"") | G9: =IF(Navegación!G9<>"",Navegación!G9,"") | H9: =IF(Navegación!H9<>"",Navegación!H9,"") | I9: =IF(Navegación!I9<>"",Navegación!I9,"")
B10: Apellidos completos | D10: =IF(Navegación!D10<>"",Navegación!D10,"") -> CAMPO TELLEZ | E10: =IF(Navegación!E10<>"",Navegación!E10,"") | F10: =IF(Navegación!F10<>"",Navegación!F10,"") | G10: =IF(Navegación!G10<>"",Navegación!G10,"") | H10: =IF(Navegación!H10<>"",Navegación!H10,"") | I10: =IF(Navegación!I10<>"",Navegación!I10,"")
B11: Centro de costo | D11: =IF(Navegación!D11<>"",Navegación!D11,"") -> 856 | E11: =IF(Navegación!E11<>"",Navegación!E11,"") | F11: =IF(Navegación!F11<>"",Navegación!F11,"") | G11: =IF(Navegación!G11<>"",Navegación!G11,"") | H11: =IF(Navegación!H11<>"",Navegación!H11,"") | I11: =IF(Navegación!I11<>"",Navegación!I11,"")
B12: Teléfono/Extensión de contacto del usuario | D12: =IF(Navegación!D12<>"",Navegación!D12,"") | E12: =IF(Navegación!E12<>"",Navegación!E12,"") | F12: =IF(Navegación!F12<>"",Navegación!F12,"") | G12: =IF(Navegación!G12<>"",Navegación!G12,"") | H12: =IF(Navegación!H12<>"",Navegación!H12,"") | I12: =IF(Navegación!I12<>"",Navegación!I12,"")
B13: Celular | D13: =IF(Navegación!D13<>"",Navegación!D13,"") -> 3150727969 | E13: =IF(Navegación!E13<>"",Navegación!E13,"") | F13: =IF(Navegación!F13<>"",Navegación!F13,"") | G13: =IF(Navegación!G13<>"",Navegación!G13,"") | H13: =IF(Navegación!H13<>"",Navegación!H13,"") | I13: =IF(Navegación!I13<>"",Navegación!I13,"")
B14: Dependencia | D14: =IF(Navegación!D14<>"",Navegación!D14,"") -> Gobierno | E14: =IF(Navegación!E14<>"",Navegación!E14,"") | F14: =IF(Navegación!F14<>"",Navegación!F14,"") | G14: =IF(Navegación!G14<>"",Navegación!G14,"") | H14: =IF(Navegación!H14<>"",Navegación!H14,"") | I14: =IF(Navegación!I14<>"",Navegación!I14,"")
B15: Cargo | D15: =IF(Navegación!D15<>"",Navegación!D15,"") -> Aprendiz Universitario | E15: =IF(Navegación!E15<>"",Navegación!E15,"") | F15: =IF(Navegación!F15<>"",Navegación!F15,"") | G15: =IF(Navegación!G15<>"",Navegación!G15,"") | H15: =IF(Navegación!H15<>"",Navegación!H15,"") | I15: =IF(Navegación!I15<>"",Navegación!I15,"")
B16: Empleado Cafam o Externo | D16: =IF(Navegación!D16<>"",Navegación!D16,"") -> Empleado CAFAM | E16: =IF(Navegación!E16<>"",Navegación!E16,"") | F16: =IF(Navegación!F16<>"",Navegación!F16,"") | G16: =IF(Navegación!G16<>"",Navegación!G16,"") | H16: =IF(Navegación!H16<>"",Navegación!H16,"") | I16: =IF(Navegación!I16<>"",Navegación!I16,"")
B17: Nombre de la empresa cuando es Externo | D17: =IF(Navegación!D17<>"",Navegación!D17,"") | E17: =IF(Navegación!E17<>"",Navegación!E17,"") | F17: =IF(Navegación!F17<>"",Navegación!F17,"") | G17: =IF(Navegación!G17<>"",Navegación!G17,"") | H17: =IF(Navegación!H17<>"",Navegación!H17,"") | I17: =IF(Navegación!I17<>"",Navegación!I17,"")
B18: Fecha inicio contrato: | D18: =IF(Navegación!D18<>"",Navegación!D18,"") -> 45849 | E18: =IF(Navegación!E18<>"",Navegación!E18,"") | F18: =IF(Navegación!F18<>"",Navegación!F18,"") | G18: =IF(Navegación!G18<>"",Navegación!G18,"") | H18: =IF(Navegación!H18<>"",Navegación!H18,"") | I18: =IF(Navegación!I18<>"",Navegación!I18,"")
B19: Fecha finalización contrato: (Si es indefinido escribir 31.12.9999) | D19: =IF(Navegación!D19<>"",Navegación!D19,"") | E19: =IF(Navegación!E19<>"",Navegación!E19,"") | F19: =IF(Navegación!F19<>"",Navegación!F19,"") | G19: =IF(Navegación!G19<>"",Navegación!G19,"") | H19: =IF(Navegación!H19<>"",Navegación!H19,"") | I19: =IF(Navegación!I19<>"",Navegación!I19,"")
B20: ZERO | D20: =IF(DZ25>0,Navegación!$E$28,"")
D21: =ADDRESS(MATCH(D$24,SaluTipoPerfil7190[[#All],[Aplicacion]],0)+251,16,1) -> $P$253 | E21: =ADDRESS(MATCH(E$24,SaluTipoPerfil7190[[#All],[Aplicacion]],0)+251,16,1) -> $P$253 | F21: =ADDRESS(MATCH(F$24,SaluTipoPerfil7190[[#All],[Aplicacion]],0)+251,16,1) -> $P$253 | G21: =ADDRESS(MATCH(G$24,SaluTipoPerfil7190[[#All],[Aplicacion]],0)+251,16,1) -> $P$253 | H21: =ADDRESS(MATCH(H$24,SaluTipoPerfil7190[[#All],[Aplicacion]],0)+251,16,1) -> $P$253 | I21: =ADDRESS(MATCH(I$24,SaluTipoPerfil7190[[#All],[Aplicacion]],0)+251,16,1) -> $P$253
D22: =ADDRESS(MATCH(D$29,SaludPerfiles7291[[#All],[TipoPerfil]],0)+251,20,1) -> #N/A | E22: =ADDRESS(MATCH(E$29,SaludPerfiles7291[[#All],[TipoPerfil]],0)+251,20,1) -> #N/A | F22: =ADDRESS(MATCH(F$29,SaludPerfiles7291[[#All],[TipoPerfil]],0)+251,20,1) -> #N/A | G22: =ADDRESS(MATCH(G$29,SaludPerfiles7291[[#All],[TipoPerfil]],0)+251,20,1) -> #N/A | H22: =ADDRESS(MATCH(H$29,SaludPerfiles7291[[#All],[TipoPerfil]],0)+251,20,1) -> #N/A | I22: =ADDRESS(MATCH(I$29,SaludPerfiles7291[[#All],[TipoPerfil]],0)+251,20,1) -> #N/A
D23: =ADDRESS(MATCH(D$24,SaludEspecialidades3088[[#All],[Sistema]],0)+251,23,1) -> $W$253 | E23: =ADDRESS(MATCH(E$24,SaludEspecialidades3088[[#All],[Sistema]],0)+251,23,1) -> $W$253 | F23: =ADDRESS(MATCH(F$24,SaludEspecialidades3088[[#All],[Sistema]],0)+251,23,1) -> $W$253 | G23: =ADDRESS(MATCH(G$24,SaludEspecialidades3088[[#All],[Sistema]],0)+251,23,1) -> $W$253 | H23: =ADDRESS(MATCH(H$24,SaludEspecialidades3088[[#All],[Sistema]],0)+251,23,1) -> $W$253 | I23: =ADDRESS(MATCH(I$24,SaludEspecialidades3088[[#All],[Sistema]],0)+251,23,1) -> $W$253
B24: Aplicativo | D24: ZERO | E24: =D24 -> ZERO | F24: =E24 -> ZERO | G24: =F24 -> ZERO | H24: =G24 -> ZERO | I24: =H24 -> ZERO
B25: Novedad (Crear/Inactivar): | DZ25: =COUNTIF(D25:I25,"<>") -> 0
B26: Sede
B27: Alias usuario
B28: Registro profesional
B29: Tipo de Perfil | E29: =INDEX(SaludPerfiles7291[#All],MATCH(E$30,SaludPerfiles7291[[#All],[Perfil]],),MATCH(SaludPerfiles7291[[#Headers],[TipoPerfil]],SaludPerfiles7291[#Headers],)) -> #N/A | F29: =INDEX(SaludPerfiles7291[#All],MATCH(F$30,SaludPerfiles7291[[#All],[Perfil]],),MATCH(SaludPerfiles7291[[#Headers],[TipoPerfil]],SaludPerfiles7291[#Headers],)) -> #N/A | G29: =INDEX(SaludPerfiles7291[#All],MATCH(G$30,SaludPerfiles7291[[#All],[Perfil]],),MATCH(SaludPerfiles7291[[#Headers],[TipoPerfil]],SaludPerfiles7291[#Headers],)) -> #N/A | H29: =INDEX(SaludPerfiles7291[#All],MATCH(H$30,SaludPerfiles7291[[#All],[Perfil]],),MATCH(SaludPerfiles7291[[#Headers],[TipoPerfil]],SaludPerfiles7291[#Headers],)) -> #N/A | I29: =INDEX(SaludPerfiles7291[#All],MATCH(I$30,SaludPerfiles7291[[#All],[Perfil]],),MATCH(SaludPerfiles7291[[#Headers],[TipoPerfil]],SaludPerfiles7291[#Headers],)) -> #N/A
B30: Perfil
B31: Especialidad
B32: Deposito
B33: Requiere tarjeta/Devuelve tarjeta (Solo para inactivar) Recuerde devolver la tarjeta en caso de Inactivar usuario
B35: Observaciones
B40: ='WINDOWS 1'!$B$37 -> APROBADOR POR: Jefe Dpto. Servicios Compartidos | F40: ='WINDOWS 1'!F37 -> V20 de 26/09/2023 | I40: ="Pág. " &Navegación!B28 & " de " &Navegación!$B$102 -> Pág. 6 de 54
DZ42: =COUNTIF(#REF!,"<>") -> #REF!
DZ51: =COUNTIF(#REF!,"<>") -> #REF!
DZ58: =COUNTIF(#REF!,"<>") -> #REF!
DZ62: =COUNTIF(D25:I25,"<>") -> 0
DZ72: =COUNTIF(#REF!,"<>") -> #REF!
DZ82: =COUNTIF(#REF!,"<>") -> #REF!
DZ88: =COUNTIF(#REF!,"<>") -> #REF!
DZ92: =COUNTIF(#REF!,"<>") -> #REF!
DZ96: =COUNTIF(#REF!,"<>") -> #REF!
DZ102: =COUNTIF(#REF!,"<>") -> #REF!
DZ106: =COUNTIF(#REF!,"<>") -> #REF!
DZ110: =COUNTIF(#REF!,"<>") -> #REF!
L252: EPS | M252: IPS | O252: Aplicacion | P252: TipoPerfil | R252: Aplicacion | S252: TipoPerfil | T252: Perfil | V252: Sistema | W252: Especialidad | Y252: DEPOSITO
L253: ZERO | M253: Clinica Calle 51 | O253: ZERO | P253: Zero-Asistencial | R253: ZERO | S253: Zero-Administrativo | T253: Administracion Datos Personales (1701) | V253: ZERO | W253: Adulto Mayor - Medico | Y253: Adm Maternidad Calle 51
L254: ZERO | M254: Clínica Cafam Calle 93 | O254: ZERO | P254: Zero-Administrativo | R254: ZERO | S254: Zero-Administrativo | T254: Admisiones (4312) | V254: ZERO | W254: Alergologia | Y254: Adm Maternidad SB
L255: ZERO | M255: Clínica Cafam Sta Barbara | R255: ZERO | S255: Zero-Asistencial | T255: Almacen | V255: ZERO | W255: Alteraciones del Joven - Medico | Y255: Adm Maternidad SB-Cuare
L256: ZERO | M256: Floresta | R256: ZERO | S256: Zero-Asistencial | T256: Asistente de Compra | V256: ZERO | W256: Anestesiologia | Y256: Adm Maternidad SB-Seria
L257: ZERO | M257: Kennedy | R257: ZERO | S257: Zero-Administrativo | T257: Auditoria Medica (4322) | V257: ZERO | W257: Anestesiologia Cardiovascular | Y257: Adm Maternidad SB-Trans
L258: ZERO | M258: Suba | R258: ZERO | S258: Zero-Administrativo | T258: Autorizaciones (4317) | V258: ZERO | W258: Auxiliar Enfermeria | Y258: Cardio Serial Calle 93
R259: ZERO | S259: Zero-Administrativo | T259: Autorizaciones-Coord (4318) | V259: ZERO | W259: Cardiologia | Y259: Cirugia Clinica
R260: ZERO | S260: Zero-Asistencial | T260: Auxiliar Cirugia | V260: ZERO | W260: Cardiologia Pediatrica | Y260: Cirugia Floresta
R261: ZERO | S261: Zero-Asistencial | T261: Auxiliar de Almacen (1103) | V261: ZERO | W261: Centros Medicos | Y261: Cirugia Kennedy
R262: ZERO | S262: Zero-Asistencial | T262: Auxiliar Deposito (1101) | V262: ZERO | W262: Cirugia Cardiovascular | Y262: Cirugia Kennedy-Serializados
R263: ZERO | S263: Zero-Asistencial | T263: Auxiliar Enf.General ( 4605) | V263: ZERO | W263: Cirugia Cardiovascular Pediatrica | Y263: Cirugia SB
R264: ZERO | S264: Zero-Asistencial | T264: Auxiliar UCI Ad | V264: ZERO | W264: Cirugia De Cabeza Y Cuello | Y264: Cirugia SB-Serializado
R265: ZERO | S265: Zero-Asistencial | T265: Auxiliar UCI Neo | V265: ZERO | W265: Cirugia De La Mano | Y265: Cirugia SB-Transito
R266: ZERO | S266: Zero-Asistencial | T266: Auxiliar UCI Ped | V266: ZERO | W266: Cirugia De Mama Y Tumores De Tejido | Y266: CX CL93 Serializado
R267: ZERO | S267: Zero-Asistencial | T267: Contratacion | V267: ZERO | W267: Cirugia De Torax | Y267: Drenaje de Silicona
R268: ZERO | S268: Zero-Asistencial | T268: Contratacion Coord | V268: ZERO | W268: Cirugia Gastrointestinal | Y268: Hosp.Adult. C93-P4
R269: ZERO | S269: Zero-Administrativo | T269: Coordinacion Recaudos (4313) | V269: ZERO | W269: Cirugia General | Y269: Hosp.Adult. C93-P4-Serializados
R270: ZERO | S270: Zero-Asistencial | T270: Cuidado Domiciliario - Coordinador | V270: ZERO | W270: Cirugia Infantil O Pediatrica | Y270: Hosp.Adult. C93-P4-Vencidos
... R302: ZERO | S302: Zero-Asistencial | T302: Unidad Transfusional | V302: ZERO | W302: Ginecologia Oncologica | Y302: Sala de Partos Calle 51
V303: ZERO | W303: Ginecologia Y Obstetricia | Y303: Sala de Partos SB
V304: ZERO | W304: Hematologia | Y304: Sala de Partos SB-Serializados
V305: ZERO | W305: Hematologia Oncologica | Y305: Sala de Partos SB-Transito
V306: ZERO | W306: Hematologia Pediatrica | Y306: Salidas
V307: ZERO | W307: Hemodinamia | Y307: Sf. Cirugia C93
V308: ZERO | W308: Hepatologia | Y308: Sf. Cirugia C93-Serializado
V309: ZERO | W309: Higiene Oral | Y309: Sf. Cirugia SB
V310: ZERO | W310: Hospitalario | Y310: Sf. Cirugia SB-Serializado
V311: ZERO | W311: Hta - Enfermeria | Y311: Sf. Cirugia SB-Transito
V312: ZERO | W312: Hta - Medico | Y312: Sf. Clinica 51 P5
V313: ZERO | W313: Hta - Medico Familiar | Y313: Sf. Hemodinamica Cl 93
V314: ZERO | W314: Hta - Medico Internista | Y314: Sf. P1. C93
... V356: ZERO | W356: Ortopedia Pediatrica | Y356: Urgencias SUBA-Serializado
V357: ZERO | W357: Ortopedia Y Traumatologia
V358: ZERO | W358: Otorrinolaringologia
V359: ZERO | W359: Otorrinolaringologia Pediatrica
V360: ZERO | W360: Otras
V361: ZERO | W361: Otras Agendas
V362: ZERO | W362: Patologia Y Anatomia Patologica
V363: ZERO | W363: Pediatria
V364: ZERO | W364: Pediatria- Md Adolecencia
V365: ZERO | W365: Pediatria-Neonatologia
V366: ZERO | W366: Periodoncia
V367: ZERO | W367: Planificacion Familiar - Enfermeria
V368: ZERO | W368: Planificacion Familiar - Medico
... V398: ZERO | W398: Urologia Pediatrica

Sheet SALUD 4
K1: 2958465
C2: FORMATO: GESTIÓN DE IDENTIDADES
F3: DOCUMENTO USO INTERNO
B5: Las celdas resaltadas en Naranja son campos obligatorios del Formato.
B6: Información Usuarios | D6: Usuario 1 | E6: Usuario 2 | F6: Usuario 3 | G6: Usuario 4 | H6: Usuario 5 | I6: Usuario 6
B7: Tipo de documento | D7: =IF(Navegación!D7<>"",Navegación!D7,"") -> Cédula Ciudadanía | E7: =IF(Navegación!E7<>"",Navegación!E7,"") | F7: =IF(Navegación!F7<>"",Navegación!F7,"") | G7: =IF(Navegación!G7<>"",Navegación!G7,"") | H7: =IF(Navegación!H7<>"",Navegación!H7,"") | I7: =IF(Navegación!I7<>"",Navegación!I7,"")
B8: Identificación | D8: =IF(Navegación!D8<>"",Navegación!D8,"") -> 1001089595 | E8: =IF(Navegación!E8<>"",Navegación!E8,"") | F8: =IF(Navegación!F8<>"",Navegación!F8,"") | G8: =IF(Navegación!G8<>"",Navegación!G8,"") | H8: =IF(Navegación!H8<>"",Navegación!H8,"") | I8: =IF(Navegación!I8<>"",Navegación!I8,"")
B9: Nombres completos | D9: =IF(Navegación!D9<>"",Navegación!D9,"") -> JUAN PABLO | E9: =IF(Navegación!E9<>"",Navegación!E9,"") | F9: =IF(Navegación!F9<>"",Navegación!F9,"") | G9: =IF(Navegación!G9<>"",Navegación!G9,"") | H9: =IF(Navegación!H9<>"",Navegación!H9,"") | I9: =IF(Navegación!I9<>"",Navegación!I9,"")
B10: Apellidos completos | D10: =IF(Navegación!D10<>"",Navegación!D10,"") -> CAMPO TELLEZ | E10: =IF(Navegación!E10<>"",Navegación!E10,"") | F10: =IF(Navegación!F10<>"",Navegación!F10,"") | G10: =IF(Navegación!G10<>"",Navegación!G10,"") | H10: =IF(Navegación!H10<>"",Navegación!H10,"") | I10: =IF(Navegación!I10<>"",Navegación!I10,"")
B11: Centro de costo | D11: =IF(Navegación!D11<>"",Navegación!D11,"") -> 856 | E11: =IF(Navegación!E11<>"",Navegación!E11,"") | F11: =IF(Navegación!F11<>"",Navegación!F11,"") | G11: =IF(Navegación!G11<>"",Navegación!G11,"") | H11: =IF(Navegación!H11<>"",Navegación!H11,"") | I11: =IF(Navegación!I11<>"",Navegación!I11,"")
B12: Teléfono/Extensión de contacto del usuario | D12: =IF(Navegación!D12<>"",Navegación!D12,"") | E12: =IF(Navegación!E12<>"",Navegación!E12,"") | F12: =IF(Navegación!F12<>"",Navegación!F12,"") | G12: =IF(Navegación!G12<>"",Navegación!G12,"") | H12: =IF(Navegación!H12<>"",Navegación!H12,"") | I12: =IF(Navegación!I12<>"",Navegación!I12,"")
B13: Celular | D13: =IF(Navegación!D13<>"",Navegación!D13,"") -> 3150727969 | E13: =IF(Navegación!E13<>"",Navegación!E13,"") | F13: =IF(Navegación!F13<>"",Navegación!F13,"") | G13: =IF(Navegación!G13<>"",Navegación!G13,"") | H13: =IF(Navegación!H13<>"",Navegación!H13,"") | I13: =IF(Navegación!I13<>"",Navegación!I13,"")
B14: Dependencia | D14: =IF(Navegación!D14<>"",Navegación!D14,"") -> Gobierno | E14: =IF(Navegación!E14<>"",Navegación!E14,"") | F14: =IF(Navegación!F14<>"",Navegación!F14,"") | G14: =IF(Navegación!G14<>"",Navegación!G14,"") | H14: =IF(Navegación!H14<>"",Navegación!H14,"") | I14: =IF(Navegación!I14<>"",Navegación!I14,"")
B15: Cargo | D15: =IF(Navegación!D15<>"",Navegación!D15,"") -> Aprendiz Universitario | E15: =IF(Navegación!E15<>"",Navegación!E15,"") | F15: =IF(Navegación!F15<>"",Navegación!F15,"") | G15: =IF(Navegación!G15<>"",Navegación!G15,"") | H15: =IF(Navegación!H15<>"",Navegación!H15,"") | I15: =IF(Navegación!I15<>"",Navegación!I15,"")
B16: Empleado Cafam o Externo | D16: =IF(Navegación!D16<>"",Navegación!D16,"") -> Empleado CAFAM | E16: =IF(Navegación!E16<>"",Navegación!E16,"") | F16: =IF(Navegación!F16<>"",Navegación!F16,"") | G16: =IF(Navegación!G16<>"",Navegación!G16,"") | H16: =IF(Navegación!H16<>"",Navegación!H16,"") | I16: =IF(Navegación!I16<>"",Navegación!I16,"")
B17: Nombre de la empresa cuando es Externo | D17: =IF(Navegación!D17<>"",Navegación!D17,"") | E17: =IF(Navegación!E17<>"",Navegación!E17,"") | F17: =IF(Navegación!F17<>"",Navegación!F17,"") | G17: =IF(Navegación!G17<>"",Navegación!G17,"") | H17: =IF(Navegación!H17<>"",Navegación!H17,"") | I17: =IF(Navegación!I17<>"",Navegación!I17,"")
B18: Fecha inicio contrato: | D18: =IF(Navegación!D18<>"",Navegación!D18,"") -> 45849 | E18: =IF(Navegación!E18<>"",Navegación!E18,"") | F18: =IF(Navegación!F18<>"",Navegación!F18,"") | G18: =IF(Navegación!G18<>"",Navegación!G18,"") | H18: =IF(Navegación!H18<>"",Navegación!H18,"") | I18: =IF(Navegación!I18<>"",Navegación!I18,"")
B19: Fecha finalización contrato: (Si es indefinido escribir 31.12.9999) | D19: =IF(Navegación!D19<>"",Navegación!D19,"") | E19: =IF(Navegación!E19<>"",Navegación!E19,"") | F19: =IF(Navegación!F19<>"",Navegación!F19,"") | G19: =IF(Navegación!G19<>"",Navegación!G19,"") | H19: =IF(Navegación!H19<>"",Navegación!H19,"") | I19: =IF(Navegación!I19<>"",Navegación!I19,"")
B20: ENTERPRISE - Validar con Administrador del Aplicativo | D20: =IF(DZ21>0,Navegación!$E$29,"")
B21: Novedad (Crear/Modificación/Inactivar): | DZ21: =COUNTIF(D21:I21,"<>") -> 0
B22: Requiere imprimir informes
B23: Requiere acceso a información confidencial
B24: Requiere agregar o eliminar exámenes
B25: Alias usuario
B26: Sede Asignación
B27: Perfil
B28: Sede Visualización y Acceso de Información
B29: Secciones a las que requiere permiso
B31: Observaciones
B36: ='WINDOWS 1'!$B$37 -> APROBADOR POR: Jefe Dpto. Servicios Compartidos | F36: ='WINDOWS 1'!F37 -> V20 de 26/09/2023 | I36: ="Pág. " &Navegación!B29 & " de " &Navegación!$B$102 -> Pág. 7 de 54
DZ42: =COUNTIF(#REF!,"<>") -> #REF!
DZ51: =COUNTIF(#REF!,"<>") -> #REF!
DZ58: =COUNTIF(D21:I21,"<>") -> 0
DZ62: =COUNTIF(#REF!,"<>") -> #REF!
DZ72: =COUNTIF(D21:I21,"<>") -> 0
DZ82: =COUNTIF(#REF!,"<>") -> #REF!
DZ88: =COUNTIF(#REF!,"<>") -> #REF!
DZ92: =COUNTIF(#REF!,"<>") -> #REF!
DZ96: =COUNTIF(#REF!,"<>") -> #REF!
DZ102: =COUNTIF(#REF!,"<>") -> #REF!
DZ106: =COUNTIF(#REF!,"<>") -> #REF!
DZ110: =COUNTIF(#REF!,"<>") -> #REF!
O252: Aplicacion | P252: TipoPerfil | R252: Aplicacion | S252: TipoPerfil | T252: Perfil
O253: ENTERPRISE | P253: Enterprise-Administrativo | R253: ENTERPRISE | S253: Enterprise-Administrativo | T253: Auditor Medico
R254: ENTERPRISE | S254: Enterprise-Administrativo | T254: Auxiliar Enfermeria
R255: ENTERPRISE | S255: Enterprise-Administrativo | T255: Auxiliares
R256: ENTERPRISE | S256: Enterprise-Administrativo | T256: Bacteriologo
R257: ENTERPRISE | S257: Enterprise-Administrativo | T257: Cajero
R258: ENTERPRISE | S258: Enterprise-Administrativo | T258: Consulta
R259: ENTERPRISE | S259: Enterprise-Administrativo | T259: Creación Usuarios
R260: ENTERPRISE | S260: Enterprise-Administrativo | T260: Enfermero
R261: ENTERPRISE | S261: Enterprise-Administrativo | T261: Estadistica
R262: ENTERPRISE | S262: Enterprise-Administrativo | T262: Soporte Sistemas

Sheet SALUD 5
K1: 2958465
C2: FORMATO: GESTIÓN DE IDENTIDADES
F3: DOCUMENTO USO INTERNO
B5: Las celdas resaltadas en Naranja son campos obligatorios del Formato.
B6: Información Usuarios | D6: Usuario 1 | E6: Usuario 2 | F6: Usuario 3 | G6: Usuario 4 | H6: Usuario 5 | I6: Usuario 6
B7: Tipo de documento | D7: =IF(Navegación!D7<>"",Navegación!D7,"") -> Cédula Ciudadanía | E7: =IF(Navegación!E7<>"",Navegación!E7,"") | F7: =IF(Navegación!F7<>"",Navegación!F7,"") | G7: =IF(Navegación!G7<>"",Navegación!G7,"") | H7: =IF(Navegación!H7<>"",Navegación!H7,"") | I7: =IF(Navegación!I7<>"",Navegación!I7,"")
B8: Identificación | D8: =IF(Navegación!D8<>"",Navegación!D8,"") -> 1001089595 | E8: =IF(Navegación!E8<>"",Navegación!E8,"") | F8: =IF(Navegación!F8<>"",Navegación!F8,"") | G8: =IF(Navegación!G8<>"",Navegación!G8,"") | H8: =IF(Navegación!H8<>"",Navegación!H8,"") | I8: =IF(Navegación!I8<>"",Navegación!I8,"")
B9: Nombres completos | D9: =IF(Navegación!D9<>"",Navegación!D9,"") -> JUAN PABLO | E9: =IF(Navegación!E9<>"",Navegación!E9,"") | F9: =IF(Navegación!F9<>"",Navegación!F9,"") | G9: =IF(Navegación!G9<>"",Navegación!G9,"") | H9: =IF(Navegación!H9<>"",Navegación!H9,"") | I9: =IF(Navegación!I9<>"",Navegación!I9,"")
B10: Apellidos completos | D10: =IF(Navegación!D10<>"",Navegación!D10,"") -> CAMPO TELLEZ | E10: =IF(Navegación!E10<>"",Navegación!E10,"") | F10: =IF(Navegación!F10<>"",Navegación!F10,"") | G10: =IF(Navegación!G10<>"",Navegación!G10,"") | H10: =IF(Navegación!H10<>"",Navegación!H10,"") | I10: =IF(Navegación!I10<>"",Navegación!I10,"")
B11: Centro de costo | D11: =IF(Navegación!D11<>"",Navegación!D11,"") -> 856 | E11: =IF(Navegación!E11<>"",Navegación!E11,"") | F11: =IF(Navegación!F11<>"",Navegación!F11,"") | G11: =IF(Navegación!G11<>"",Navegación!G11,"") | H11: =IF(Navegación!H11<>"",Navegación!H11,"") | I11: =IF(Navegación!I11<>"",Navegación!I11,"")
B12: Teléfono/Extensión de contacto del usuario | D12: =IF(Navegación!D12<>"",Navegación!D12,"") | E12: =IF(Navegación!E12<>"",Navegación!E12,"") | F12: =IF(Navegación!F12<>"",Navegación!F12,"") | G12: =IF(Navegación!G12<>"",Navegación!G12,"") | H12: =IF(Navegación!H12<>"",Navegación!H12,"") | I12: =IF(Navegación!I12<>"",Navegación!I12,"")
B13: Celular | D13: =IF(Navegación!D13<>"",Navegación!D13,"") -> 3150727969 | E13: =IF(Navegación!E13<>"",Navegación!E13,"") | F13: =IF(Navegación!F13<>"",Navegación!F13,"") | G13: =IF(Navegación!G13<>"",Navegación!G13,"") | H13: =IF(Navegación!H13<>"",Navegación!H13,"") | I13: =IF(Navegación!I13<>"",Navegación!I13,"")
B14: Dependencia | D14: =IF(Navegación!D14<>"",Navegación!D14,"") -> Gobierno | E14: =IF(Navegación!E14<>"",Navegación!E14,"") | F14: =IF(Navegación!F14<>"",Navegación!F14,"") | G14: =IF(Navegación!G14<>"",Navegación!G14,"") | H14: =IF(Navegación!H14<>"",Navegación!H14,"") | I14: =IF(Navegación!I14<>"",Navegación!I14,"")
B15: Cargo | D15: =IF(Navegación!D15<>"",Navegación!D15,"") -> Aprendiz Universitario | E15: =IF(Navegación!E15<>"",Navegación!E15,"") | F15: =IF(Navegación!F15<>"",Navegación!F15,"") | G15: =IF(Navegación!G15<>"",Navegación!G15,"") | H15: =IF(Navegación!H15<>"",Navegación!H15,"") | I15: =IF(Navegación!I15<>"",Navegación!I15,"")
B16: Empleado Cafam o Externo | D16: =IF(Navegación!D16<>"",Navegación!D16,"") -> Empleado CAFAM | E16: =IF(Navegación!E16<>"",Navegación!E16,"") | F16: =IF(Navegación!F16<>"",Navegación!F16,"") | G16: =IF(Navegación!G16<>"",Navegación!G16,"") | H16: =IF(Navegación!H16<>"",Navegación!H16,"") | I16: =IF(Navegación!I16<>"",Navegación!I16,"")
B17: Nombre de la empresa cuando es Externo | D17: =IF(Navegación!D17<>"",Navegación!D17,"") | E17: =IF(Navegación!E17<>"",Navegación!E17,"") | F17: =IF(Navegación!F17<>"",Navegación!F17,"") | G17: =IF(Navegación!G17<>"",Navegación!G17,"") | H17: =IF(Navegación!H17<>"",Navegación!H17,"") | I17: =IF(Navegación!I17<>"",Navegación!I17,"")
B18: Fecha inicio contrato: | D18: =IF(Navegación!D18<>"",Navegación!D18,"") -> 45849 | E18: =IF(Navegación!E18<>"",Navegación!E18,"") | F18: =IF(Navegación!F18<>"",Navegación!F18,"") | G18: =IF(Navegación!G18<>"",Navegación!G18,"") | H18: =IF(Navegación!H18<>"",Navegación!H18,"") | I18: =IF(Navegación!I18<>"",Navegación!I18,"")
B19: Fecha finalización contrato: (Si es indefinido escribir 31.12.9999) | D19: =IF(Navegación!D19<>"",Navegación!D19,"") | E19: =IF(Navegación!E19<>"",Navegación!E19,"") | F19: =IF(Navegación!F19<>"",Navegación!F19,"") | G19: =IF(Navegación!G19<>"",Navegación!G19,"") | H19: =IF(Navegación!H19<>"",Navegación!H19,"") | I19: =IF(Navegación!I19<>"",Navegación!I19,"")
B20: Consulta Informacion SICYPROH | D20: =IF(DZ21>0,Navegación!$E$30,"")
B21: Novedad (Asignar/Retirar): (bdd_sicyproh) | DZ21: =COUNTIF(D21:I21,"<>") -> 0
B22: Aplicativo | D22: SICYPROH | E22: SICYPROH | F22: SICYPROH | G22: SICYPROH | H22: SICYPROH | I22: SICYPROH
B23: Alias usuario
B24: Registro profesional
B25: Tipo de Perfil
B26: Perfil | DZ26: =COUNTIF(#REF!,"<>") -> #REF!
B27: Especialidad
B28: Celular
B29: Estado Civil
B30: Fecha de Nacimiento
B31: Dirección
B32: Barrio
B33: SIGESA | D33: =IF(DZ35>0,Navegación!$E$31,"")
D34: =ADDRESS(MATCH(D$38,SaludPerfiles729196101[[#All],[TipoPerfil]],0)+251,20,1) -> #N/A | E34: =ADDRESS(MATCH(E$38,SaludPerfiles729196101[[#All],[TipoPerfil]],0)+251,20,1) -> #N/A | F34: =ADDRESS(MATCH(F$38,SaludPerfiles729196101[[#All],[TipoPerfil]],0)+251,20,1) -> #N/A | G34: =ADDRESS(MATCH(G$38,SaludPerfiles729196101[[#All],[TipoPerfil]],0)+251,20,1) -> #N/A | H34: =ADDRESS(MATCH(H$38,SaludPerfiles729196101[[#All],[TipoPerfil]],0)+251,20,1) -> #N/A | I34: =ADDRESS(MATCH(I$38,SaludPerfiles729196101[[#All],[TipoPerfil]],0)+251,20,1) -> #N/A
B35: Novedad (Crear/Modificación/Inactivar): | DZ35: =COUNTIF(D35:I35,"<>") -> 0
B36: Aplicativo | G36: SIGESA | H36: SIGESA | I36: SIGESA
B37: Alias usuario
B38: Tipo de Perfil
B39: Perfil
B41: Observaciones
B46: ='WINDOWS 1'!$B$37 -> APROBADOR POR: Jefe Dpto. Servicios Compartidos | F46: ='WINDOWS 1'!F37 -> V20 de 26/09/2023 | I46: ="Pág. " &Navegación!B30 & " de " &Navegación!$B$102 -> Pág. 8 de 54
DZ51: =COUNTIF(#REF!,"<>") -> #REF!
DZ58: =COUNTIF(#REF!,"<>") -> #REF!
DZ62: =COUNTIF(#REF!,"<>") -> #REF!
DZ72: =COUNTIF(#REF!,"<>") -> #REF!
DZ82: =COUNTIF(D21:I21,"<>") -> 0
DZ88: =COUNTIF(#REF!,"<>") -> #REF!
DZ92: =COUNTIF(#REF!,"<>") -> #REF!
DZ96: =COUNTIF(D35:I35,"<>") -> 0
DZ102: =COUNTIF(#REF!,"<>") -> #REF!
DZ106: =COUNTIF(#REF!,"<>") -> #REF!
DZ110: =COUNTIF(#REF!,"<>") -> #REF!
O252: Aplicacion | P252: TipoPerfil | R252: Aplicacion | S252: TipoPerfil | T252: Perfil | V252: Sistema | W252: Especialidad
O253: SICYPROH | P253: Sicyproh-Administrativo | R253: SICYPROH | S253: Sicyproh-Administrativo | T253: Cajero | V253: SICYPROH | W253: Contingencia
O254: SICYPROH | P254: Sicyproh-Asistencial | R254: SICYPROH | S254: Sicyproh-Administrativo | T254: Recaudador | V254: SICYPROH | W254: Dermatología
O255: SIGESA | P255: Sigesa-Asistencial | R255: SICYPROH | S255: Sicyproh-Asistencial | T255: Auxiliar Enfermeria | V255: SICYPROH | W255: Efebologia
R256: SICYPROH | S256: Sicyproh-Asistencial | T256: Enfermera Jefe | V256: SICYPROH | W256: Endocrinología
R257: SICYPROH | S257: Sicyproh-Asistencial | T257: Instrumentadora | V257: SICYPROH | W257: Endodoncia
R258: SICYPROH | S258: Sicyproh-Asistencial | T258: Medico Especialista | V258: SICYPROH | W258: Enfermería Grupal Grips
R259: SICYPROH | S259: Sicyproh-Asistencial | T259: Medico General | V259: SICYPROH | W259: Enfermería Grupal Grips
R260: SICYPROH | S260: Sicyproh-Asistencial | T260: Otros Profesionales | V260: SICYPROH | W260: Enfermería Grupal Grips
R261: SIGESA | S261: Sigesa-Asistencial | T261: Implantologia | V261: SICYPROH | W261: Enfermería Individual Grips
R262: SIGESA | S262: Sigesa-Asistencial | T262: Periodoncia | V262: SICYPROH | W262: Enfermería Medico-Quirúrgica
R263: SIGESA | S263: Sigesa-Asistencial | T263: Prostodoncia | V263: SICYPROH | W263: Fisioterapeutas
V264: SICYPROH | W264: Fonoaudiología
V265: SICYPROH | W265: Gastroenterología
V266: SICYPROH | W266: Ginecología Obstetricia Grips
V267: SICYPROH | W267: Ginecología Y Obstetricia
V268: SICYPROH | W268: Hemato Oncología
V269: SICYPROH | W269: Higiene Oral
V270: SICYPROH | W270: Imágenes Diagnosticas
V271: SICYPROH | W271: Infectologia
V272: SICYPROH | W272: Inmunología
V273: SICYPROH | W273: Maternidad Mg
V274: SICYPROH | W274: Medicina Del Trabajo
V275: SICYPROH | W275: Medicina Familiar
... V332: SIGESA | W332: Prostodoncia

Sheet SALUD 6
K1: 2958465
C2: FORMATO: GESTIÓN DE IDENTIDADES
F3: DOCUMENTO USO INTERNO
B5: Las celdas resaltadas en Naranja son campos obligatorios del Formato.
B6: Información Usuarios | D6: Usuario 1 | E6: Usuario 2 | F6: Usuario 3 | G6: Usuario 4 | H6: Usuario 5 | I6: Usuario 6
B7: Tipo de documento | D7: =IF(Navegación!D7<>"",Navegación!D7,"") -> Cédula Ciudadanía | E7: =IF(Navegación!E7<>"",Navegación!E7,"") | F7: =IF(Navegación!F7<>"",Navegación!F7,"") | G7: =IF(Navegación!G7<>"",Navegación!G7,"") | H7: =IF(Navegación!H7<>"",Navegación!H7,"") | I7: =IF(Navegación!I7<>"",Navegación!I7,"")
B8: Identificación | D8: =IF(Navegación!D8<>"",Navegación!D8,"") -> 1001089595 | E8: =IF(Navegación!E8<>"",Navegación!E8,"") | F8: =IF(Navegación!F8<>"",Navegación!F8,"") | G8: =IF(Navegación!G8<>"",Navegación!G8,"") | H8: =IF(Navegación!H8<>"",Navegación!H8,"") | I8: =IF(Navegación!I8<>"",Navegación!I8,"")
B9: Nombres completos | D9: =IF(Navegación!D9<>"",Navegación!D9,"") -> JUAN PABLO | E9: =IF(Navegación!E9<>"",Navegación!E9,"") | F9: =IF(Navegación!F9<>"",Navegación!F9,"") | G9: =IF(Navegación!G9<>"",Navegación!G9,"") | H9: =IF(Navegación!H9<>"",Navegación!H9,"") | I9: =IF(Navegación!I9<>"",Navegación!I9,"")
B10: Apellidos completos | D10: =IF(Navegación!D10<>"",Navegación!D10,"") -> CAMPO TELLEZ | E10: =IF(Navegación!E10<>"",Navegación!E10,"") | F10: =IF(Navegación!F10<>"",Navegación!F10,"") | G10: =IF(Navegación!G10<>"",Navegación!G10,"") | H10: =IF(Navegación!H10<>"",Navegación!H10,"") | I10: =IF(Navegación!I10<>"",Navegación!I10,"")
B11: Centro de costo | D11: =IF(Navegación!D11<>"",Navegación!D11,"") -> 856 | E11: =IF(Navegación!E11<>"",Navegación!E11,"") | F11: =IF(Navegación!F11<>"",Navegación!F11,"") | G11: =IF(Navegación!G11<>"",Navegación!G11,"") | H11: =IF(Navegación!H11<>"",Navegación!H11,"") | I11: =IF(Navegación!I11<>"",Navegación!I11,"")
B12: Teléfono/Extensión de contacto del usuario | D12: =IF(Navegación!D12<>"",Navegación!D12,"") | E12: =IF(Navegación!E12<>"",Navegación!E12,"") | F12: =IF(Navegación!F12<>"",Navegación!F12,"") | G12: =IF(Navegación!G12<>"",Navegación!G12,"") | H12: =IF(Navegación!H12<>"",Navegación!H12,"") | I12: =IF(Navegación!I12<>"",Navegación!I12,"")
B13: Celular | D13: =IF(Navegación!D13<>"",Navegación!D13,"") -> 3150727969 | E13: =IF(Navegación!E13<>"",Navegación!E13,"") | F13: =IF(Navegación!F13<>"",Navegación!F13,"") | G13: =IF(Navegación!G13<>"",Navegación!G13,"") | H13: =IF(Navegación!H13<>"",Navegación!H13,"") | I13: =IF(Navegación!I13<>"",Navegación!I13,"")
B14: Dependencia | D14: =IF(Navegación!D14<>"",Navegación!D14,"") -> Gobierno | E14: =IF(Navegación!E14<>"",Navegación!E14,"") | F14: =IF(Navegación!F14<>"",Navegación!F14,"") | G14: =IF(Navegación!G14<>"",Navegación!G14,"") | H14: =IF(Navegación!H14<>"",Navegación!H14,"") | I14: =IF(Navegación!I14<>"",Navegación!I14,"")
B15: Cargo | D15: =IF(Navegación!D15<>"",Navegación!D15,"") -> Aprendiz Universitario | E15: =IF(Navegación!E15<>"",Navegación!E15,"") | F15: =IF(Navegación!F15<>"",Navegación!F15,"") | G15: =IF(Navegación!G15<>"",Navegación!G15,"") | H15: =IF(Navegación!H15<>"",Navegación!H15,"") | I15: =IF(Navegación!I15<>"",Navegación!I15,"")
B16: Empleado Cafam o Externo | D16: =IF(Navegación!D16<>"",Navegación!D16,"") -> Empleado CAFAM | E16: =IF(Navegación!E16<>"",Navegación!E16,"") | F16: =IF(Navegación!F16<>"",Navegación!F16,"") | G16: =IF(Navegación!G16<>"",Navegación!G16,"") | H16: =IF(Navegación!H16<>"",Navegación!H16,"") | I16: =IF(Navegación!I16<>"",Navegación!I16,"")
B17: Nombre de la empresa cuando es Externo | D17: =IF(Navegación!D17<>"",Navegación!D17,"") | E17: =IF(Navegación!E17<>"",Navegación!E17,"") | F17: =IF(Navegación!F17<>"",Navegación!F17,"") | G17: =IF(Navegación!G17<>"",Navegación!G17,"") | H17: =IF(Navegación!H17<>"",Navegación!H17,"") | I17: =IF(Navegación!I17<>"",Navegación!I17,"")
B18: Fecha inicio contrato: | D18: =IF(Navegación!D18<>"",Navegación!D18,"") -> 45849 | E18: =IF(Navegación!E18<>"",Navegación!E18,"") | F18: =IF(Navegación!F18<>"",Navegación!F18,"") | G18: =IF(Navegación!G18<>"",Navegación!G18,"") | H18: =IF(Navegación!H18<>"",Navegación!H18,"") | I18: =IF(Navegación!I18<>"",Navegación!I18,"")
B19: Fecha finalización contrato: (Si es indefinido escribir 31.12.9999) | D19: =IF(Navegación!D19<>"",Navegación!D19,"") | E19: =IF(Navegación!E19<>"",Navegación!E19,"") | F19: =IF(Navegación!F19<>"",Navegación!F19,"") | G19: =IF(Navegación!G19<>"",Navegación!G19,"") | H19: =IF(Navegación!H19<>"",Navegación!H19,"") | I19: =IF(Navegación!I19<>"",Navegación!I19,"")
B20: Plataforma Iseries SALUD | D20: =IF(DZ21>0,Navegación!$E$32,"")
B21: Novedad (Crear/Modificación/Inactivar): | DZ21: =COUNTIF(D21:I21,"<>") -> 0
B22: Alias Usuario
B23: Nombre del perfil
B25: Observaciones
B30: ='WINDOWS 1'!$B$37 -> APROBADOR POR: Jefe Dpto. Servicios Compartidos | F30: ='WINDOWS 1'!F37 -> V20 de 26/09/2023 | I30: ="Pág. " &Navegación!B32 & " de " &Navegación!$B$102 -> Pág. 10 de 54
DZ42: =COUNTIF(#REF!,"<>") -> #REF!
DZ51: =COUNTIF(#REF!,"<>") -> #REF!
DZ58: =COUNTIF(#REF!,"<>") -> #REF!
DZ62: =COUNTIF(#REF!,"<>") -> #REF!
DZ72: =COUNTIF(#REF!,"<>") -> #REF!
DZ82: =COUNTIF(#REF!,"<>") -> #REF!
DZ88: =COUNTIF(D21:I21,"<>") -> 0
DZ92: =COUNTIF(#REF!,"<>") -> #REF!
DZ96: =COUNTIF(#REF!,"<>") -> #REF!
DZ102: =COUNTIF(D21:I21,"<>") -> 0
DZ106: =COUNTIF(#REF!,"<>") -> #REF!
DZ110: =COUNTIF(#REF!,"<>") -> #REF!
O252: Aplicacion | P252: TipoPerfil | R252: Aplicacion | S252: TipoPerfil | T252: Perfil
O253: ISERIES | P253: Iseries-Administrativo | R253: ISERIES | S253: Iseries-Administrativo | T253: Cajero
O254: ISERIES | P254: Iseries-Asistencial | R254: ISERIES | S254: Iseries-Administrativo | T254: Call Center
R255: ISERIES | S255: Iseries-Administrativo | T255: Recaudos
R256: ISERIES | S256: Iseries-Asistencial | T256: Endodoncia
R257: ISERIES | S257: Iseries-Asistencial | T257: Ortodoncia
R258: ISERIES | S258: Iseries-Asistencial | T258: Periodoncia
R259: ISERIES | S259: Iseries-Asistencial | T259: Prostodoncia

Sheet SALUD 7
K1: 2958465
C2: FORMATO: GESTIÓN DE IDENTIDADES
F3: DOCUMENTO USO INTERNO
B5: Las celdas resaltadas en Naranja son campos obligatorios del Formato.
B6: Información Usuarios | D6: Usuario 1 | E6: Usuario 2 | F6: Usuario 3 | G6: Usuario 4 | H6: Usuario 5 | I6: Usuario 6
B7: Tipo de documento | D7: =IF(Navegación!D7<>"",Navegación!D7,"") -> Cédula Ciudadanía | E7: =IF(Navegación!E7<>"",Navegación!E7,"") | F7: =IF(Navegación!F7<>"",Navegación!F7,"") | G7: =IF(Navegación!G7<>"",Navegación!G7,"") | H7: =IF(Navegación!H7<>"",Navegación!H7,"") | I7: =IF(Navegación!I7<>"",Navegación!I7,"")
B8: Identificación | D8: =IF(Navegación!D8<>"",Navegación!D8,"") -> 1001089595 | E8: =IF(Navegación!E8<>"",Navegación!E8,"") | F8: =IF(Navegación!F8<>"",Navegación!F8,"") | G8: =IF(Navegación!G8<>"",Navegación!G8,"") | H8: =IF(Navegación!H8<>"",Navegación!H8,"") | I8: =IF(Navegación!I8<>"",Navegación!I8,"")
B9: Nombres completos | D9: =IF(Navegación!D9<>"",Navegación!D9,"") -> JUAN PABLO | E9: =IF(Navegación!E9<>"",Navegación!E9,"") | F9: =IF(Navegación!F9<>"",Navegación!F9,"") | G9: =IF(Navegación!G9<>"",Navegación!G9,"") | H9: =IF(Navegación!H9<>"",Navegación!H9,"") | I9: =IF(Navegación!I9<>"",Navegación!I9,"")
B10: Apellidos completos | D10: =IF(Navegación!D10<>"",Navegación!D10,"") -> CAMPO TELLEZ | E10: =IF(Navegación!E10<>"",Navegación!E10,"") | F10: =IF(Navegación!F10<>"",Navegación!F10,"") | G10: =IF(Navegación!G10<>"",Navegación!G10,"") | H10: =IF(Navegación!H10<>"",Navegación!H10,"") | I10: =IF(Navegación!I10<>"",Navegación!I10,"")
B11: Centro de costo | D11: =IF(Navegación!D11<>"",Navegación!D11,"") -> 856 | E11: =IF(Navegación!E11<>"",Navegación!E11,"") | F11: =IF(Navegación!F11<>"",Navegación!F11,"") | G11: =IF(Navegación!G11<>"",Navegación!G11,"") | H11: =IF(Navegación!H11<>"",Navegación!H11,"") | I11: =IF(Navegación!I11<>"",Navegación!I11,"")
B12: Teléfono/Extensión de contacto del usuario | D12: =IF(Navegación!D12<>"",Navegación!D12,"") | E12: =IF(Navegación!E12<>"",Navegación!E12,"") | F12: =IF(Navegación!F12<>"",Navegación!F12,"") | G12: =IF(Navegación!G12<>"",Navegación!G12,"") | H12: =IF(Navegación!H12<>"",Navegación!H12,"") | I12: =IF(Navegación!I12<>"",Navegación!I12,"")
B13: Celular | D13: =IF(Navegación!D13<>"",Navegación!D13,"") -> 3150727969 | E13: =IF(Navegación!E13<>"",Navegación!E13,"") | F13: =IF(Navegación!F13<>"",Navegación!F13,"") | G13: =IF(Navegación!G13<>"",Navegación!G13,"") | H13: =IF(Navegación!H13<>"",Navegación!H13,"") | I13: =IF(Navegación!I13<>"",Navegación!I13,"")
B14: Dependencia | D14: =IF(Navegación!D14<>"",Navegación!D14,"") -> Gobierno | E14: =IF(Navegación!E14<>"",Navegación!E14,"") | F14: =IF(Navegación!F14<>"",Navegación!F14,"") | G14: =IF(Navegación!G14<>"",Navegación!G14,"") | H14: =IF(Navegación!H14<>"",Navegación!H14,"") | I14: =IF(Navegación!I14<>"",Navegación!I14,"")
B15: Cargo | D15: =IF(Navegación!D15<>"",Navegación!D15,"") -> Aprendiz Universitario | E15: =IF(Navegación!E15<>"",Navegación!E15,"") | F15: =IF(Navegación!F15<>"",Navegación!F15,"") | G15: =IF(Navegación!G15<>"",Navegación!G15,"") | H15: =IF(Navegación!H15<>"",Navegación!H15,"") | I15: =IF(Navegación!I15<>"",Navegación!I15,"")
B16: Empleado Cafam o Externo | D16: =IF(Navegación!D16<>"",Navegación!D16,"") -> Empleado CAFAM | E16: =IF(Navegación!E16<>"",Navegación!E16,"") | F16: =IF(Navegación!F16<>"",Navegación!F16,"") | G16: =IF(Navegación!G16<>"",Navegación!G16,"") | H16: =IF(Navegación!H16<>"",Navegación!H16,"") | I16: =IF(Navegación!I16<>"",Navegación!I16,"")
B17: Nombre de la empresa cuando es Externo | D17: =IF(Navegación!D17<>"",Navegación!D17,"") | E17: =IF(Navegación!E17<>"",Navegación!E17,"") | F17: =IF(Navegación!F17<>"",Navegación!F17,"") | G17: =IF(Navegación!G17<>"",Navegación!G17,"") | H17: =IF(Navegación!H17<>"",Navegación!H17,"") | I17: =IF(Navegación!I17<>"",Navegación!I17,"")
B18: Fecha inicio contrato: | D18: =IF(Navegación!D18<>"",Navegación!D18,"") -> 45849 | E18: =IF(Navegación!E18<>"",Navegación!E18,"") | F18: =IF(Navegación!F18<>"",Navegación!F18,"") | G18: =IF(Navegación!G18<>"",Navegación!G18,"") | H18: =IF(Navegación!H18<>"",Navegación!H18,"") | I18: =IF(Navegación!I18<>"",Navegación!I18,"")
B19: Fecha finalización contrato: (Si es indefinido escribir 31.12.9999) | D19: =IF(Navegación!D19<>"",Navegación!D19,"") | E19: =IF(Navegación!E19<>"",Navegación!E19,"") | F19: =IF(Navegación!F19<>"",Navegación!F19,"") | G19: =IF(Navegación!G19<>"",Navegación!G19,"") | H19: =IF(Navegación!H19<>"",Navegación!H19,"") | I19: =IF(Navegación!I19<>"",Navegación!I19,"")
B20: Paginas WEB | D20: =IF(DZ21>0,Navegación!$E$33,"")
B21: Famisanar en linea | DZ21: =COUNTIF(D21:I21,"<>") -> 0
B22: Email (Obligatoriamente una cuenta de dominio cafam.com.co o famisanar.com.co)
B23: RUAF | C23: Sede
C26: Rol | DZ26: =COUNTIF(D26:I26,"<>") -> 0
B28: Observaciones
B33: ='WINDOWS 1'!$B$37 -> APROBADOR POR: Jefe Dpto. Servicios Compartidos | F33: ='WINDOWS 1'!F37 -> V20 de 26/09/2023 | I33: ="Pág. " &Navegación!B34 & " de " &Navegación!$B$102 -> Pág. 12 de 54
DZ42: =COUNTIF(#REF!,"<>") -> #REF!
DZ51: =COUNTIF(#REF!,"<>") -> #REF!
DZ58: =COUNTIF(#REF!,"<>") -> #REF!
DZ62: =COUNTIF(#REF!,"<>") -> #REF!
DZ72: =COUNTIF(#REF!,"<>") -> #REF!
DZ82: =COUNTIF(#REF!,"<>") -> #REF!
DZ88: =COUNTIF(#REF!,"<>") -> #REF!
DZ92: =COUNTIF(D21:I21,"<>") -> 0
DZ96: =COUNTIF(#REF!,"<>") -> #REF!
DZ102: =COUNTIF(#REF!,"<>") -> #REF!
DZ106: =COUNTIF(D21:I21,"<>") -> 0
DZ110: =COUNTIF(D26:I26,"<>") -> 0

Sheet SAP 1
K1: 2958465
C2: FORMATO: GESTIÓN DE IDENTIDADES
F3: DOCUMENTO USO INTERNO
B5: Las celdas resaltadas en Naranja son campos obligatorios del Formato.
B6: Información Usuarios | D6: Usuario 1 | E6: Usuario 2 | F6: Usuario 3 | G6: Usuario 4 | H6: Usuario 5 | I6: Usuario 6
B7: Tipo de documento | D7: =IF(Navegación!D7<>"",Navegación!D7,"") -> Cédula Ciudadanía | E7: =IF(Navegación!E7<>"",Navegación!E7,"") | F7: =IF(Navegación!F7<>"",Navegación!F7,"") | G7: =IF(Navegación!G7<>"",Navegación!G7,"") | H7: =IF(Navegación!H7<>"",Navegación!H7,"") | I7: =IF(Navegación!I7<>"",Navegación!I7,"")
B8: Identificación | D8: =IF(Navegación!D8<>"",Navegación!D8,"") -> 1001089595 | E8: =IF(Navegación!E8<>"",Navegación!E8,"") | F8: =IF(Navegación!F8<>"",Navegación!F8,"") | G8: =IF(Navegación!G8<>"",Navegación!G8,"") | H8: =IF(Navegación!H8<>"",Navegación!H8,"") | I8: =IF(Navegación!I8<>"",Navegación!I8,"")
B9: Nombres completos | D9: =IF(Navegación!D9<>"",Navegación!D9,"") -> JUAN PABLO | E9: =IF(Navegación!E9<>"",Navegación!E9,"") | F9: =IF(Navegación!F9<>"",Navegación!F9,"") | G9: =IF(Navegación!G9<>"",Navegación!G9,"") | H9: =IF(Navegación!H9<>"",Navegación!H9,"") | I9: =IF(Navegación!I9<>"",Navegación!I9,"")
B10: Apellidos completos | D10: =IF(Navegación!D10<>"",Navegación!D10,"") -> CAMPO TELLEZ | E10: =IF(Navegación!E10<>"",Navegación!E10,"") | F10: =IF(Navegación!F10<>"",Navegación!F10,"") | G10: =IF(Navegación!G10<>"",Navegación!G10,"") | H10: =IF(Navegación!H10<>"",Navegación!H10,"") | I10: =IF(Navegación!I10<>"",Navegación!I10,"")
B11: Centro de costo | D11: =IF(Navegación!D11<>"",Navegación!D11,"") -> 856 | E11: =IF(Navegación!E11<>"",Navegación!E11,"") | F11: =IF(Navegación!F11<>"",Navegación!F11,"") | G11: =IF(Navegación!G11<>"",Navegación!G11,"") | H11: =IF(Navegación!H11<>"",Navegación!H11,"") | I11: =IF(Navegación!I11<>"",Navegación!I11,"")
B12: Teléfono/Extensión de contacto del usuario | D12: =IF(Navegación!D12<>"",Navegación!D12,"") | E12: =IF(Navegación!E12<>"",Navegación!E12,"") | F12: =IF(Navegación!F12<>"",Navegación!F12,"") | G12: =IF(Navegación!G12<>"",Navegación!G12,"") | H12: =IF(Navegación!H12<>"",Navegación!H12,"") | I12: =IF(Navegación!I12<>"",Navegación!I12,"")
B13: Celular | D13: =IF(Navegación!D13<>"",Navegación!D13,"") -> 3150727969 | E13: =IF(Navegación!E13<>"",Navegación!E13,"") | F13: =IF(Navegación!F13<>"",Navegación!F13,"") | G13: =IF(Navegación!G13<>"",Navegación!G13,"") | H13: =IF(Navegación!H13<>"",Navegación!H13,"") | I13: =IF(Navegación!I13<>"",Navegación!I13,"")
B14: Dependencia | D14: =IF(Navegación!D14<>"",Navegación!D14,"") -> Gobierno | E14: =IF(Navegación!E14<>"",Navegación!E14,"") | F14: =IF(Navegación!F14<>"",Navegación!F14,"") | G14: =IF(Navegación!G14<>"",Navegación!G14,"") | H14: =IF(Navegación!H14<>"",Navegación!H14,"") | I14: =IF(Navegación!I14<>"",Navegación!I14,"")
B15: Cargo | D15: =IF(Navegación!D15<>"",Navegación!D15,"") -> Aprendiz Universitario | E15: =IF(Navegación!E15<>"",Navegación!E15,"") | F15: =IF(Navegación!F15<>"",Navegación!F15,"") | G15: =IF(Navegación!G15<>"",Navegación!G15,"") | H15: =IF(Navegación!H15<>"",Navegación!H15,"") | I15: =IF(Navegación!I15<>"",Navegación!I15,"")
B16: Empleado Cafam o Externo | D16: =IF(Navegación!D16<>"",Navegación!D16,"") -> Empleado CAFAM | E16: =IF(Navegación!E16<>"",Navegación!E16,"") | F16: =IF(Navegación!F16<>"",Navegación!F16,"") | G16: =IF(Navegación!G16<>"",Navegación!G16,"") | H16: =IF(Navegación!H16<>"",Navegación!H16,"") | I16: =IF(Navegación!I16<>"",Navegación!I16,"")
B17: Nombre de la empresa cuando es Externo | D17: =IF(Navegación!D17<>"",Navegación!D17,"") | E17: =IF(Navegación!E17<>"",Navegación!E17,"") | F17: =IF(Navegación!F17<>"",Navegación!F17,"") | G17: =IF(Navegación!G17<>"",Navegación!G17,"") | H17: =IF(Navegación!H17<>"",Navegación!H17,"") | I17: =IF(Navegación!I17<>"",Navegación!I17,"")
B18: Fecha inicio contrato: | D18: =IF(Navegación!D18<>"",Navegación!D18,"") -> 45849 | E18: =IF(Navegación!E18<>"",Navegación!E18,"") | F18: =IF(Navegación!F18<>"",Navegación!F18,"") | G18: =IF(Navegación!G18<>"",Navegación!G18,"") | H18: =IF(Navegación!H18<>"",Navegación!H18,"") | I18: =IF(Navegación!I18<>"",Navegación!I18,"")
B19: Fecha finalización contrato: (Si es indefinido escribir 31.12.9999) | D19: =IF(Navegación!D19<>"",Navegación!D19,"") | E19: =IF(Navegación!E19<>"",Navegación!E19,"") | F19: =IF(Navegación!F19<>"",Navegación!F19,"") | G19: =IF(Navegación!G19<>"",Navegación!G19,"") | H19: =IF(Navegación!H19<>"",Navegación!H19,"") | I19: =IF(Navegación!I19<>"",Navegación!I19,"")
B21: Requerimientos Plataforma SAP | D21: =IF(DZ22>0,Navegación!$E$37,"")
B22: Novedad (Crear/Modificación/Baja/Ampliación Vigencia/Reactivar): | DZ22: =COUNTIF(D22:I22,"<>") -> 0
B23: Sistema: (Seleccione los sistemas requeridos)
B24: Ambiente: (Seleccione los ambientes requeridos)
B25: Roles y perfiles (En caso de no conocer los roles, indicar un usuario de copia con las mismas funciones)
B27: Observaciones
DZ30: =COUNTIF(#REF!,"<>") -> #REF!
B32: ='WINDOWS 1'!$B$37 -> APROBADOR POR: Jefe Dpto. Servicios Compartidos | F32: ='WINDOWS 1'!F37 -> V20 de 26/09/2023 | I32: ="Pág. " &Navegación!B37 & " de " &Navegación!$B$102 -> Pág. 13 de 54
DZ34: =COUNTIF(#REF!,"<>") -> #REF!
DZ40: =COUNTIF(#REF!,"<>") -> #REF!
DZ43: =COUNTIF(#REF!,"<>") -> #REF!

Sheet SAP 2
K1: 2958465
C2: FORMATO: GESTIÓN DE IDENTIDADES
F3: DOCUMENTO USO INTERNO
B5: Las celdas resaltadas en Naranja son campos obligatorios del Formato.
B6: Información Usuarios | D6: Usuario 1 | E6: Usuario 2 | F6: Usuario 3 | G6: Usuario 4 | H6: Usuario 5 | I6: Usuario 6
B7: Tipo de documento | D7: =IF(Navegación!D7<>"",Navegación!D7,"") -> Cédula Ciudadanía | E7: =IF(Navegación!E7<>"",Navegación!E7,"") | F7: =IF(Navegación!F7<>"",Navegación!F7,"") | G7: =IF(Navegación!G7<>"",Navegación!G7,"") | H7: =IF(Navegación!H7<>"",Navegación!H7,"") | I7: =IF(Navegación!I7<>"",Navegación!I7,"")
B8: Identificación | D8: =IF(Navegación!D8<>"",Navegación!D8,"") -> 1001089595 | E8: =IF(Navegación!E8<>"",Navegación!E8,"") | F8: =IF(Navegación!F8<>"",Navegación!F8,"") | G8: =IF(Navegación!G8<>"",Navegación!G8,"") | H8: =IF(Navegación!H8<>"",Navegación!H8,"") | I8: =IF(Navegación!I8<>"",Navegación!I8,"")
B9: Nombres completos | D9: =IF(Navegación!D9<>"",Navegación!D9,"") -> JUAN PABLO | E9: =IF(Navegación!E9<>"",Navegación!E9,"") | F9: =IF(Navegación!F9<>"",Navegación!F9,"") | G9: =IF(Navegación!G9<>"",Navegación!G9,"") | H9: =IF(Navegación!H9<>"",Navegación!H9,"") | I9: =IF(Navegación!I9<>"",Navegación!I9,"")
B10: Apellidos completos | D10: =IF(Navegación!D10<>"",Navegación!D10,"") -> CAMPO TELLEZ | E10: =IF(Navegación!E10<>"",Navegación!E10,"") | F10: =IF(Navegación!F10<>"",Navegación!F10,"") | G10: =IF(Navegación!G10<>"",Navegación!G10,"") | H10: =IF(Navegación!H10<>"",Navegación!H10,"") | I10: =IF(Navegación!I10<>"",Navegación!I10,"")
B11: Centro de costo | D11: =IF(Navegación!D11<>"",Navegación!D11,"") -> 856 | E11: =IF(Navegación!E11<>"",Navegación!E11,"") | F11: =IF(Navegación!F11<>"",Navegación!F11,"") | G11: =IF(Navegación!G11<>"",Navegación!G11,"") | H11: =IF(Navegación!H11<>"",Navegación!H11,"") | I11: =IF(Navegación!I11<>"",Navegación!I11,"")
B12: Teléfono/Extensión de contacto del usuario | D12: =IF(Navegación!D12<>"",Navegación!D12,"") | E12: =IF(Navegación!E12<>"",Navegación!E12,"") | F12: =IF(Navegación!F12<>"",Navegación!F12,"") | G12: =IF(Navegación!G12<>"",Navegación!G12,"") | H12: =IF(Navegación!H12<>"",Navegación!H12,"") | I12: =IF(Navegación!I12<>"",Navegación!I12,"")
B13: Celular | D13: =IF(Navegación!D13<>"",Navegación!D13,"") -> 3150727969 | E13: =IF(Navegación!E13<>"",Navegación!E13,"") | F13: =IF(Navegación!F13<>"",Navegación!F13,"") | G13: =IF(Navegación!G13<>"",Navegación!G13,"") | H13: =IF(Navegación!H13<>"",Navegación!H13,"") | I13: =IF(Navegación!I13<>"",Navegación!I13,"")
B14: Dependencia | D14: =IF(Navegación!D14<>"",Navegación!D14,"") -> Gobierno | E14: =IF(Navegación!E14<>"",Navegación!E14,"") | F14: =IF(Navegación!F14<>"",Navegación!F14,"") | G14: =IF(Navegación!G14<>"",Navegación!G14,"") | H14: =IF(Navegación!H14<>"",Navegación!H14,"") | I14: =IF(Navegación!I14<>"",Navegación!I14,"")
B15: Cargo | D15: =IF(Navegación!D15<>"",Navegación!D15,"") -> Aprendiz Universitario | E15: =IF(Navegación!E15<>"",Navegación!E15,"") | F15: =IF(Navegación!F15<>"",Navegación!F15,"") | G15: =IF(Navegación!G15<>"",Navegación!G15,"") | H15: =IF(Navegación!H15<>"",Navegación!H15,"") | I15: =IF(Navegación!I15<>"",Navegación!I15,"")
B16: Empleado Cafam o Externo | D16: =IF(Navegación!D16<>"",Navegación!D16,"") -> Empleado CAFAM | E16: =IF(Navegación!E16<>"",Navegación!E16,"") | F16: =IF(Navegación!F16<>"",Navegación!F16,"") | G16: =IF(Navegación!G16<>"",Navegación!G16,"") | H16: =IF(Navegación!H16<>"",Navegación!H16,"") | I16: =IF(Navegación!I16<>"",Navegación!I16,"")
B17: Nombre de la empresa cuando es Externo | D17: =IF(Navegación!D17<>"",Navegación!D17,"") | E17: =IF(Navegación!E17<>"",Navegación!E17,"") | F17: =IF(Navegación!F17<>"",Navegación!F17,"") | G17: =IF(Navegación!G17<>"",Navegación!G17,"") | H17: =IF(Navegación!H17<>"",Navegación!H17,"") | I17: =IF(Navegación!I17<>"",Navegación!I17,"")
B18: Fecha inicio contrato: | D18: =IF(Navegación!D18<>"",Navegación!D18,"") -> 45849 | E18: =IF(Navegación!E18<>"",Navegación!E18,"") | F18: =IF(Navegación!F18<>"",Navegación!F18,"") | G18: =IF(Navegación!G18<>"",Navegación!G18,"") | H18: =IF(Navegación!H18<>"",Navegación!H18,"") | I18: =IF(Navegación!I18<>"",Navegación!I18,"")
B19: Fecha finalización contrato: (Si es indefinido escribir 31.12.9999) | D19: =IF(Navegación!D19<>"",Navegación!D19,"") | E19: =IF(Navegación!E19<>"",Navegación!E19,"") | F19: =IF(Navegación!F19<>"",Navegación!F19,"") | G19: =IF(Navegación!G19<>"",Navegación!G19,"") | H19: =IF(Navegación!H19<>"",Navegación!H19,"") | I19: =IF(Navegación!I19<>"",Navegación!I19,"")
B21: Solución WEB Roles Y Transacciones SAP | D21: =IF(DZ22>0,Navegación!$E$38,"")
B22: Novedad (Crear/Baja): | DZ22: =COUNTIF(D22:I22,"<>") -> 0
B23: Alias usuario
B24: Perfil:
B26: Observaciones
DZ30: =COUNTIF(D22:I22,"<>") -> 0
B31: ='WINDOWS 1'!$B$37 -> APROBADOR POR: Jefe Dpto. Servicios Compartidos | F31: ='WINDOWS 1'!F37 -> V20 de 26/09/2023 | I31: ="Pág. " &Navegación!B38 & " de " &Navegación!$B$102 -> Pág. 14 de 54
DZ34: =COUNTIF(#REF!,"<>") -> #REF!
DZ40: =COUNTIF(#REF!,"<>") -> #REF!
DZ43: =COUNTIF(#REF!,"<>") -> #REF!

Sheet SAP 3
K1: 2958465
C2: FORMATO: GESTIÓN DE IDENTIDADES
F3: DOCUMENTO USO INTERNO
B5: Las celdas resaltadas en Naranja son campos obligatorios del Formato.
B6: Información Usuarios | D6: Usuario 1 | E6: Usuario 2 | F6: Usuario 3 | G6: Usuario 4 | H6: Usuario 5 | I6: Usuario 6
B7: Tipo de documento | D7: =IF(Navegación!D7<>"",Navegación!D7,"") -> Cédula Ciudadanía | E7: =IF(Navegación!E7<>"",Navegación!E7,"") | F7: =IF(Navegación!F7<>"",Navegación!F7,"") | G7: =IF(Navegación!G7<>"",Navegación!G7,"") | H7: =IF(Navegación!H7<>"",Navegación!H7,"") | I7: =IF(Navegación!I7<>"",Navegación!I7,"")
B8: Identificación | D8: =IF(Navegación!D8<>"",Navegación!D8,"") -> 1001089595 | E8: =IF(Navegación!E8<>"",Navegación!E8,"") | F8: =IF(Navegación!F8<>"",Navegación!F8,"") | G8: =IF(Navegación!G8<>"",Navegación!G8,"") | H8: =IF(Navegación!H8<>"",Navegación!H8,"") | I8: =IF(Navegación!I8<>"",Navegación!I8,"")
B9: Nombres completos | D9: =IF(Navegación!D9<>"",Navegación!D9,"") -> JUAN PABLO | E9: =IF(Navegación!E9<>"",Navegación!E9,"") | F9: =IF(Navegación!F9<>"",Navegación!F9,"") | G9: =IF(Navegación!G9<>"",Navegación!G9,"") | H9: =IF(Navegación!H9<>"",Navegación!H9,"") | I9: =IF(Navegación!I9<>"",Navegación!I9,"")
B10: Apellidos completos | D10: =IF(Navegación!D10<>"",Navegación!D10,"") -> CAMPO TELLEZ | E10: =IF(Navegación!E10<>"",Navegación!E10,"") | F10: =IF(Navegación!F10<>"",Navegación!F10,"") | G10: =IF(Navegación!G10<>"",Navegación!G10,"") | H10: =IF(Navegación!H10<>"",Navegación!H10,"") | I10: =IF(Navegación!I10<>"",Navegación!I10,"")
B11: Centro de costo | D11: =IF(Navegación!D11<>"",Navegación!D11,"") -> 856 | E11: =IF(Navegación!E11<>"",Navegación!E11,"") | F11: =IF(Navegación!F11<>"",Navegación!F11,"") | G11: =IF(Navegación!G11<>"",Navegación!G11,"") | H11: =IF(Navegación!H11<>"",Navegación!H11,"") | I11: =IF(Navegación!I11<>"",Navegación!I11,"")
B12: Teléfono/Extensión de contacto del usuario | D12: =IF(Navegación!D12<>"",Navegación!D12,"") | E12: =IF(Navegación!E12<>"",Navegación!E12,"") | F12: =IF(Navegación!F12<>"",Navegación!F12,"") | G12: =IF(Navegación!G12<>"",Navegación!G12,"") | H12: =IF(Navegación!H12<>"",Navegación!H12,"") | I12: =IF(Navegación!I12<>"",Navegación!I12,"")
B13: Celular | D13: =IF(Navegación!D13<>"",Navegación!D13,"") -> 3150727969 | E13: =IF(Navegación!E13<>"",Navegación!E13,"") | F13: =IF(Navegación!F13<>"",Navegación!F13,"") | G13: =IF(Navegación!G13<>"",Navegación!G13,"") | H13: =IF(Navegación!H13<>"",Navegación!H13,"") | I13: =IF(Navegación!I13<>"",Navegación!I13,"")
B14: Dependencia | D14: =IF(Navegación!D14<>"",Navegación!D14,"") -> Gobierno | E14: =IF(Navegación!E14<>"",Navegación!E14,"") | F14: =IF(Navegación!F14<>"",Navegación!F14,"") | G14: =IF(Navegación!G14<>"",Navegación!G14,"") | H14: =IF(Navegación!H14<>"",Navegación!H14,"") | I14: =IF(Navegación!I14<>"",Navegación!I14,"")
B15: Cargo | D15: =IF(Navegación!D15<>"",Navegación!D15,"") -> Aprendiz Universitario | E15: =IF(Navegación!E15<>"",Navegación!E15,"") | F15: =IF(Navegación!F15<>"",Navegación!F15,"") | G15: =IF(Navegación!G15<>"",Navegación!G15,"") | H15: =IF(Navegación!H15<>"",Navegación!H15,"") | I15: =IF(Navegación!I15<>"",Navegación!I15,"")
B16: Empleado Cafam o Externo | D16: =IF(Navegación!D16<>"",Navegación!D16,"") -> Empleado CAFAM | E16: =IF(Navegación!E16<>"",Navegación!E16,"") | F16: =IF(Navegación!F16<>"",Navegación!F16,"") | G16: =IF(Navegación!G16<>"",Navegación!G16,"") | H16: =IF(Navegación!H16<>"",Navegación!H16,"") | I16: =IF(Navegación!I16<>"",Navegación!I16,"")
B17: Nombre de la empresa cuando es Externo | D17: =IF(Navegación!D17<>"",Navegación!D17,"") | E17: =IF(Navegación!E17<>"",Navegación!E17,"") | F17: =IF(Navegación!F17<>"",Navegación!F17,"") | G17: =IF(Navegación!G17<>"",Navegación!G17,"") | H17: =IF(Navegación!H17<>"",Navegación!H17,"") | I17: =IF(Navegación!I17<>"",Navegación!I17,"")
B18: Fecha inicio contrato: | D18: =IF(Navegación!D18<>"",Navegación!D18,"") -> 45849 | E18: =IF(Navegación!E18<>"",Navegación!E18,"") | F18: =IF(Navegación!F18<>"",Navegación!F18,"") | G18: =IF(Navegación!G18<>"",Navegación!G18,"") | H18: =IF(Navegación!H18<>"",Navegación!H18,"") | I18: =IF(Navegación!I18<>"",Navegación!I18,"")
B19: Fecha finalización contrato: (Si es indefinido escribir 31.12.9999) | D19: =IF(Navegación!D19<>"",Navegación!D19,"") | E19: =IF(Navegación!E19<>"",Navegación!E19,"") | F19: =IF(Navegación!F19<>"",Navegación!F19,"") | G19: =IF(Navegación!G19<>"",Navegación!G19,"") | H19: =IF(Navegación!H19<>"",Navegación!H19,"") | I19: =IF(Navegación!I19<>"",Navegación!I19,"")
B21: Otros Requerimientos Plataforma SAP | D21: =IF(OR(DZ23>0,DZ29>0,DZ32>0),Navegación!$E$39,"")
B22: CASHJOURNAL
B23: Cajas para asignar (Educación, Subsidio, Ambas): | DZ23: =COUNTIF(D23:I23,"<>")+COUNTIF(D29:I29,"<>")+COUNTIF(D32:I32,"<>") -> 0
B24: Función a desempeñar (Cajero, Revisor):
B25: Corresponde a reemplazo o asignación nueva:
B26: Nombre Sucursal:
B27: Nombre de la Caja que tenía anterior si es un traslado, o Nombre de la Caja que reemplaza
B28: FACTURADOR SD
B29: Sector
B30: Canal Distribución
B31: LIBERACIÓN PEDIDOS
B32: Nivel de liberación: (YA, YH, YB, YC, YD)
B33: Grupo de Compras
B35: Observaciones
B40: ='WINDOWS 1'!$B$37 -> APROBADOR POR: Jefe Dpto. Servicios Compartidos | F40: ='WINDOWS 1'!F37 -> V20 de 26/09/2023 | I40: ="Pág. " &Navegación!B39 & " de " &Navegación!$B$102 -> Pág. 15 de 54 | DZ40: =COUNTIF(D29:I29,"<>") -> 0
DZ43: =COUNTIF(D32:I32,"<>") -> 0

Sheet MEDICAMENTOS 1
K1: 2958465
C2: FORMATO: GESTIÓN DE IDENTIDADES
F3: DOCUMENTO USO INTERNO
B5: Las celdas resaltadas en Naranja son campos obligatorios del Formato.
B6: Información Usuarios | D6: Usuario 1 | E6: Usuario 2 | F6: Usuario 3 | G6: Usuario 4 | H6: Usuario 5 | I6: Usuario 6
B7: Tipo de documento | D7: =IF(Navegación!D7<>"",Navegación!D7,"") -> Cédula Ciudadanía | E7: =IF(Navegación!E7<>"",Navegación!E7,"") | F7: =IF(Navegación!F7<>"",Navegación!F7,"") | G7: =IF(Navegación!G7<>"",Navegación!G7,"") | H7: =IF(Navegación!H7<>"",Navegación!H7,"") | I7: =IF(Navegación!I7<>"",Navegación!I7,"")
B8: Identificación | D8: =IF(Navegación!D8<>"",Navegación!D8,"") -> 1001089595 | E8: =IF(Navegación!E8<>"",Navegación!E8,"") | F8: =IF(Navegación!F8<>"",Navegación!F8,"") | G8: =IF(Navegación!G8<>"",Navegación!G8,"") | H8: =IF(Navegación!H8<>"",Navegación!H8,"") | I8: =IF(Navegación!I8<>"",Navegación!I8,"")
B9: Nombres completos | D9: =IF(Navegación!D9<>"",Navegación!D9,"") -> JUAN PABLO | E9: =IF(Navegación!E9<>"",Navegación!E9,"") | F9: =IF(Navegación!F9<>"",Navegación!F9,"") | G9: =IF(Navegación!G9<>"",Navegación!G9,"") | H9: =IF(Navegación!H9<>"",Navegación!H9,"") | I9: =IF(Navegación!I9<>"",Navegación!I9,"")
B10: Apellidos completos | D10: =IF(Navegación!D10<>"",Navegación!D10,"") -> CAMPO TELLEZ | E10: =IF(Navegación!E10<>"",Navegación!E10,"") | F10: =IF(Navegación!F10<>"",Navegación!F10,"") | G10: =IF(Navegación!G10<>"",Navegación!G10,"") | H10: =IF(Navegación!H10<>"",Navegación!H10,"") | I10: =IF(Navegación!I10<>"",Navegación!I10,"")
B11: Centro de costo | D11: =IF(Navegación!D11<>"",Navegación!D11,"") -> 856 | E11: =IF(Navegación!E11<>"",Navegación!E11,"") | F11: =IF(Navegación!F11<>"",Navegación!F11,"") | G11: =IF(Navegación!G11<>"",Navegación!G11,"") | H11: =IF(Navegación!H11<>"",Navegación!H11,"") | I11: =IF(Navegación!I11<>"",Navegación!I11,"")
B12: Teléfono/Extensión de contacto del usuario | D12: =IF(Navegación!D12<>"",Navegación!D12,"") | E12: =IF(Navegación!E12<>"",Navegación!E12,"") | F12: =IF(Navegación!F12<>"",Navegación!F12,"") | G12: =IF(Navegación!G12<>"",Navegación!G12,"") | H12: =IF(Navegación!H12<>"",Navegación!H12,"") | I12: =IF(Navegación!I12<>"",Navegación!I12,"")
B13: Celular | D13: =IF(Navegación!D13<>"",Navegación!D13,"") -> 3150727969 | E13: =IF(Navegación!E13<>"",Navegación!E13,"") | F13: =IF(Navegación!F13<>"",Navegación!F13,"") | G13: =IF(Navegación!G13<>"",Navegación!G13,"") | H13: =IF(Navegación!H13<>"",Navegación!H13,"") | I13: =IF(Navegación!I13<>"",Navegación!I13,"")
B14: Dependencia | D14: =IF(Navegación!D14<>"",Navegación!D14,"") -> Gobierno | E14: =IF(Navegación!E14<>"",Navegación!E14,"") | F14: =IF(Navegación!F14<>"",Navegación!F14,"") | G14: =IF(Navegación!G14<>"",Navegación!G14,"") | H14: =IF(Navegación!H14<>"",Navegación!H14,"") | I14: =IF(Navegación!I14<>"",Navegación!I14,"")
B15: Cargo
B16: Empleado Cafam o Externo | D16: =IF(Navegación!D16<>"",Navegación!D16,"") -> Empleado CAFAM | E16: =IF(Navegación!E16<>"",Navegación!E16,"") | F16: =IF(Navegación!F16<>"",Navegación!F16,"") | G16: =IF(Navegación!G16<>"",Navegación!G16,"") | H16: =IF(Navegación!H16<>"",Navegación!H16,"") | I16: =IF(Navegación!I16<>"",Navegación!I16,"")
B17: Nombre de la empresa cuando es Externo | D17: =IF(Navegación!D17<>"",Navegación!D17,"") | E17: =IF(Navegación!E17<>"",Navegación!E17,"") | F17: =IF(Navegación!F17<>"",Navegación!F17,"") | G17: =IF(Navegación!G17<>"",Navegación!G17,"") | H17: =IF(Navegación!H17<>"",Navegación!H17,"") | I17: =IF(Navegación!I17<>"",Navegación!I17,"")
B18: Fecha inicio contrato: | D18: =IF(Navegación!D18<>"",Navegación!D18,"") -> 45849 | E18: =IF(Navegación!E18<>"",Navegación!E18,"") | F18: =IF(Navegación!F18<>"",Navegación!F18,"") | G18: =IF(Navegación!G18<>"",Navegación!G18,"") | H18: =IF(Navegación!H18<>"",Navegación!H18,"") | I18: =IF(Navegación!I18<>"",Navegación!I18,"")
B19: Fecha finalización contrato: (Si es indefinido escribir 31.12.9999) | D19: =IF(Navegación!D19<>"",Navegación!D19,"") | E19: =IF(Navegación!E19<>"",Navegación!E19,"") | F19: =IF(Navegación!F19<>"",Navegación!F19,"") | G19: =IF(Navegación!G19<>"",Navegación!G19,"") | H19: =IF(Navegación!H19<>"",Navegación!H19,"") | I19: =IF(Navegación!I19<>"",Navegación!I19,"")
B21: Requerimientos Plataformas MEDICAMENTOS
B22: TPNET | D22: =IF(OR(DZ30>0,DZ32>0,DZ34>0,DZ36>0,DZ38>0,DZ40>0),Navegación!$E$42,"")
D23: =ADDRESS(MATCH(D$26,TPNETFuncion[[#All],[Unidad]],0)+249,19,1) -> #N/A | E23: =ADDRESS(MATCH(E$26,TPNETFuncion[[#All],[Unidad]],0)+249,19,1) -> #N/A | F23: =ADDRESS(MATCH(F$26,TPNETFuncion[[#All],[Unidad]],0)+249,19,1) -> #N/A | G23: =ADDRESS(MATCH(G$26,TPNETFuncion[[#All],[Unidad]],0)+249,19,1) -> #N/A | H23: =ADDRESS(MATCH(H$26,TPNETFuncion[[#All],[Unidad]],0)+249,19,1) -> #N/A | I23: =ADDRESS(MATCH(I$26,TPNETFuncion[[#All],[Unidad]],0)+249,19,1) -> #N/A
D24: =ADDRESS(MATCH(D$27,TPNETPerfil[[#All],[Funcion]],)+249,14,1) -> #N/A | E24: =ADDRESS(MATCH(E$27,TPNETPerfil[[#All],[Funcion]],)+249,14,1) -> #N/A | F24: =ADDRESS(MATCH(F$27,TPNETPerfil[[#All],[Funcion]],)+249,14,1) -> #N/A | G24: =ADDRESS(MATCH(G$27,TPNETPerfil[[#All],[Funcion]],)+249,14,1) -> #N/A | H24: =ADDRESS(MATCH(H$27,TPNETPerfil[[#All],[Funcion]],)+249,14,1) -> #N/A | I24: =ADDRESS(MATCH(I$27,TPNETPerfil[[#All],[Funcion]],)+249,14,1) -> #N/A
B25: Alias Usuario
B26: Unidad
B27: Funcion
B28: Perfil
B29: TPAdmin | C29: Ambiente (Pruebas, Producción, Ambos):
C30: Novedad (Alta/Modificación/Inactivar): | DZ30: =COUNTIF(D30:I30,"<>") -> 0
B31: TPAnalyze | C31: Ambiente (Pruebas, Producción, Ambos):
C32: Novedad (Alta/Modificación/Inactivar): | DZ32: =COUNTIF(D32:I32,"<>") -> 0
B33: TPNET POS | C33: Ambiente (Pruebas, Producción, Ambos):
C34: Novedad (Alta/Modificación/Inactivar): | DZ34: =COUNTIF(D34:I34,"<>") -> 0
B35: CUBO (Se maneja con grupo de DA) | C35: Ambiente (Pruebas, Producción, Ambos):
C36: Novedad (Alta/Modificación/Inactivar): | DZ36: =COUNTIF(D36:I36,"<>") -> 0
B37: Backstore | C37: Ambiente (Pruebas, Producción, Ambos):
C38: Novedad (Alta/Modificación/Inactivar): | DZ38: =COUNTIF(D38:I38,"<>") -> 0
B39: TPLovalty | C39: Ambiente (Pruebas, Producción, Ambos):
C40: Novedad (Alta/Modificación/Inactivar): | DZ40: =COUNTIF(D40:I40,"<>") -> 0
B42: Observaciones
B47: ='WINDOWS 1'!$B$37 -> APROBADOR POR: Jefe Dpto. Servicios Compartidos | F47: ='WINDOWS 1'!F37 -> V20 de 26/09/2023 | I47: ="Pág. " &Navegación!B42 & " de " &Navegación!$B$102 -> Pág. 16 de 54
DZ50: =COUNTIF(#REF!,"<>") -> #REF!
DZ54: =COUNTIF(#REF!,"<>") -> #REF!
DZ56: =COUNTIF('MEDICAMENTOS 5'!D23:I23,"<>") -> 0
DZ58: =COUNTIF(#REF!,"<>") -> #REF!
L250: Unidad | M250: Funcion | N250: Perfil | P250: Unidad | R250: Unidad | S250: Funcion
L251: Cartera | M251: Analista Cartera | N251: Analista de Cartera | P251: Cartera | R251: Cartera | S251: Analista Cartera
L252: Cartera | M252: Oficinista Facturacion | N252: Oficinista (Facturación) | P252: Contabilidad | R252: Cartera | S252: Oficinista Facturacion
L253: Contabilidad | M253: Contabilidad | N253: Analista de Contabilidad | P253: CVS | R253: Contabilidad | S253: Contabilidad
L254: CVS | M254: Analista CVS | N254: Analista Operaciones Medicamentos (Control de Activos) | P254: Gerencia Comercial | R254: CVS | S254: Analista CVS
L255: CVS | M255: Control Operación CVS | N255: Gestor Aseguramiento de Operaciones | P255: Gerencia Compras | R255: CVS | S255: Control Operación CVS
L256: CVS | M256: Coordinador CVS | N256: Coordinador Control y Soporte CVS | P256: Gerencia Operaciones | R256: CVS | S256: Coordinador CVS
L257: CVS | M257: Operador CVS | N257: Operador Mesa de Ayuda Medicamentos | P257: Gerencia Vtas Canal Institucional | R257: CVS | S257: Operador CVS
L258: Gerencia Comercial | M258: Administrativo 2 | N258: Prof. Mercadeo Corporativo I | P258: Sistemas Informacion | R258: Gerencia Comercial | S258: Administrativo 2
L259: Gerencia Comercial | M259: Administrativo 2 | N259: Prof. Mercadeo Corporativo II | P259: Tecnología | R259: Gerencia Compras | S259: Compras
L260: Gerencia Compras | M260: Compras | N260: Analista Compras Medicamentos | P260: Unidad Vtas Comerciales | R260: Gerencia Operaciones | S260: Control Operación
L261: Gerencia Compras | M261: Compras | N261: Negociador Medicamentos I | R261: Gerencia Operaciones | S261: Control Productividad
L262: Gerencia Compras | M262: Compras | N262: Negociador Medicamentos II | R262: Gerencia Vtas Canal Institucional | S262: Administrador Punto Vta Cnal Ins
L263: Gerencia Compras | M263: Compras | N263: Oficinista | R263: Gerencia Vtas Canal Institucional | S263: Administrativo 1 Vta Cnal Ins
L264: Gerencia Compras | M264: Compras | N264: Oficinista Compras | R264: Gerencia Vtas Canal Institucional | S264: Agente Contact Center Vta Cnal Ins
L265: Gerencia Operaciones | M265: Control Operación | N265: Revisor Movimiento de Mercancías | R265: Gerencia Vtas Canal Institucional | S265: Operador Punto Vta Cnal Ins
L266: Gerencia Operaciones | M266: Control Operación | N266: Analista Operaciones Medicamentos (Control de Activos) | R266: Gerencia Vtas Canal Institucional | S266: Regente
L267: Gerencia Operaciones | M267: Control Productividad | N267: Analista Operaciones Medicamentos (Malla de Turnos) | R267: Gerencia Vtas Canal Institucional | S267: Revisor Facturacion
L268: Gerencia Operaciones | M268: Control Productividad | N268: Oficinista (Malla de Turnos) | R268: Sistemas Informacion | S268: Analisis Informacion
L269: Gerencia Vtas Canal Institucional | M269: Administrador Punto Vta Cnal Ins | N269: Administrador de Punto | R269: Sistemas Informacion | S269: Apoyo Datos Maestros
L270: Gerencia Vtas Canal Institucional | M270: Administrador Punto Vta Cnal Ins | N270: Supervisor Zonal Medicamentos | R270: Sistemas Informacion | S270: Lider Datos Maestros
L271: Gerencia Vtas Canal Institucional | M271: Administrativo 1 Vta Cnal Ins | N271: Analista Convenios Institucionales | R271: Tecnología | S271: Especialista Soporte
L272: Gerencia Vtas Canal Institucional | M272: Administrativo 1 Vta Cnal Ins | N272: Profesional Medicamentos Institucionales | R272: Tecnología | S272: Gestión Identidades
... L279: Gerencia Vtas Canal Institucional | M279: Administrativo 1 Vta Cnal Ins | N279: Supervisor Ventas Institucionales | R279: Unidad Vtas Comerciales | S279: Operador Punto
L280: Gerencia Vtas Canal Institucional | M280: Administrativo 1 Vta Cnal Ins | N280: Administrador Operaciones
L281: Gerencia Vtas Canal Institucional | M281: Administrativo 1 Vta Cnal Ins | N281: Supervisor Ejecutivos III
L282: Gerencia Vtas Canal Institucional | M282: Agente Contact Center Vta Cnal Ins | N282: Agente Contact Center
L283: Gerencia Vtas Canal Institucional | M283: Operador Punto Vta Cnal Ins | N283: Vendedor Farmacia
L284: Gerencia Vtas Canal Institucional | M284: Regente | N284: Regente de Farmacia
L285: Gerencia Vtas Canal Institucional | M285: Revisor Facturacion | N285: Analista Operaciones Medicamentos
L286: Sistemas Informacion | M286: Analisis Informacion | N286: Oficinista Sistemas de Informacion y Proyectos
L287: Sistemas Informacion | M287: Apoyo Datos Maestros | N287: Oficinista Sistemas de Informacion y Proyectos
L288: Sistemas Informacion | M288: Lider Datos Maestros | N288: Coodinador Sistemas de Informacion y Proyectos
L289: Sistemas Informacion | M289: Lider Datos Maestros | N289: Analista Sistemas de Informacion y Proyectos
L290: Tecnología | M290: Especialista Soporte | N290: Soporte Operaciones TI
L291: Tecnología | M291: Gestión Identidades | N291: Operador Gestion Identidades
... L303: Unidad Vtas Comerciales | M303: Operador Punto | N303: Vendedor Farmacia

Sheet MEDICAMENTOS 4
D2: SOLICITUD DE ADMINISTRACIÓN DE CUENTAS DE USUARIO MEDIC@R | I2: VERSIÓN: 1 FECHA: 05-09-2022
B5: CONVENIO | C5: NOVEDAD Activación (A) Inactivación (I) Creación ( C) | D5: LOGIN | E5: NOMBRE | F5: PERFIL MEDIC@R | G5: CENTRO DE COSTOS | H5: EMAIL (Opcional) | I5: OBSERVACIONES | AB5: Perfil | AD5: Convenio | AF5: Novedad
AB6: Administrador | AD6: Aliados | AF6: CREACION
AB7: Autorizador anulacion por monto | AD7: Alianza COC | AF7: INACTIVACION
AB8: Certificador | AD8: CADUCEO | AF8: ACTIVACION
AB9: Mesa de control | AD9: COLMENA
AB10: Mixto | AD10: COMFENALCO
AB11: Regente Mixto | AD11: EPS Bolivar
AB12: Soporte Tecnologia CAFAM | AD12: ETB
AB13: Sistemas de Información | AD13: FAMISANAR
AB14: Super Despachador | AD14: Nueva EPS
AD15: QUICK HELP
AD16: Seguros Bolivar
AD17: SERVIMED
AD18: Union Temporal
AD19: Venta Comercial

Sheet MEDICAMENTOS 2
K1: 2958465
C2: FORMATO: GESTIÓN DE IDENTIDADES
F3: DOCUMENTO USO INTERNO
B5: Las celdas resaltadas en Naranja son campos obligatorios del Formato.
B6: Información Usuarios | D6: Usuario 1 | E6: Usuario 2 | F6: Usuario 3 | G6: Usuario 4 | H6: Usuario 5 | I6: Usuario 6
B7: Tipo de documento | D7: =IF(Navegación!D7<>"",Navegación!D7,"") -> Cédula Ciudadanía | E7: =IF(Navegación!E7<>"",Navegación!E7,"") | F7: =IF(Navegación!F7<>"",Navegación!F7,"") | G7: =IF(Navegación!G7<>"",Navegación!G7,"") | H7: =IF(Navegación!H7<>"",Navegación!H7,"") | I7: =IF(Navegación!I7<>"",Navegación!I7,"")
B8: Identificación | D8: =IF(Navegación!D8<>"",Navegación!D8,"") -> 1001089595 | E8: =IF(Navegación!E8<>"",Navegación!E8,"") | F8: =IF(Navegación!F8<>"",Navegación!F8,"") | G8: =IF(Navegación!G8<>"",Navegación!G8,"") | H8: =IF(Navegación!H8<>"",Navegación!H8,"") | I8: =IF(Navegación!I8<>"",Navegación!I8,"")
B9: Nombres completos | D9: =IF(Navegación!D9<>"",Navegación!D9,"") -> JUAN PABLO | E9: =IF(Navegación!E9<>"",Navegación!E9,"") | F9: =IF(Navegación!F9<>"",Navegación!F9,"") | G9: =IF(Navegación!G9<>"",Navegación!G9,"") | H9: =IF(Navegación!H9<>"",Navegación!H9,"") | I9: =IF(Navegación!I9<>"",Navegación!I9,"")
B10: Apellidos completos | D10: =IF(Navegación!D10<>"",Navegación!D10,"") -> CAMPO TELLEZ | E10: =IF(Navegación!E10<>"",Navegación!E10,"") | F10: =IF(Navegación!F10<>"",Navegación!F10,"") | G10: =IF(Navegación!G10<>"",Navegación!G10,"") | H10: =IF(Navegación!H10<>"",Navegación!H10,"") | I10: =IF(Navegación!I10<>"",Navegación!I10,"")
B11: Centro de costo | D11: =IF(Navegación!D11<>"",Navegación!D11,"") -> 856 | E11: =IF(Navegación!E11<>"",Navegación!E11,"") | F11: =IF(Navegación!F11<>"",Navegación!F11,"") | G11: =IF(Navegación!G11<>"",Navegación!G11,"") | H11: =IF(Navegación!H11<>"",Navegación!H11,"") | I11: =IF(Navegación!I11<>"",Navegación!I11,"")
B12: Teléfono/Extensión de contacto del usuario | D12: =IF(Navegación!D12<>"",Navegación!D12,"") | E12: =IF(Navegación!E12<>"",Navegación!E12,"") | F12: =IF(Navegación!F12<>"",Navegación!F12,"") | G12: =IF(Navegación!G12<>"",Navegación!G12,"") | H12: =IF(Navegación!H12<>"",Navegación!H12,"") | I12: =IF(Navegación!I12<>"",Navegación!I12,"")
B13: Celular | D13: =IF(Navegación!D13<>"",Navegación!D13,"") -> 3150727969 | E13: =IF(Navegación!E13<>"",Navegación!E13,"") | F13: =IF(Navegación!F13<>"",Navegación!F13,"") | G13: =IF(Navegación!G13<>"",Navegación!G13,"") | H13: =IF(Navegación!H13<>"",Navegación!H13,"") | I13: =IF(Navegación!I13<>"",Navegación!I13,"")
B14: Dependencia | D14: =IF(Navegación!D14<>"",Navegación!D14,"") -> Gobierno | E14: =IF(Navegación!E14<>"",Navegación!E14,"") | F14: =IF(Navegación!F14<>"",Navegación!F14,"") | G14: =IF(Navegación!G14<>"",Navegación!G14,"") | H14: =IF(Navegación!H14<>"",Navegación!H14,"") | I14: =IF(Navegación!I14<>"",Navegación!I14,"")
B15: Cargo
B16: Empleado Cafam o Externo | D16: =IF(Navegación!D16<>"",Navegación!D16,"") -> Empleado CAFAM | E16: =IF(Navegación!E16<>"",Navegación!E16,"") | F16: =IF(Navegación!F16<>"",Navegación!F16,"") | G16: =IF(Navegación!G16<>"",Navegación!G16,"") | H16: =IF(Navegación!H16<>"",Navegación!H16,"") | I16: =IF(Navegación!I16<>"",Navegación!I16,"")
B17: Nombre de la empresa cuando es Externo | D17: =IF(Navegación!D17<>"",Navegación!D17,"") | E17: =IF(Navegación!E17<>"",Navegación!E17,"") | F17: =IF(Navegación!F17<>"",Navegación!F17,"") | G17: =IF(Navegación!G17<>"",Navegación!G17,"") | H17: =IF(Navegación!H17<>"",Navegación!H17,"") | I17: =IF(Navegación!I17<>"",Navegación!I17,"")
B18: Fecha inicio contrato: | D18: =IF(Navegación!D18<>"",Navegación!D18,"") -> 45849 | E18: =IF(Navegación!E18<>"",Navegación!E18,"") | F18: =IF(Navegación!F18<>"",Navegación!F18,"") | G18: =IF(Navegación!G18<>"",Navegación!G18,"") | H18: =IF(Navegación!H18<>"",Navegación!H18,"") | I18: =IF(Navegación!I18<>"",Navegación!I18,"")
B19: Fecha finalización contrato: (Si es indefinido escribir 31.12.9999) | D19: =IF(Navegación!D19<>"",Navegación!D19,"") | E19: =IF(Navegación!E19<>"",Navegación!E19,"") | F19: =IF(Navegación!F19<>"",Navegación!F19,"") | G19: =IF(Navegación!G19<>"",Navegación!G19,"") | H19: =IF(Navegación!H19<>"",Navegación!H19,"") | I19: =IF(Navegación!I19<>"",Navegación!I19,"")
B21: Requerimientos Plataformas MEDICAMENTOS
B22: WMS | D22: =IF(DZ23>0,Navegación!$E$43,"")
B23: Novedad (Crear/Modificar/Inactivar): | DZ23: =COUNTIF(D23:I23,"<>") -> 0
B24: Ambiente (Pruebas, Producción, Ambos):
B25: Rol Funcional
B26: Rol Sistemico
B27: Alias Usuario
B28: Sucursal
B29: Compañía
B31: Observaciones
DZ32: =COUNTIF(#REF!,"<>") -> #REF!
DZ34: =COUNTIF(#REF!,"<>") -> #REF!
B36: ='WINDOWS 1'!$B$37 -> APROBADOR POR: Jefe Dpto. Servicios Compartidos | F36: ='WINDOWS 1'!F37 -> V20 de 26/09/2023 | I36: ="Pág. " &Navegación!B43 & " de " &Navegación!$B$102 -> Pág. 17 de 54 | DZ36: =COUNTIF(#REF!,"<>") -> #REF!
DZ38: =COUNTIF(#REF!,"<>") -> #REF!
DZ40: =COUNTIF(#REF!,"<>") -> #REF!
DZ42: =COUNTIF(D23:I23,"<>") -> 0
DZ50: =COUNTIF(#REF!,"<>") -> #REF!
DZ54: =COUNTIF(#REF!,"<>") -> #REF!
DZ56: =COUNTIF('MEDICAMENTOS 5'!D23:I23,"<>") -> 0
DZ58: =COUNTIF(#REF!,"<>") -> #REF!

Sheet MEDICAMENTOS 3
K1: 2958465
C2: FORMATO: GESTIÓN DE IDENTIDADES
F3: DOCUMENTO USO INTERNO
B5: Las celdas resaltadas en Naranja son campos obligatorios del Formato.
B6: Información Usuarios | D6: Usuario 1 | E6: Usuario 2 | F6: Usuario 3 | G6: Usuario 4 | H6: Usuario 5 | I6: Usuario 6
B7: Tipo de documento | D7: =IF(Navegación!D7<>"",Navegación!D7,"") -> Cédula Ciudadanía | E7: =IF(Navegación!E7<>"",Navegación!E7,"") | F7: =IF(Navegación!F7<>"",Navegación!F7,"") | G7: =IF(Navegación!G7<>"",Navegación!G7,"") | H7: =IF(Navegación!H7<>"",Navegación!H7,"") | I7: =IF(Navegación!I7<>"",Navegación!I7,"")
B8: Identificación | D8: =IF(Navegación!D8<>"",Navegación!D8,"") -> 1001089595 | E8: =IF(Navegación!E8<>"",Navegación!E8,"") | F8: =IF(Navegación!F8<>"",Navegación!F8,"") | G8: =IF(Navegación!G8<>"",Navegación!G8,"") | H8: =IF(Navegación!H8<>"",Navegación!H8,"") | I8: =IF(Navegación!I8<>"",Navegación!I8,"")
B9: Nombres completos | D9: =IF(Navegación!D9<>"",Navegación!D9,"") -> JUAN PABLO | E9: =IF(Navegación!E9<>"",Navegación!E9,"") | F9: =IF(Navegación!F9<>"",Navegación!F9,"") | G9: =IF(Navegación!G9<>"",Navegación!G9,"") | H9: =IF(Navegación!H9<>"",Navegación!H9,"") | I9: =IF(Navegación!I9<>"",Navegación!I9,"")
B10: Apellidos completos | D10: =IF(Navegación!D10<>"",Navegación!D10,"") -> CAMPO TELLEZ | E10: =IF(Navegación!E10<>"",Navegación!E10,"") | F10: =IF(Navegación!F10<>"",Navegación!F10,"") | G10: =IF(Navegación!G10<>"",Navegación!G10,"") | H10: =IF(Navegación!H10<>"",Navegación!H10,"") | I10: =IF(Navegación!I10<>"",Navegación!I10,"")
B11: Centro de costo | D11: =IF(Navegación!D11<>"",Navegación!D11,"") -> 856 | E11: =IF(Navegación!E11<>"",Navegación!E11,"") | F11: =IF(Navegación!F11<>"",Navegación!F11,"") | G11: =IF(Navegación!G11<>"",Navegación!G11,"") | H11: =IF(Navegación!H11<>"",Navegación!H11,"") | I11: =IF(Navegación!I11<>"",Navegación!I11,"")
B12: Teléfono/Extensión de contacto del usuario | D12: =IF(Navegación!D12<>"",Navegación!D12,"") | E12: =IF(Navegación!E12<>"",Navegación!E12,"") | F12: =IF(Navegación!F12<>"",Navegación!F12,"") | G12: =IF(Navegación!G12<>"",Navegación!G12,"") | H12: =IF(Navegación!H12<>"",Navegación!H12,"") | I12: =IF(Navegación!I12<>"",Navegación!I12,"")
B13: Celular | D13: =IF(Navegación!D13<>"",Navegación!D13,"") -> 3150727969 | E13: =IF(Navegación!E13<>"",Navegación!E13,"") | F13: =IF(Navegación!F13<>"",Navegación!F13,"") | G13: =IF(Navegación!G13<>"",Navegación!G13,"") | H13: =IF(Navegación!H13<>"",Navegación!H13,"") | I13: =IF(Navegación!I13<>"",Navegación!I13,"")
B14: Dependencia | D14: =IF(Navegación!D14<>"",Navegación!D14,"") -> Gobierno | E14: =IF(Navegación!E14<>"",Navegación!E14,"") | F14: =IF(Navegación!F14<>"",Navegación!F14,"") | G14: =IF(Navegación!G14<>"",Navegación!G14,"") | H14: =IF(Navegación!H14<>"",Navegación!H14,"") | I14: =IF(Navegación!I14<>"",Navegación!I14,"")
B15: Cargo
B16: Empleado Cafam o Externo | D16: =IF(Navegación!D16<>"",Navegación!D16,"") -> Empleado CAFAM | E16: =IF(Navegación!E16<>"",Navegación!E16,"") | F16: =IF(Navegación!F16<>"",Navegación!F16,"") | G16: =IF(Navegación!G16<>"",Navegación!G16,"") | H16: =IF(Navegación!H16<>"",Navegación!H16,"") | I16: =IF(Navegación!I16<>"",Navegación!I16,"")
B17: Nombre de la empresa cuando es Externo | D17: =IF(Navegación!D17<>"",Navegación!D17,"") | E17: =IF(Navegación!E17<>"",Navegación!E17,"") | F17: =IF(Navegación!F17<>"",Navegación!F17,"") | G17: =IF(Navegación!G17<>"",Navegación!G17,"") | H17: =IF(Navegación!H17<>"",Navegación!H17,"") | I17: =IF(Navegación!I17<>"",Navegación!I17,"")
B18: Fecha inicio contrato: | D18: =IF(Navegación!D18<>"",Navegación!D18,"") -> 45849 | E18: =IF(Navegación!E18<>"",Navegación!E18,"") | F18: =IF(Navegación!F18<>"",Navegación!F18,"") | G18: =IF(Navegación!G18<>"",Navegación!G18,"") | H18: =IF(Navegación!H18<>"",Navegación!H18,"") | I18: =IF(Navegación!I18<>"",Navegación!I18,"")
B19: Fecha finalización contrato: (Si es indefinido escribir 31.12.9999) | D19: =IF(Navegación!D19<>"",Navegación!D19,"") | E19: =IF(Navegación!E19<>"",Navegación!E19,"") | F19: =IF(Navegación!F19<>"",Navegación!F19,"") | G19: =IF(Navegación!G19<>"",Navegación!G19,"") | H19: =IF(Navegación!H19<>"",Navegación!H19,"") | I19: =IF(Navegación!I19<>"",Navegación!I19,"")
B21: Requerimientos Plataformas MEDICAMENTOS
B22: SIGED | D22: =IF(OR(DZ23>0,DZ27>0),Navegación!$E$44,"")
B23: Novedad | DZ23: =COUNTIF(D23:I23,"<>") -> 0
B24: Perfil
B25: Detalle
B26: Recursos IFS
B27: Novedad de acceso | DZ27: =COUNTIF(D27:I27,"<>") -> 0
B28: Ruta de acceso
B30: Observaciones
DZ34: =COUNTIF(#REF!,"<>") -> #REF!
B35: ='WINDOWS 1'!$B$37 -> APROBADOR POR: Jefe Dpto. Servicios Compartidos | F35: ='WINDOWS 1'!F37 -> V20 de 26/09/2023 | I35: ="Pág. " &Navegación!B44 & " de " &Navegación!$B$102 -> Pág. 18 de 54
DZ36: =COUNTIF(#REF!,"<>") -> #REF!
DZ38: =COUNTIF(#REF!,"<>") -> #REF!
DZ40: =COUNTIF(#REF!,"<>") -> #REF!
DZ42: =COUNTIF(#REF!,"<>") -> #REF!
DZ50: =COUNTIF(D23:I23,"<>") -> 0
DZ54: =COUNTIF(#REF!,"<>") -> #REF!
DZ56: =COUNTIF('MEDICAMENTOS 5'!D23:I23,"<>") -> 0
DZ58: =COUNTIF(#REF!,"<>") -> #REF!
L250: Unidad | M250: Funcion | N250: Perfil | P250: Unidad | R250: Unidad | S250: Funcion
L251: Cartera | M251: Analista Cartera | N251: Analista de Cartera | P251: Cartera | R251: Cartera | S251: Analista Cartera
L252: Cartera | M252: Oficinista Facturacion | N252: Oficinista (Facturación) | P252: Contabilidad | R252: Cartera | S252: Oficinista Facturacion
L253: Contabilidad | M253: Contabilidad | N253: Analista de Contabilidad | P253: CVS | R253: Contabilidad | S253: Contabilidad
L254: CVS | M254: Analista CVS | N254: Analista Operaciones Medicamentos (Control de Activos) | P254: Gerencia Comercial | R254: CVS | S254: Analista CVS
L255: CVS | M255: Control Operación CVS | N255: Gestor Aseguramiento de Operaciones | P255: Gerencia Compras | R255: CVS | S255: Control Operación CVS
L256: CVS | M256: Coordinador CVS | N256: Coordinador Control y Soporte CVS | P256: Gerencia Operaciones | R256: CVS | S256: Coordinador CVS
L257: CVS | M257: Operador CVS | N257: Operador Mesa de Ayuda Medicamentos | P257: Gerencia Vtas Canal Institucional | R257: CVS | S257: Operador CVS
L258: Gerencia Comercial | M258: Administrativo 2 | N258: Prof. Mercadeo Corporativo I | P258: Sistemas Informacion | R258: Gerencia Comercial | S258: Administrativo 2
L259: Gerencia Comercial | M259: Administrativo 2 | N259: Prof. Mercadeo Corporativo II | P259: Tecnología | R259: Gerencia Compras | S259: Compras
L260: Gerencia Compras | M260: Compras | N260: Analista Compras Medicamentos | P260: Unidad Vtas Comerciales | R260: Gerencia Operaciones | S260: Control Operación
L261: Gerencia Compras | M261: Compras | N261: Negociador Medicamentos I | R261: Gerencia Operaciones | S261: Control Productividad
L262: Gerencia Compras | M262: Compras | N262: Negociador Medicamentos II | R262: Gerencia Vtas Canal Institucional | S262: Administrador Punto Vta Cnal Ins
L263: Gerencia Compras | M263: Compras | N263: Oficinista | R263: Gerencia Vtas Canal Institucional | S263: Administrativo 1 Vta Cnal Ins
L264: Gerencia Compras | M264: Compras | N264: Oficinista Compras | R264: Gerencia Vtas Canal Institucional | S264: Agente Contact Center Vta Cnal Ins
L265: Gerencia Operaciones | M265: Control Operación | N265: Revisor Movimiento de Mercancías | R265: Gerencia Vtas Canal Institucional | S265: Operador Punto Vta Cnal Ins
L266: Gerencia Operaciones | M266: Control Operación | N266: Analista Operaciones Medicamentos (Control de Activos) | R266: Gerencia Vtas Canal Institucional | S266: Regente
L267: Gerencia Operaciones | M267: Control Productividad | N267: Analista Operaciones Medicamentos (Malla de Turnos) | R267: Gerencia Vtas Canal Institucional | S267: Revisor Facturacion
L268: Gerencia Operaciones | M268: Control Productividad | N268: Oficinista (Malla de Turnos) | R268: Sistemas Informacion | S268: Analisis Informacion
L269: Gerencia Vtas Canal Institucional | M269: Administrador Punto Vta Cnal Ins | N269: Administrador de Punto | R269: Sistemas Informacion | S269: Apoyo Datos Maestros
L270: Gerencia Vtas Canal Institucional | M270: Administrador Punto Vta Cnal Ins | N270: Supervisor Zonal Medicamentos | R270: Sistemas Informacion | S270: Lider Datos Maestros
L271: Gerencia Vtas Canal Institucional | M271: Administrativo 1 Vta Cnal Ins | N271: Analista Convenios Institucionales | R271: Tecnología | S271: Especialista Soporte
L272: Gerencia Vtas Canal Institucional | M272: Administrativo 1 Vta Cnal Ins | N272: Profesional Medicamentos Institucionales | R272: Tecnología | S272: Gestión Identidades
... L279: Gerencia Vtas Canal Institucional | M279: Administrativo 1 Vta Cnal Ins | N279: Supervisor Ventas Institucionales | R279: Unidad Vtas Comerciales | S279: Operador Punto
L280: Gerencia Vtas Canal Institucional | M280: Administrativo 1 Vta Cnal Ins | N280: Administrador Operaciones
L281: Gerencia Vtas Canal Institucional | M281: Administrativo 1 Vta Cnal Ins | N281: Supervisor Ejecutivos III
L282: Gerencia Vtas Canal Institucional | M282: Agente Contact Center Vta Cnal Ins | N282: Agente Contact Center
L283: Gerencia Vtas Canal Institucional | M283: Operador Punto Vta Cnal Ins | N283: Vendedor Farmacia
L284: Gerencia Vtas Canal Institucional | M284: Regente | N284: Regente de Farmacia
L285: Gerencia Vtas Canal Institucional | M285: Revisor Facturacion | N285: Analista Operaciones Medicamentos
L286: Sistemas Informacion | M286: Analisis Informacion | N286: Oficinista Sistemas de Informacion y Proyectos
L287: Sistemas Informacion | M287: Apoyo Datos Maestros | N287: Oficinista Sistemas de Informacion y Proyectos
L288: Sistemas Informacion | M288: Lider Datos Maestros | N288: Coodinador Sistemas de Informacion y Proyectos
L289: Sistemas Informacion | M289: Lider Datos Maestros | N289: Analista Sistemas de Informacion y Proyectos
L290: Tecnología | M290: Especialista Soporte | N290: Soporte Operaciones TI
L291: Tecnología | M291: Gestión Identidades | N291: Operador Gestion Identidades
... L303: Unidad Vtas Comerciales | M303: Operador Punto | N303: Vendedor Farmacia

Sheet MEDICAMENTOS 5
K1: 2958465
C2: FORMATO: GESTIÓN DE IDENTIDADES
F3: DOCUMENTO USO INTERNO
B5: Las celdas resaltadas en Naranja son campos obligatorios del Formato.
B6: Información Usuarios | D6: Usuario 1 | E6: Usuario 2 | F6: Usuario 3 | G6: Usuario 4 | H6: Usuario 5 | I6: Usuario 6
B7: Tipo de documento | D7: =IF(Navegación!D7<>"",Navegación!D7,"") -> Cédula Ciudadanía | E7: =IF(Navegación!E7<>"",Navegación!E7,"") | F7: =IF(Navegación!F7<>"",Navegación!F7,"") | G7: =IF(Navegación!G7<>"",Navegación!G7,"") | H7: =IF(Navegación!H7<>"",Navegación!H7,"") | I7: =IF(Navegación!I7<>"",Navegación!I7,"")
B8: Identificación | D8: =IF(Navegación!D8<>"",Navegación!D8,"") -> 1001089595 | E8: =IF(Navegación!E8<>"",Navegación!E8,"") | F8: =IF(Navegación!F8<>"",Navegación!F8,"") | G8: =IF(Navegación!G8<>"",Navegación!G8,"") | H8: =IF(Navegación!H8<>"",Navegación!H8,"") | I8: =IF(Navegación!I8<>"",Navegación!I8,"")
B9: Nombres completos | D9: =IF(Navegación!D9<>"",Navegación!D9,"") -> JUAN PABLO | E9: =IF(Navegación!E9<>"",Navegación!E9,"") | F9: =IF(Navegación!F9<>"",Navegación!F9,"") | G9: =IF(Navegación!G9<>"",Navegación!G9,"") | H9: =IF(Navegación!H9<>"",Navegación!H9,"") | I9: =IF(Navegación!I9<>"",Navegación!I9,"")
B10: Apellidos completos | D10: =IF(Navegación!D10<>"",Navegación!D10,"") -> CAMPO TELLEZ | E10: =IF(Navegación!E10<>"",Navegación!E10,"") | F10: =IF(Navegación!F10<>"",Navegación!F10,"") | G10: =IF(Navegación!G10<>"",Navegación!G10,"") | H10: =IF(Navegación!H10<>"",Navegación!H10,"") | I10: =IF(Navegación!I10<>"",Navegación!I10,"")
B11: Centro de costo | D11: =IF(Navegación!D11<>"",Navegación!D11,"") -> 856 | E11: =IF(Navegación!E11<>"",Navegación!E11,"") | F11: =IF(Navegación!F11<>"",Navegación!F11,"") | G11: =IF(Navegación!G11<>"",Navegación!G11,"") | H11: =IF(Navegación!H11<>"",Navegación!H11,"") | I11: =IF(Navegación!I11<>"",Navegación!I11,"")
B12: Teléfono/Extensión de contacto del usuario | D12: =IF(Navegación!D12<>"",Navegación!D12,"") | E12: =IF(Navegación!E12<>"",Navegación!E12,"") | F12: =IF(Navegación!F12<>"",Navegación!F12,"") | G12: =IF(Navegación!G12<>"",Navegación!G12,"") | H12: =IF(Navegación!H12<>"",Navegación!H12,"") | I12: =IF(Navegación!I12<>"",Navegación!I12,"")
B13: Celular | D13: =IF(Navegación!D13<>"",Navegación!D13,"") -> 3150727969 | E13: =IF(Navegación!E13<>"",Navegación!E13,"") | F13: =IF(Navegación!F13<>"",Navegación!F13,"") | G13: =IF(Navegación!G13<>"",Navegación!G13,"") | H13: =IF(Navegación!H13<>"",Navegación!H13,"") | I13: =IF(Navegación!I13<>"",Navegación!I13,"")
B14: Dependencia | D14: =IF(Navegación!D14<>"",Navegación!D14,"") -> Gobierno | E14: =IF(Navegación!E14<>"",Navegación!E14,"") | F14: =IF(Navegación!F14<>"",Navegación!F14,"") | G14: =IF(Navegación!G14<>"",Navegación!G14,"") | H14: =IF(Navegación!H14<>"",Navegación!H14,"") | I14: =IF(Navegación!I14<>"",Navegación!I14,"")
B15: Cargo | D15: =IF(Navegación!D15<>"",Navegación!D15,"") -> Aprendiz Universitario | E15: =IF(Navegación!E15<>"",Navegación!E15,"") | F15: =IF(Navegación!F15<>"",Navegación!F15,"") | G15: =IF(Navegación!G15<>"",Navegación!G15,"") | H15: =IF(Navegación!H15<>"",Navegación!H15,"") | I15: =IF(Navegación!I15<>"",Navegación!I15,"")
B16: Empleado Cafam o Externo | D16: =IF(Navegación!D16<>"",Navegación!D16,"") -> Empleado CAFAM | E16: =IF(Navegación!E16<>"",Navegación!E16,"") | F16: =IF(Navegación!F16<>"",Navegación!F16,"") | G16: =IF(Navegación!G16<>"",Navegación!G16,"") | H16: =IF(Navegación!H16<>"",Navegación!H16,"") | I16: =IF(Navegación!I16<>"",Navegación!I16,"")
B17: Nombre de la empresa cuando es Externo | D17: =IF(Navegación!D17<>"",Navegación!D17,"") | E17: =IF(Navegación!E17<>"",Navegación!E17,"") | F17: =IF(Navegación!F17<>"",Navegación!F17,"") | G17: =IF(Navegación!G17<>"",Navegación!G17,"") | H17: =IF(Navegación!H17<>"",Navegación!H17,"") | I17: =IF(Navegación!I17<>"",Navegación!I17,"")
B18: Fecha inicio contrato: | D18: =IF(Navegación!D18<>"",Navegación!D18,"") -> 45849 | E18: =IF(Navegación!E18<>"",Navegación!E18,"") | F18: =IF(Navegación!F18<>"",Navegación!F18,"") | G18: =IF(Navegación!G18<>"",Navegación!G18,"") | H18: =IF(Navegación!H18<>"",Navegación!H18,"") | I18: =IF(Navegación!I18<>"",Navegación!I18,"")
B19: Fecha finalización contrato: (Si es indefinido escribir 31.12.9999) | D19: =IF(Navegación!D19<>"",Navegación!D19,"") | E19: =IF(Navegación!E19<>"",Navegación!E19,"") | F19: =IF(Navegación!F19<>"",Navegación!F19,"") | G19: =IF(Navegación!G19<>"",Navegación!G19,"") | H19: =IF(Navegación!H19<>"",Navegación!H19,"") | I19: =IF(Navegación!I19<>"",Navegación!I19,"")
B21: Requerimientos Plataformas MEDICAMENTOS - MULTICANAL
B22: GO- Domicilios.com | D22: =IF(DZ23>0,Navegación!$E$46,"")
B23: Novedad (Crear/Modificar/Inactivar): | DZ23: =COUNTIF(D23:I23,"<>") -> 0
B24: CeCo | H24: =IFERROR(INDEX(SharePoint!$CI$1:$CI$20,MATCH('MEDICAMENTOS 5'!H$25,SharePoint!#REF!,),MATCH($B$24,SharePoint!$CI$1:$CI$1,)),"") | I24: =IFERROR(INDEX(SharePoint!$CI$1:$CI$20,MATCH('MEDICAMENTOS 5'!I$25,SharePoint!#REF!,),MATCH($B$24,SharePoint!$CI$1:$CI$1,)),"")
B25: Correo (Usuario/Drogueria)
B26: Contraseña (Dato entregado por el proveedor)
B27: Lider Zonal (No aplica para usuarios nombrados)
B29: Observaciones
B34: ='WINDOWS 1'!$B$37 -> APROBADOR POR: Jefe Dpto. Servicios Compartidos | F34: ='WINDOWS 1'!F37 -> V20 de 26/09/2023 | I34: ="Pág. " &Navegación!B46 & " de " &Navegación!$B$102 -> Pág. 20 de 54

Sheet MEDICAMENTOS 6
K1: 2958465
C2: FORMATO: GESTIÓN DE IDENTIDADES
F3: DOCUMENTO USO INTERNO
B5: Las celdas resaltadas en Naranja son campos obligatorios del Formato.
B6: Información Usuarios | D6: Usuario 1 | E6: Usuario 2 | F6: Usuario 3 | G6: Usuario 4 | H6: Usuario 5 | I6: Usuario 6
B7: Tipo de documento | D7: =IF(Navegación!D7<>"",Navegación!D7,"") -> Cédula Ciudadanía | E7: =IF(Navegación!E7<>"",Navegación!E7,"") | F7: =IF(Navegación!F7<>"",Navegación!F7,"") | G7: =IF(Navegación!G7<>"",Navegación!G7,"") | H7: =IF(Navegación!H7<>"",Navegación!H7,"") | I7: =IF(Navegación!I7<>"",Navegación!I7,"")
B8: Identificación | D8: =IF(Navegación!D8<>"",Navegación!D8,"") -> 1001089595 | E8: =IF(Navegación!E8<>"",Navegación!E8,"") | F8: =IF(Navegación!F8<>"",Navegación!F8,"") | G8: =IF(Navegación!G8<>"",Navegación!G8,"") | H8: =IF(Navegación!H8<>"",Navegación!H8,"") | I8: =IF(Navegación!I8<>"",Navegación!I8,"")
B9: Nombres completos | D9: =IF(Navegación!D9<>"",Navegación!D9,"") -> JUAN PABLO | E9: =IF(Navegación!E9<>"",Navegación!E9,"") | F9: =IF(Navegación!F9<>"",Navegación!F9,"") | G9: =IF(Navegación!G9<>"",Navegación!G9,"") | H9: =IF(Navegación!H9<>"",Navegación!H9,"") | I9: =IF(Navegación!I9<>"",Navegación!I9,"")
B10: Apellidos completos | D10: =IF(Navegación!D10<>"",Navegación!D10,"") -> CAMPO TELLEZ | E10: =IF(Navegación!E10<>"",Navegación!E10,"") | F10: =IF(Navegación!F10<>"",Navegación!F10,"") | G10: =IF(Navegación!G10<>"",Navegación!G10,"") | H10: =IF(Navegación!H10<>"",Navegación!H10,"") | I10: =IF(Navegación!I10<>"",Navegación!I10,"")
B11: Centro de costo | D11: =IF(Navegación!D11<>"",Navegación!D11,"") -> 856 | E11: =IF(Navegación!E11<>"",Navegación!E11,"") | F11: =IF(Navegación!F11<>"",Navegación!F11,"") | G11: =IF(Navegación!G11<>"",Navegación!G11,"") | H11: =IF(Navegación!H11<>"",Navegación!H11,"") | I11: =IF(Navegación!I11<>"",Navegación!I11,"")
B12: Teléfono/Extensión de contacto del usuario | D12: =IF(Navegación!D12<>"",Navegación!D12,"") | E12: =IF(Navegación!E12<>"",Navegación!E12,"") | F12: =IF(Navegación!F12<>"",Navegación!F12,"") | G12: =IF(Navegación!G12<>"",Navegación!G12,"") | H12: =IF(Navegación!H12<>"",Navegación!H12,"") | I12: =IF(Navegación!I12<>"",Navegación!I12,"")
B13: Celular | D13: =IF(Navegación!D13<>"",Navegación!D13,"") -> 3150727969 | E13: =IF(Navegación!E13<>"",Navegación!E13,"") | F13: =IF(Navegación!F13<>"",Navegación!F13,"") | G13: =IF(Navegación!G13<>"",Navegación!G13,"") | H13: =IF(Navegación!H13<>"",Navegación!H13,"") | I13: =IF(Navegación!I13<>"",Navegación!I13,"")
B14: Dependencia | D14: =IF(Navegación!D14<>"",Navegación!D14,"") -> Gobierno | E14: =IF(Navegación!E14<>"",Navegación!E14,"") | F14: =IF(Navegación!F14<>"",Navegación!F14,"") | G14: =IF(Navegación!G14<>"",Navegación!G14,"") | H14: =IF(Navegación!H14<>"",Navegación!H14,"") | I14: =IF(Navegación!I14<>"",Navegación!I14,"")
B15: Cargo
B16: Empleado Cafam o Externo | D16: =IF(Navegación!D16<>"",Navegación!D16,"") -> Empleado CAFAM | E16: =IF(Navegación!E16<>"",Navegación!E16,"") | F16: =IF(Navegación!F16<>"",Navegación!F16,"") | G16: =IF(Navegación!G16<>"",Navegación!G16,"") | H16: =IF(Navegación!H16<>"",Navegación!H16,"") | I16: =IF(Navegación!I16<>"",Navegación!I16,"")
B17: Nombre de la empresa cuando es Externo | D17: =IF(Navegación!D17<>"",Navegación!D17,"") | E17: =IF(Navegación!E17<>"",Navegación!E17,"") | F17: =IF(Navegación!F17<>"",Navegación!F17,"") | G17: =IF(Navegación!G17<>"",Navegación!G17,"") | H17: =IF(Navegación!H17<>"",Navegación!H17,"") | I17: =IF(Navegación!I17<>"",Navegación!I17,"")
B18: Fecha inicio contrato: | D18: =IF(Navegación!D18<>"",Navegación!D18,"") -> 45849 | E18: =IF(Navegación!E18<>"",Navegación!E18,"") | F18: =IF(Navegación!F18<>"",Navegación!F18,"") | G18: =IF(Navegación!G18<>"",Navegación!G18,"") | H18: =IF(Navegación!H18<>"",Navegación!H18,"") | I18: =IF(Navegación!I18<>"",Navegación!I18,"")
B19: Fecha finalización contrato: (Si es indefinido escribir 31.12.9999) | D19: =IF(Navegación!D19<>"",Navegación!D19,"") | E19: =IF(Navegación!E19<>"",Navegación!E19,"") | F19: =IF(Navegación!F19<>"",Navegación!F19,"") | G19: =IF(Navegación!G19<>"",Navegación!G19,"") | H19: =IF(Navegación!H19<>"",Navegación!H19,"") | I19: =IF(Navegación!I19<>"",Navegación!I19,"")
B21: Requerimientos Plataformas MEDICAMENTOS
B22: POS IBM | D22: =IF(DZ23>0,Navegación!$E$47,"")
B23: Novedad | DZ23: =COUNTIF(D23:I23,"<>") -> 0
B24: Perfil
B26: Observaciones
B31: ='WINDOWS 1'!$B$37 -> APROBADOR POR: Jefe Dpto. Servicios Compartidos | F31: ='WINDOWS 1'!F37 -> V20 de 26/09/2023 | I31: ="Pág. " &Navegación!B47 & " de " &Navegación!$B$102 -> Pág. 21 de 54
DZ32: =COUNTIF(#REF!,"<>") -> #REF!
DZ34: =COUNTIF(#REF!,"<>") -> #REF!
DZ36: =COUNTIF(#REF!,"<>") -> #REF!
DZ38: =COUNTIF(#REF!,"<>") -> #REF!
DZ40: =COUNTIF(#REF!,"<>") -> #REF!
DZ42: =COUNTIF(#REF!,"<>") -> #REF!
DZ50: =COUNTIF(#REF!,"<>") -> #REF!
DZ54: =COUNTIF(#REF!,"<>") -> #REF!
DZ56: =COUNTIF('MEDICAMENTOS 5'!D23:I23,"<>") -> 0
DZ58: =COUNTIF(#REF!,"<>") -> #REF!

Sheet MEDICAMENTOS 7
K1: 2958465
C2: FORMATO: GESTIÓN DE IDENTIDADES
F3: DOCUMENTO USO INTERNO
B5: Las celdas resaltadas en Naranja son campos obligatorios del Formato.
B6: Información Usuarios | D6: Usuario 1 | E6: Usuario 2 | F6: Usuario 3 | G6: Usuario 4 | H6: Usuario 5 | I6: Usuario 6
B7: Tipo de documento | D7: =IF(Navegación!D7<>"",Navegación!D7,"") -> Cédula Ciudadanía | E7: =IF(Navegación!E7<>"",Navegación!E7,"") | F7: =IF(Navegación!F7<>"",Navegación!F7,"") | G7: =IF(Navegación!G7<>"",Navegación!G7,"") | H7: =IF(Navegación!H7<>"",Navegación!H7,"") | I7: =IF(Navegación!I7<>"",Navegación!I7,"")
B8: Identificación | D8: =IF(Navegación!D8<>"",Navegación!D8,"") -> 1001089595 | E8: =IF(Navegación!E8<>"",Navegación!E8,"") | F8: =IF(Navegación!F8<>"",Navegación!F8,"") | G8: =IF(Navegación!G8<>"",Navegación!G8,"") | H8: =IF(Navegación!H8<>"",Navegación!H8,"") | I8: =IF(Navegación!I8<>"",Navegación!I8,"")
B9: Nombres completos | D9: =IF(Navegación!D9<>"",Navegación!D9,"") -> JUAN PABLO | E9: =IF(Navegación!E9<>"",Navegación!E9,"") | F9: =IF(Navegación!F9<>"",Navegación!F9,"") | G9: =IF(Navegación!G9<>"",Navegación!G9,"") | H9: =IF(Navegación!H9<>"",Navegación!H9,"") | I9: =IF(Navegación!I9<>"",Navegación!I9,"")
B10: Apellidos completos | D10: =IF(Navegación!D10<>"",Navegación!D10,"") -> CAMPO TELLEZ | E10: =IF(Navegación!E10<>"",Navegación!E10,"") | F10: =IF(Navegación!F10<>"",Navegación!F10,"") | G10: =IF(Navegación!G10<>"",Navegación!G10,"") | H10: =IF(Navegación!H10<>"",Navegación!H10,"") | I10: =IF(Navegación!I10<>"",Navegación!I10,"")
B11: Centro de costo | D11: =IF(Navegación!D11<>"",Navegación!D11,"") -> 856 | E11: =IF(Navegación!E11<>"",Navegación!E11,"") | F11: =IF(Navegación!F11<>"",Navegación!F11,"") | G11: =IF(Navegación!G11<>"",Navegación!G11,"") | H11: =IF(Navegación!H11<>"",Navegación!H11,"") | I11: =IF(Navegación!I11<>"",Navegación!I11,"")
B12: Teléfono/Extensión de contacto del usuario | D12: =IF(Navegación!D12<>"",Navegación!D12,"") | E12: =IF(Navegación!E12<>"",Navegación!E12,"") | F12: =IF(Navegación!F12<>"",Navegación!F12,"") | G12: =IF(Navegación!G12<>"",Navegación!G12,"") | H12: =IF(Navegación!H12<>"",Navegación!H12,"") | I12: =IF(Navegación!I12<>"",Navegación!I12,"")
B13: Celular | D13: =IF(Navegación!D13<>"",Navegación!D13,"") -> 3150727969 | E13: =IF(Navegación!E13<>"",Navegación!E13,"") | F13: =IF(Navegación!F13<>"",Navegación!F13,"") | G13: =IF(Navegación!G13<>"",Navegación!G13,"") | H13: =IF(Navegación!H13<>"",Navegación!H13,"") | I13: =IF(Navegación!I13<>"",Navegación!I13,"")
B14: Dependencia | D14: =IF(Navegación!D14<>"",Navegación!D14,"") -> Gobierno | E14: =IF(Navegación!E14<>"",Navegación!E14,"") | F14: =IF(Navegación!F14<>"",Navegación!F14,"") | G14: =IF(Navegación!G14<>"",Navegación!G14,"") | H14: =IF(Navegación!H14<>"",Navegación!H14,"") | I14: =IF(Navegación!I14<>"",Navegación!I14,"")
B15: Cargo
B16: Empleado Cafam o Externo | D16: =IF(Navegación!D16<>"",Navegación!D16,"") -> Empleado CAFAM | E16: =IF(Navegación!E16<>"",Navegación!E16,"") | F16: =IF(Navegación!F16<>"",Navegación!F16,"") | G16: =IF(Navegación!G16<>"",Navegación!G16,"") | H16: =IF(Navegación!H16<>"",Navegación!H16,"") | I16: =IF(Navegación!I16<>"",Navegación!I16,"")
B17: Nombre de la empresa cuando es Externo | D17: =IF(Navegación!D17<>"",Navegación!D17,"") | E17: =IF(Navegación!E17<>"",Navegación!E17,"") | F17: =IF(Navegación!F17<>"",Navegación!F17,"") | G17: =IF(Navegación!G17<>"",Navegación!G17,"") | H17: =IF(Navegación!H17<>"",Navegación!H17,"") | I17: =IF(Navegación!I17<>"",Navegación!I17,"")
B18: Fecha inicio contrato: | D18: =IF(Navegación!D18<>"",Navegación!D18,"") -> 45849 | E18: =IF(Navegación!E18<>"",Navegación!E18,"") | F18: =IF(Navegación!F18<>"",Navegación!F18,"") | G18: =IF(Navegación!G18<>"",Navegación!G18,"") | H18: =IF(Navegación!H18<>"",Navegación!H18,"") | I18: =IF(Navegación!I18<>"",Navegación!I18,"")
B19: Fecha finalización contrato: (Si es indefinido escribir 31.12.9999) | D19: =IF(Navegación!D19<>"",Navegación!D19,"") | E19: =IF(Navegación!E19<>"",Navegación!E19,"") | F19: =IF(Navegación!F19<>"",Navegación!F19,"") | G19: =IF(Navegación!G19<>"",Navegación!G19,"") | H19: =IF(Navegación!H19<>"",Navegación!H19,"") | I19: =IF(Navegación!I19<>"",Navegación!I19,"")
B21: WEB FAMISANAR | D21: =IF(DZ22>0,Navegación!$E$48,"")
B22: Acceso a web Famisanar | C22: Se requiere acceso? | DZ22: =COUNTIF(D22:I22,"<>") -> 0
C23: Perfil
C24: Correo electronico (unicamente en dominio cafam.com.co)
B26: Observaciones
B31: ='WINDOWS 1'!$B$37 -> APROBADOR POR: Jefe Dpto. Servicios Compartidos | F31: ='WINDOWS 1'!F37 -> V20 de 26/09/2023 | I31: ="Pág. " &Navegación!B48 & " de " &Navegación!$B$102 -> Pág. 22 de 54
DZ32: =COUNTIF(#REF!,"<>") -> #REF!
DZ34: =COUNTIF(#REF!,"<>") -> #REF!
DZ36: =COUNTIF(#REF!,"<>") -> #REF!
DZ38: =COUNTIF(#REF!,"<>") -> #REF!
DZ40: =COUNTIF(#REF!,"<>") -> #REF!
DZ42: =COUNTIF(#REF!,"<>") -> #REF!
DZ50: =COUNTIF(#REF!,"<>") -> #REF!
DZ54: =COUNTIF(#REF!,"<>") -> #REF!
DZ56: =COUNTIF('MEDICAMENTOS 5'!D23:I23,"<>") -> 0
DZ58: =COUNTIF(D22:I22,"<>") -> 0

Sheet MEDICAMENTOS 8
K1: 2958465
C2: FORMATO: GESTIÓN DE IDENTIDADES
F3: DOCUMENTO USO INTERNO
B5: Las celdas resaltadas en Naranja son campos obligatorios del Formato.
B6: Información Usuarios | D6: Usuario 1 | E6: Usuario 2 | F6: Usuario 3 | G6: Usuario 4 | H6: Usuario 5 | I6: Usuario 6
B7: Tipo de documento | D7: =IF(Navegación!D7<>"",Navegación!D7,"") -> Cédula Ciudadanía | E7: =IF(Navegación!E7<>"",Navegación!E7,"") | F7: =IF(Navegación!F7<>"",Navegación!F7,"") | G7: =IF(Navegación!G7<>"",Navegación!G7,"") | H7: =IF(Navegación!H7<>"",Navegación!H7,"") | I7: =IF(Navegación!I7<>"",Navegación!I7,"")
B8: Identificación | D8: =IF(Navegación!D8<>"",Navegación!D8,"") -> 1001089595 | E8: =IF(Navegación!E8<>"",Navegación!E8,"") | F8: =IF(Navegación!F8<>"",Navegación!F8,"") | G8: =IF(Navegación!G8<>"",Navegación!G8,"") | H8: =IF(Navegación!H8<>"",Navegación!H8,"") | I8: =IF(Navegación!I8<>"",Navegación!I8,"")
B9: Nombres completos | D9: =IF(Navegación!D9<>"",Navegación!D9,"") -> JUAN PABLO | E9: =IF(Navegación!E9<>"",Navegación!E9,"") | F9: =IF(Navegación!F9<>"",Navegación!F9,"") | G9: =IF(Navegación!G9<>"",Navegación!G9,"") | H9: =IF(Navegación!H9<>"",Navegación!H9,"") | I9: =IF(Navegación!I9<>"",Navegación!I9,"")
B10: Apellidos completos | D10: =IF(Navegación!D10<>"",Navegación!D10,"") -> CAMPO TELLEZ | E10: =IF(Navegación!E10<>"",Navegación!E10,"") | F10: =IF(Navegación!F10<>"",Navegación!F10,"") | G10: =IF(Navegación!G10<>"",Navegación!G10,"") | H10: =IF(Navegación!H10<>"",Navegación!H10,"") | I10: =IF(Navegación!I10<>"",Navegación!I10,"")
B11: Centro de costo | D11: =IF(Navegación!D11<>"",Navegación!D11,"") -> 856 | E11: =IF(Navegación!E11<>"",Navegación!E11,"") | F11: =IF(Navegación!F11<>"",Navegación!F11,"") | G11: =IF(Navegación!G11<>"",Navegación!G11,"") | H11: =IF(Navegación!H11<>"",Navegación!H11,"") | I11: =IF(Navegación!I11<>"",Navegación!I11,"")
B12: Teléfono/Extensión de contacto del usuario | D12: =IF(Navegación!D12<>"",Navegación!D12,"") | E12: =IF(Navegación!E12<>"",Navegación!E12,"") | F12: =IF(Navegación!F12<>"",Navegación!F12,"") | G12: =IF(Navegación!G12<>"",Navegación!G12,"") | H12: =IF(Navegación!H12<>"",Navegación!H12,"") | I12: =IF(Navegación!I12<>"",Navegación!I12,"")
B13: Celular | D13: =IF(Navegación!D13<>"",Navegación!D13,"") -> 3150727969 | E13: =IF(Navegación!E13<>"",Navegación!E13,"") | F13: =IF(Navegación!F13<>"",Navegación!F13,"") | G13: =IF(Navegación!G13<>"",Navegación!G13,"") | H13: =IF(Navegación!H13<>"",Navegación!H13,"") | I13: =IF(Navegación!I13<>"",Navegación!I13,"")
B14: Dependencia | D14: =IF(Navegación!D14<>"",Navegación!D14,"") -> Gobierno | E14: =IF(Navegación!E14<>"",Navegación!E14,"") | F14: =IF(Navegación!F14<>"",Navegación!F14,"") | G14: =IF(Navegación!G14<>"",Navegación!G14,"") | H14: =IF(Navegación!H14<>"",Navegación!H14,"") | I14: =IF(Navegación!I14<>"",Navegación!I14,"")
B15: Cargo
B16: Empleado Cafam o Externo | D16: =IF(Navegación!D16<>"",Navegación!D16,"") -> Empleado CAFAM | E16: =IF(Navegación!E16<>"",Navegación!E16,"") | F16: =IF(Navegación!F16<>"",Navegación!F16,"") | G16: =IF(Navegación!G16<>"",Navegación!G16,"") | H16: =IF(Navegación!H16<>"",Navegación!H16,"") | I16: =IF(Navegación!I16<>"",Navegación!I16,"")
B17: Nombre de la empresa cuando es Externo | D17: =IF(Navegación!D17<>"",Navegación!D17,"") | E17: =IF(Navegación!E17<>"",Navegación!E17,"") | F17: =IF(Navegación!F17<>"",Navegación!F17,"") | G17: =IF(Navegación!G17<>"",Navegación!G17,"") | H17: =IF(Navegación!H17<>"",Navegación!H17,"") | I17: =IF(Navegación!I17<>"",Navegación!I17,"")
B18: Fecha inicio contrato: | D18: =IF(Navegación!D18<>"",Navegación!D18,"") -> 45849 | E18: =IF(Navegación!E18<>"",Navegación!E18,"") | F18: =IF(Navegación!F18<>"",Navegación!F18,"") | G18: =IF(Navegación!G18<>"",Navegación!G18,"") | H18: =IF(Navegación!H18<>"",Navegación!H18,"") | I18: =IF(Navegación!I18<>"",Navegación!I18,"")
B19: Fecha finalización contrato: (Si es indefinido escribir 31.12.9999) | D19: =IF(Navegación!D19<>"",Navegación!D19,"") | E19: =IF(Navegación!E19<>"",Navegación!E19,"") | F19: =IF(Navegación!F19<>"",Navegación!F19,"") | G19: =IF(Navegación!G19<>"",Navegación!G19,"") | H19: =IF(Navegación!H19<>"",Navegación!H19,"") | I19: =IF(Navegación!I19<>"",Navegación!I19,"")
B21: Requerimientos Plataformas MEDICAMENTOS
B22: MERCADO PAGO | D22: =IF(DZ24>0,Navegación!$E$49,"")
B23: Tipo de usuario
B24: Novedad (Crear/Modificación/Inactivar): | DZ24: =COUNTIF(D24:I24,"<>") -> 0
B25: Email Usuario
B26: Ambiente (Pruebas, Producción, Ambos):
B27: Rol
B28: Sucursal
B30: Observaciones
B35: ='WINDOWS 1'!$B$37 -> APROBADOR POR: Jefe Dpto. Servicios Compartidos | F35: ='WINDOWS 1'!F37 -> V20 de 26/09/2023 | I35: ="Pág. " &Navegación!B49 & " de " &Navegación!$B$102 -> Pág. 23 de 54
DZ38: =COUNTIF(#REF!,"<>") -> #REF!
DZ40: =COUNTIF(#REF!,"<>") -> #REF!
DZ42: =COUNTIF(#REF!,"<>") -> #REF!
DZ50: =COUNTIF(#REF!,"<>") -> #REF!
DZ54: =COUNTIF(#REF!,"<>") -> #REF!
DZ56: =COUNTIF('MEDICAMENTOS 5'!D23:I23,"<>") -> 0
DZ58: =COUNTIF(#REF!,"<>") -> #REF!

Sheet MEDICAMENTOS 9
K1: 2958465
C2: FORMATO: GESTIÓN DE IDENTIDADES
F3: DOCUMENTO USO INTERNO
B5: Las celdas resaltadas en Naranja son campos obligatorios del Formato.
B6: Información Usuarios | D6: Usuario 1 | E6: Usuario 2 | F6: Usuario 3 | G6: Usuario 4 | H6: Usuario 5 | I6: Usuario 6
B7: Tipo de documento | D7: =IF(Navegación!D7<>"",Navegación!D7,"") -> Cédula Ciudadanía | E7: =IF(Navegación!E7<>"",Navegación!E7,"") | F7: =IF(Navegación!F7<>"",Navegación!F7,"") | G7: =IF(Navegación!G7<>"",Navegación!G7,"") | H7: =IF(Navegación!H7<>"",Navegación!H7,"") | I7: =IF(Navegación!I7<>"",Navegación!I7,"")
B8: Identificación | D8: =IF(Navegación!D8<>"",Navegación!D8,"") -> 1001089595 | E8: =IF(Navegación!E8<>"",Navegación!E8,"") | F8: =IF(Navegación!F8<>"",Navegación!F8,"") | G8: =IF(Navegación!G8<>"",Navegación!G8,"") | H8: =IF(Navegación!H8<>"",Navegación!H8,"") | I8: =IF(Navegación!I8<>"",Navegación!I8,"")
B9: Nombres completos | D9: =IF(Navegación!D9<>"",Navegación!D9,"") -> JUAN PABLO | E9: =IF(Navegación!E9<>"",Navegación!E9,"") | F9: =IF(Navegación!F9<>"",Navegación!F9,"") | G9: =IF(Navegación!G9<>"",Navegación!G9,"") | H9: =IF(Navegación!H9<>"",Navegación!H9,"") | I9: =IF(Navegación!I9<>"",Navegación!I9,"")
B10: Apellidos completos | D10: =IF(Navegación!D10<>"",Navegación!D10,"") -> CAMPO TELLEZ | E10: =IF(Navegación!E10<>"",Navegación!E10,"") | F10: =IF(Navegación!F10<>"",Navegación!F10,"") | G10: =IF(Navegación!G10<>"",Navegación!G10,"") | H10: =IF(Navegación!H10<>"",Navegación!H10,"") | I10: =IF(Navegación!I10<>"",Navegación!I10,"")
B11: Centro de costo | D11: =IF(Navegación!D11<>"",Navegación!D11,"") -> 856 | E11: =IF(Navegación!E11<>"",Navegación!E11,"") | F11: =IF(Navegación!F11<>"",Navegación!F11,"") | G11: =IF(Navegación!G11<>"",Navegación!G11,"") | H11: =IF(Navegación!H11<>"",Navegación!H11,"") | I11: =IF(Navegación!I11<>"",Navegación!I11,"")
B12: Teléfono/Extensión de contacto del usuario | D12: =IF(Navegación!D12<>"",Navegación!D12,"") | E12: =IF(Navegación!E12<>"",Navegación!E12,"") | F12: =IF(Navegación!F12<>"",Navegación!F12,"") | G12: =IF(Navegación!G12<>"",Navegación!G12,"") | H12: =IF(Navegación!H12<>"",Navegación!H12,"") | I12: =IF(Navegación!I12<>"",Navegación!I12,"")
B13: Celular | D13: =IF(Navegación!D13<>"",Navegación!D13,"") -> 3150727969 | E13: =IF(Navegación!E13<>"",Navegación!E13,"") | F13: =IF(Navegación!F13<>"",Navegación!F13,"") | G13: =IF(Navegación!G13<>"",Navegación!G13,"") | H13: =IF(Navegación!H13<>"",Navegación!H13,"") | I13: =IF(Navegación!I13<>"",Navegación!I13,"")
B14: Dependencia | D14: =IF(Navegación!D14<>"",Navegación!D14,"") -> Gobierno | E14: =IF(Navegación!E14<>"",Navegación!E14,"") | F14: =IF(Navegación!F14<>"",Navegación!F14,"") | G14: =IF(Navegación!G14<>"",Navegación!G14,"") | H14: =IF(Navegación!H14<>"",Navegación!H14,"") | I14: =IF(Navegación!I14<>"",Navegación!I14,"")
B15: Cargo
B16: Empleado Cafam o Externo | D16: =IF(Navegación!D16<>"",Navegación!D16,"") -> Empleado CAFAM | E16: =IF(Navegación!E16<>"",Navegación!E16,"") | F16: =IF(Navegación!F16<>"",Navegación!F16,"") | G16: =IF(Navegación!G16<>"",Navegación!G16,"") | H16: =IF(Navegación!H16<>"",Navegación!H16,"") | I16: =IF(Navegación!I16<>"",Navegación!I16,"")
B17: Nombre de la empresa cuando es Externo | D17: =IF(Navegación!D17<>"",Navegación!D17,"") | E17: =IF(Navegación!E17<>"",Navegación!E17,"") | F17: =IF(Navegación!F17<>"",Navegación!F17,"") | G17: =IF(Navegación!G17<>"",Navegación!G17,"") | H17: =IF(Navegación!H17<>"",Navegación!H17,"") | I17: =IF(Navegación!I17<>"",Navegación!I17,"")
B18: Fecha inicio contrato: | D18: =IF(Navegación!D18<>"",Navegación!D18,"") -> 45849 | E18: =IF(Navegación!E18<>"",Navegación!E18,"") | F18: =IF(Navegación!F18<>"",Navegación!F18,"") | G18: =IF(Navegación!G18<>"",Navegación!G18,"") | H18: =IF(Navegación!H18<>"",Navegación!H18,"") | I18: =IF(Navegación!I18<>"",Navegación!I18,"")
B19: Fecha finalización contrato: (Si es indefinido escribir 31.12.9999) | D19: =IF(Navegación!D19<>"",Navegación!D19,"") | E19: =IF(Navegación!E19<>"",Navegación!E19,"") | F19: =IF(Navegación!F19<>"",Navegación!F19,"") | G19: =IF(Navegación!G19<>"",Navegación!G19,"") | H19: =IF(Navegación!H19<>"",Navegación!H19,"") | I19: =IF(Navegación!I19<>"",Navegación!I19,"")
B21: Requerimientos Plataformas MEDICAMENTOS
B22: MERCADO LIBRE | D22: =IF(DZ24>0,Navegación!$E$50,"")
B23: Tipo de usuario
B24: Novedad (Crear/Modificación/Inactivar): | DZ24: =COUNTIF(D24:I24,"<>") -> 0
B25: Email Usuario
B26: Ambiente (Pruebas, Producción, Ambos):
B27: Rol
B28: Sucursal
B30: Observaciones
B35: ='WINDOWS 1'!$B$37 -> APROBADOR POR: Jefe Dpto. Servicios Compartidos | F35: ='WINDOWS 1'!F37 -> V20 de 26/09/2023 | I35: ="Pág. " &Navegación!B53 & " de " &Navegación!$B$102 -> Pág. 27 de 54
DZ38: =COUNTIF(#REF!,"<>") -> #REF!
DZ40: =COUNTIF(#REF!,"<>") -> #REF!
DZ42: =COUNTIF(#REF!,"<>") -> #REF!
DZ50: =COUNTIF(#REF!,"<>") -> #REF!
DZ54: =COUNTIF(#REF!,"<>") -> #REF!
DZ56: =COUNTIF('MEDICAMENTOS 5'!D23:I23,"<>") -> 0
DZ58: =COUNTIF(#REF!,"<>") -> #REF!

Sheet MEDICAMENTOS 10
K1: 2958465
C2: FORMATO: GESTIÓN DE IDENTIDADES
F3: DOCUMENTO USO INTERNO
B5: Las celdas resaltadas en Naranja son campos obligatorios del Formato.
B6: Información Usuarios | D6: Usuario 1 | E6: Usuario 2 | F6: Usuario 3 | G6: Usuario 4 | H6: Usuario 5 | I6: Usuario 6
B7: Tipo de documento | D7: =IF(Navegación!D7<>"",Navegación!D7,"") -> Cédula Ciudadanía | E7: =IF(Navegación!E7<>"",Navegación!E7,"") | F7: =IF(Navegación!F7<>"",Navegación!F7,"") | G7: =IF(Navegación!G7<>"",Navegación!G7,"") | H7: =IF(Navegación!H7<>"",Navegación!H7,"") | I7: =IF(Navegación!I7<>"",Navegación!I7,"")
B8: Identificación | D8: =IF(Navegación!D8<>"",Navegación!D8,"") -> 1001089595 | E8: =IF(Navegación!E8<>"",Navegación!E8,"") | F8: =IF(Navegación!F8<>"",Navegación!F8,"") | G8: =IF(Navegación!G8<>"",Navegación!G8,"") | H8: =IF(Navegación!H8<>"",Navegación!H8,"") | I8: =IF(Navegación!I8<>"",Navegación!I8,"")
B9: Nombres completos | D9: =IF(Navegación!D9<>"",Navegación!D9,"") -> JUAN PABLO | E9: =IF(Navegación!E9<>"",Navegación!E9,"") | F9: =IF(Navegación!F9<>"",Navegación!F9,"") | G9: =IF(Navegación!G9<>"",Navegación!G9,"") | H9: =IF(Navegación!H9<>"",Navegación!H9,"") | I9: =IF(Navegación!I9<>"",Navegación!I9,"")
B10: Apellidos completos | D10: =IF(Navegación!D10<>"",Navegación!D10,"") -> CAMPO TELLEZ | E10: =IF(Navegación!E10<>"",Navegación!E10,"") | F10: =IF(Navegación!F10<>"",Navegación!F10,"") | G10: =IF(Navegación!G10<>"",Navegación!G10,"") | H10: =IF(Navegación!H10<>"",Navegación!H10,"") | I10: =IF(Navegación!I10<>"",Navegación!I10,"")
B11: Centro de costo | D11: =IF(Navegación!D11<>"",Navegación!D11,"") -> 856 | E11: =IF(Navegación!E11<>"",Navegación!E11,"") | F11: =IF(Navegación!F11<>"",Navegación!F11,"") | G11: =IF(Navegación!G11<>"",Navegación!G11,"") | H11: =IF(Navegación!H11<>"",Navegación!H11,"") | I11: =IF(Navegación!I11<>"",Navegación!I11,"")
B12: Teléfono/Extensión de contacto del usuario | D12: =IF(Navegación!D12<>"",Navegación!D12,"") | E12: =IF(Navegación!E12<>"",Navegación!E12,"") | F12: =IF(Navegación!F12<>"",Navegación!F12,"") | G12: =IF(Navegación!G12<>"",Navegación!G12,"") | H12: =IF(Navegación!H12<>"",Navegación!H12,"") | I12: =IF(Navegación!I12<>"",Navegación!I12,"")
B13: Celular | D13: =IF(Navegación!D13<>"",Navegación!D13,"") -> 3150727969 | E13: =IF(Navegación!E13<>"",Navegación!E13,"") | F13: =IF(Navegación!F13<>"",Navegación!F13,"") | G13: =IF(Navegación!G13<>"",Navegación!G13,"") | H13: =IF(Navegación!H13<>"",Navegación!H13,"") | I13: =IF(Navegación!I13<>"",Navegación!I13,"")
B14: Dependencia | D14: =IF(Navegación!D14<>"",Navegación!D14,"") -> Gobierno | E14: =IF(Navegación!E14<>"",Navegación!E14,"") | F14: =IF(Navegación!F14<>"",Navegación!F14,"") | G14: =IF(Navegación!G14<>"",Navegación!G14,"") | H14: =IF(Navegación!H14<>"",Navegación!H14,"") | I14: =IF(Navegación!I14<>"",Navegación!I14,"")
B15: Cargo | D15: =IF(Navegación!D15<>"",Navegación!D15,"") -> Aprendiz Universitario | E15: =IF(Navegación!E15<>"",Navegación!E15,"") | F15: =IF(Navegación!F15<>"",Navegación!F15,"") | G15: =IF(Navegación!G15<>"",Navegación!G15,"") | H15: =IF(Navegación!H15<>"",Navegación!H15,"") | I15: =IF(Navegación!I15<>"",Navegación!I15,"")
B16: Empleado Cafam o Externo | D16: =IF(Navegación!D16<>"",Navegación!D16,"") -> Empleado CAFAM | E16: =IF(Navegación!E16<>"",Navegación!E16,"") | F16: =IF(Navegación!F16<>"",Navegación!F16,"") | G16: =IF(Navegación!G16<>"",Navegación!G16,"") | H16: =IF(Navegación!H16<>"",Navegación!H16,"") | I16: =IF(Navegación!I16<>"",Navegación!I16,"")
B17: Nombre de la empresa cuando es Externo | D17: =IF(Navegación!D17<>"",Navegación!D17,"") | E17: =IF(Navegación!E17<>"",Navegación!E17,"") | F17: =IF(Navegación!F17<>"",Navegación!F17,"") | G17: =IF(Navegación!G17<>"",Navegación!G17,"") | H17: =IF(Navegación!H17<>"",Navegación!H17,"") | I17: =IF(Navegación!I17<>"",Navegación!I17,"")
B18: Fecha inicio contrato: | D18: =IF(Navegación!D18<>"",Navegación!D18,"") -> 45849 | E18: =IF(Navegación!E18<>"",Navegación!E18,"") | F18: =IF(Navegación!F18<>"",Navegación!F18,"") | G18: =IF(Navegación!G18<>"",Navegación!G18,"") | H18: =IF(Navegación!H18<>"",Navegación!H18,"") | I18: =IF(Navegación!I18<>"",Navegación!I18,"")
B19: Fecha finalización contrato: (Si es indefinido escribir 31.12.9999) | D19: =IF(Navegación!D19<>"",Navegación!D19,"") | E19: =IF(Navegación!E19<>"",Navegación!E19,"") | F19: =IF(Navegación!F19<>"",Navegación!F19,"") | G19: =IF(Navegación!G19<>"",Navegación!G19,"") | H19: =IF(Navegación!H19<>"",Navegación!H19,"") | I19: =IF(Navegación!I19<>"",Navegación!I19,"")
B21: Requerimientos Plataformas MEDICAMENTOS
B22: NAPSE | D22: =IF(OR(DZ24>0,DZ29>DZ34>DZ39>0),Navegación!$E$52,"") -> Esta aplicación solo requiere VoBo de su Jefatura
B23: Bridge POS | D23: =ADDRESS(MATCH(D$26,P_NAPSE[[#All],[App]],0)+249,13,1) -> #N/A | E23: =ADDRESS(MATCH(E$26,P_NAPSE[[#All],[App]],0)+249,13,1) -> #N/A | F23: =ADDRESS(MATCH(F$26,P_NAPSE[[#All],[App]],0)+249,13,1) -> #N/A | G23: =ADDRESS(MATCH(G$26,P_NAPSE[[#All],[App]],0)+249,13,1) -> #N/A | H23: =ADDRESS(MATCH(H$26,P_NAPSE[[#All],[App]],0)+249,13,1) -> #N/A | I23: =ADDRESS(MATCH(I$26,P_NAPSE[[#All],[App]],0)+249,13,1) -> #N/A
B24: =B23 -> Bridge POS | C24: Novedad (Crear/Modificación/Baja): | DZ24: =COUNTIF(D24:I24,"<>") -> 0
C25: Alias Usuario
C26: Aplicación
C27: Nombre del perfil
B28: Bridge Director
B29: =B28 -> Bridge Director | C29: Novedad (Crear/Modificación/Baja):
C30: Alias Usuario
C31: Aplicación
C32: Nombre del perfil
B33: Bridge Promo
B34: =B33 -> Bridge Promo | C34: Novedad (Crear/Modificación/Baja):
C35: Alias Usuario
C36: Aplicación
C37: Nombre del perfil
B38: Bridge Fiscal Flow
B39: =B38 -> Bridge Fiscal Flow | C39: Novedad (Crear/Modificación/Baja):
C40: Alias Usuario
C41: Aplicación
C42: Nombre del perfil
B44: Observaciones
B49: ='WINDOWS 1'!$B$37 -> APROBADOR POR: Jefe Dpto. Servicios Compartidos | F49: ='WINDOWS 1'!F37 -> V20 de 26/09/2023 | I49: ="Pág. " &Navegación!B56 & " de " &Navegación!$B$102 -> Pág. 28 de 54
L250: App | M250: Perfil
L251: Bridge Director | M251: Administrador de productos
L252: Bridge Director | M252: Administrador de versiones
L253: Bridge Director | M253: Gestión de aplicaciones
L254: Bridge Director | M254: Gestión de identidades
L255: Bridge Director | M255: Gestión de identidades N2
L256: Bridge Director | M256: Sistemas de información
L257: Bridge Director | M257: Supervisor de productos
L258: Bridge Director | M258: Supervisor de terminales
L259: Bridge Director | M259: TI Mesa de ayuda
L260: Bridge Fiscal Flow | M260: Administrador
L261: Bridge Fiscal Flow | M261: Cartera
... L281: Bridge Promo | M281: T.I. Soporte De Aplicaciones

Sheet MEDICAMENTOS 11
K1: 2958465
C2: FORMATO: GESTIÓN DE IDENTIDADES
F3: DOCUMENTO USO INTERNO
B5: Las celdas resaltadas en Naranja son campos obligatorios del Formato.
B6: Información Usuarios | D6: Usuario 1 | E6: Usuario 2 | F6: Usuario 3 | G6: Usuario 4 | H6: Usuario 5 | I6: Usuario 6
B7: Tipo de documento | D7: =IF(Navegación!D7<>"",Navegación!D7,"") -> Cédula Ciudadanía | E7: =IF(Navegación!E7<>"",Navegación!E7,"") | F7: =IF(Navegación!F7<>"",Navegación!F7,"") | G7: =IF(Navegación!G7<>"",Navegación!G7,"") | H7: =IF(Navegación!H7<>"",Navegación!H7,"") | I7: =IF(Navegación!I7<>"",Navegación!I7,"")
B8: Identificación | D8: =IF(Navegación!D8<>"",Navegación!D8,"") -> 1001089595 | E8: =IF(Navegación!E8<>"",Navegación!E8,"") | F8: =IF(Navegación!F8<>"",Navegación!F8,"") | G8: =IF(Navegación!G8<>"",Navegación!G8,"") | H8: =IF(Navegación!H8<>"",Navegación!H8,"") | I8: =IF(Navegación!I8<>"",Navegación!I8,"")
B9: Nombres completos | D9: =IF(Navegación!D9<>"",Navegación!D9,"") -> JUAN PABLO | E9: =IF(Navegación!E9<>"",Navegación!E9,"") | F9: =IF(Navegación!F9<>"",Navegación!F9,"") | G9: =IF(Navegación!G9<>"",Navegación!G9,"") | H9: =IF(Navegación!H9<>"",Navegación!H9,"") | I9: =IF(Navegación!I9<>"",Navegación!I9,"")
B10: Apellidos completos | D10: =IF(Navegación!D10<>"",Navegación!D10,"") -> CAMPO TELLEZ | E10: =IF(Navegación!E10<>"",Navegación!E10,"") | F10: =IF(Navegación!F10<>"",Navegación!F10,"") | G10: =IF(Navegación!G10<>"",Navegación!G10,"") | H10: =IF(Navegación!H10<>"",Navegación!H10,"") | I10: =IF(Navegación!I10<>"",Navegación!I10,"")
B11: Centro de costo | D11: =IF(Navegación!D11<>"",Navegación!D11,"") -> 856 | E11: =IF(Navegación!E11<>"",Navegación!E11,"") | F11: =IF(Navegación!F11<>"",Navegación!F11,"") | G11: =IF(Navegación!G11<>"",Navegación!G11,"") | H11: =IF(Navegación!H11<>"",Navegación!H11,"") | I11: =IF(Navegación!I11<>"",Navegación!I11,"")
B12: Teléfono/Extensión de contacto del usuario | D12: =IF(Navegación!D12<>"",Navegación!D12,"") | E12: =IF(Navegación!E12<>"",Navegación!E12,"") | F12: =IF(Navegación!F12<>"",Navegación!F12,"") | G12: =IF(Navegación!G12<>"",Navegación!G12,"") | H12: =IF(Navegación!H12<>"",Navegación!H12,"") | I12: =IF(Navegación!I12<>"",Navegación!I12,"")
B13: Celular | D13: =IF(Navegación!D13<>"",Navegación!D13,"") -> 3150727969 | E13: =IF(Navegación!E13<>"",Navegación!E13,"") | F13: =IF(Navegación!F13<>"",Navegación!F13,"") | G13: =IF(Navegación!G13<>"",Navegación!G13,"") | H13: =IF(Navegación!H13<>"",Navegación!H13,"") | I13: =IF(Navegación!I13<>"",Navegación!I13,"")
B14: Dependencia | D14: =IF(Navegación!D14<>"",Navegación!D14,"") -> Gobierno | E14: =IF(Navegación!E14<>"",Navegación!E14,"") | F14: =IF(Navegación!F14<>"",Navegación!F14,"") | G14: =IF(Navegación!G14<>"",Navegación!G14,"") | H14: =IF(Navegación!H14<>"",Navegación!H14,"") | I14: =IF(Navegación!I14<>"",Navegación!I14,"")
B15: Cargo | D15: =IF(Navegación!D15<>"",Navegación!D15,"") -> Aprendiz Universitario | E15: =IF(Navegación!E15<>"",Navegación!E15,"") | F15: =IF(Navegación!F15<>"",Navegación!F15,"") | G15: =IF(Navegación!G15<>"",Navegación!G15,"") | H15: =IF(Navegación!H15<>"",Navegación!H15,"") | I15: =IF(Navegación!I15<>"",Navegación!I15,"")
B16: Empleado Cafam o Externo | D16: =IF(Navegación!D16<>"",Navegación!D16,"") -> Empleado CAFAM | E16: =IF(Navegación!E16<>"",Navegación!E16,"") | F16: =IF(Navegación!F16<>"",Navegación!F16,"") | G16: =IF(Navegación!G16<>"",Navegación!G16,"") | H16: =IF(Navegación!H16<>"",Navegación!H16,"") | I16: =IF(Navegación!I16<>"",Navegación!I16,"")
B17: Nombre de la empresa cuando es Externo | D17: =IF(Navegación!D17<>"",Navegación!D17,"") | E17: =IF(Navegación!E17<>"",Navegación!E17,"") | F17: =IF(Navegación!F17<>"",Navegación!F17,"") | G17: =IF(Navegación!G17<>"",Navegación!G17,"") | H17: =IF(Navegación!H17<>"",Navegación!H17,"") | I17: =IF(Navegación!I17<>"",Navegación!I17,"")
B18: Fecha inicio contrato: | D18: =IF(Navegación!D18<>"",Navegación!D18,"") -> 45849 | E18: =IF(Navegación!E18<>"",Navegación!E18,"") | F18: =IF(Navegación!F18<>"",Navegación!F18,"") | G18: =IF(Navegación!G18<>"",Navegación!G18,"") | H18: =IF(Navegación!H18<>"",Navegación!H18,"") | I18: =IF(Navegación!I18<>"",Navegación!I18,"")
B19: Fecha finalización contrato: (Si es indefinido escribir 31.12.9999) | D19: =IF(Navegación!D19<>"",Navegación!D19,"") | E19: =IF(Navegación!E19<>"",Navegación!E19,"") | F19: =IF(Navegación!F19<>"",Navegación!F19,"") | G19: =IF(Navegación!G19<>"",Navegación!G19,"") | H19: =IF(Navegación!H19<>"",Navegación!H19,"") | I19: =IF(Navegación!I19<>"",Navegación!I19,"")
B21: Requerimientos Plataformas MEDICAMENTOS
B22: Planeación de la Demanda - GAINS | D22: =IF(DZ23>0,Navegación!$E$50,"")
B23: Novedad (Crear/Modificación/Baja): | DZ23: =COUNTIF(D23:I23,"<>") -> 0
B24: Alias Usuario
B25: Nombre del perfil
B27: Observaciones
B32: ='WINDOWS 1'!$B$37 -> APROBADOR POR: Jefe Dpto. Servicios Compartidos | F32: ='WINDOWS 1'!F37 -> V20 de 26/09/2023 | I32: ="Pág. " &Navegación!B56 & " de " &Navegación!$B$102 -> Pág. 28 de 54

Sheet MEDICAMENTOS 12
K1: 2958465
C2: FORMATO: GESTIÓN DE IDENTIDADES
F3: DOCUMENTO USO INTERNO
B5: Las celdas resaltadas en Naranja son campos obligatorios del Formato.
B6: Información Usuarios | D6: Usuario 1 | E6: Usuario 2 | F6: Usuario 3 | G6: Usuario 4 | H6: Usuario 5 | I6: Usuario 6
B7: Tipo de documento | D7: =IF(Navegación!D7<>"",Navegación!D7,"") -> Cédula Ciudadanía | E7: =IF(Navegación!E7<>"",Navegación!E7,"") | F7: =IF(Navegación!F7<>"",Navegación!F7,"") | G7: =IF(Navegación!G7<>"",Navegación!G7,"") | H7: =IF(Navegación!H7<>"",Navegación!H7,"") | I7: =IF(Navegación!I7<>"",Navegación!I7,"")
B8: Identificación | D8: =IF(Navegación!D8<>"",Navegación!D8,"") -> 1001089595 | E8: =IF(Navegación!E8<>"",Navegación!E8,"") | F8: =IF(Navegación!F8<>"",Navegación!F8,"") | G8: =IF(Navegación!G8<>"",Navegación!G8,"") | H8: =IF(Navegación!H8<>"",Navegación!H8,"") | I8: =IF(Navegación!I8<>"",Navegación!I8,"")
B9: Nombres completos | D9: =IF(Navegación!D9<>"",Navegación!D9,"") -> JUAN PABLO | E9: =IF(Navegación!E9<>"",Navegación!E9,"") | F9: =IF(Navegación!F9<>"",Navegación!F9,"") | G9: =IF(Navegación!G9<>"",Navegación!G9,"") | H9: =IF(Navegación!H9<>"",Navegación!H9,"") | I9: =IF(Navegación!I9<>"",Navegación!I9,"")
B10: Apellidos completos | D10: =IF(Navegación!D10<>"",Navegación!D10,"") -> CAMPO TELLEZ | E10: =IF(Navegación!E10<>"",Navegación!E10,"") | F10: =IF(Navegación!F10<>"",Navegación!F10,"") | G10: =IF(Navegación!G10<>"",Navegación!G10,"") | H10: =IF(Navegación!H10<>"",Navegación!H10,"") | I10: =IF(Navegación!I10<>"",Navegación!I10,"")
B11: Centro de costo | D11: =IF(Navegación!D11<>"",Navegación!D11,"") -> 856 | E11: =IF(Navegación!E11<>"",Navegación!E11,"") | F11: =IF(Navegación!F11<>"",Navegación!F11,"") | G11: =IF(Navegación!G11<>"",Navegación!G11,"") | H11: =IF(Navegación!H11<>"",Navegación!H11,"") | I11: =IF(Navegación!I11<>"",Navegación!I11,"")
B12: Teléfono/Extensión de contacto del usuario | D12: =IF(Navegación!D12<>"",Navegación!D12,"") | E12: =IF(Navegación!E12<>"",Navegación!E12,"") | F12: =IF(Navegación!F12<>"",Navegación!F12,"") | G12: =IF(Navegación!G12<>"",Navegación!G12,"") | H12: =IF(Navegación!H12<>"",Navegación!H12,"") | I12: =IF(Navegación!I12<>"",Navegación!I12,"")
B13: Celular | D13: =IF(Navegación!D13<>"",Navegación!D13,"") -> 3150727969 | E13: =IF(Navegación!E13<>"",Navegación!E13,"") | F13: =IF(Navegación!F13<>"",Navegación!F13,"") | G13: =IF(Navegación!G13<>"",Navegación!G13,"") | H13: =IF(Navegación!H13<>"",Navegación!H13,"") | I13: =IF(Navegación!I13<>"",Navegación!I13,"")
B14: Dependencia | D14: =IF(Navegación!D14<>"",Navegación!D14,"") -> Gobierno | E14: =IF(Navegación!E14<>"",Navegación!E14,"") | F14: =IF(Navegación!F14<>"",Navegación!F14,"") | G14: =IF(Navegación!G14<>"",Navegación!G14,"") | H14: =IF(Navegación!H14<>"",Navegación!H14,"") | I14: =IF(Navegación!I14<>"",Navegación!I14,"")
B15: Cargo | D15: =IF(Navegación!D15<>"",Navegación!D15,"") -> Aprendiz Universitario | E15: =IF(Navegación!E15<>"",Navegación!E15,"") | F15: =IF(Navegación!F15<>"",Navegación!F15,"") | G15: =IF(Navegación!G15<>"",Navegación!G15,"") | H15: =IF(Navegación!H15<>"",Navegación!H15,"") | I15: =IF(Navegación!I15<>"",Navegación!I15,"")
B16: Empleado Cafam o Externo | D16: =IF(Navegación!D16<>"",Navegación!D16,"") -> Empleado CAFAM | E16: =IF(Navegación!E16<>"",Navegación!E16,"") | F16: =IF(Navegación!F16<>"",Navegación!F16,"") | G16: =IF(Navegación!G16<>"",Navegación!G16,"") | H16: =IF(Navegación!H16<>"",Navegación!H16,"") | I16: =IF(Navegación!I16<>"",Navegación!I16,"")
B17: Nombre de la empresa cuando es Externo | D17: =IF(Navegación!D17<>"",Navegación!D17,"") | E17: =IF(Navegación!E17<>"",Navegación!E17,"") | F17: =IF(Navegación!F17<>"",Navegación!F17,"") | G17: =IF(Navegación!G17<>"",Navegación!G17,"") | H17: =IF(Navegación!H17<>"",Navegación!H17,"") | I17: =IF(Navegación!I17<>"",Navegación!I17,"")
B18: Fecha inicio contrato: | D18: =IF(Navegación!D18<>"",Navegación!D18,"") -> 45849 | E18: =IF(Navegación!E18<>"",Navegación!E18,"") | F18: =IF(Navegación!F18<>"",Navegación!F18,"") | G18: =IF(Navegación!G18<>"",Navegación!G18,"") | H18: =IF(Navegación!H18<>"",Navegación!H18,"") | I18: =IF(Navegación!I18<>"",Navegación!I18,"")
B19: Fecha finalización contrato: (Si es indefinido escribir 31.12.9999) | D19: =IF(Navegación!D19<>"",Navegación!D19,"") | E19: =IF(Navegación!E19<>"",Navegación!E19,"") | F19: =IF(Navegación!F19<>"",Navegación!F19,"") | G19: =IF(Navegación!G19<>"",Navegación!G19,"") | H19: =IF(Navegación!H19<>"",Navegación!H19,"") | I19: =IF(Navegación!I19<>"",Navegación!I19,"")
B21: Requerimientos Plataformas MEDICAMENTOS
B22: DR. AKI | D22: =IF(DZ23>0,Navegación!$E$50,"")
B23: Novedad (Crear/Modificación/Baja): | DZ23: =COUNTIF(D23:I23,"<>") -> 0
B24: Alias Usuario
B25: Nombre del perfil
B27: Observaciones
B32: ='WINDOWS 1'!$B$37 -> APROBADOR POR: Jefe Dpto. Servicios Compartidos | F32: ='WINDOWS 1'!F37 -> V20 de 26/09/2023 | I32: ="Pág. " &Navegación!B56 & " de " &Navegación!$B$102 -> Pág. 28 de 54

Sheet RECREACION 1
K1: 2958465
C2: FORMATO: GESTIÓN DE IDENTIDADES
F3: DOCUMENTO USO INTERNO
B5: Las celdas resaltadas en Naranja son campos obligatorios del Formato.
B6: Información Usuarios | D6: Usuario 1 | E6: Usuario 2 | F6: Usuario 3 | G6: Usuario 4 | H6: Usuario 5 | I6: Usuario 6
B7: Tipo de documento | D7: =IF(Navegación!D7<>"",Navegación!D7,"") -> Cédula Ciudadanía | E7: =IF(Navegación!E7<>"",Navegación!E7,"") | F7: =IF(Navegación!F7<>"",Navegación!F7,"") | G7: =IF(Navegación!G7<>"",Navegación!G7,"") | H7: =IF(Navegación!H7<>"",Navegación!H7,"") | I7: =IF(Navegación!I7<>"",Navegación!I7,"")
B8: Identificación | D8: =IF(Navegación!D8<>"",Navegación!D8,"") -> 1001089595 | E8: =IF(Navegación!E8<>"",Navegación!E8,"") | F8: =IF(Navegación!F8<>"",Navegación!F8,"") | G8: =IF(Navegación!G8<>"",Navegación!G8,"") | H8: =IF(Navegación!H8<>"",Navegación!H8,"") | I8: =IF(Navegación!I8<>"",Navegación!I8,"")
B9: Nombres completos | D9: =IF(Navegación!D9<>"",Navegación!D9,"") -> JUAN PABLO | E9: =IF(Navegación!E9<>"",Navegación!E9,"") | F9: =IF(Navegación!F9<>"",Navegación!F9,"") | G9: =IF(Navegación!G9<>"",Navegación!G9,"") | H9: =IF(Navegación!H9<>"",Navegación!H9,"") | I9: =IF(Navegación!I9<>"",Navegación!I9,"")
B10: Apellidos completos | D10: =IF(Navegación!D10<>"",Navegación!D10,"") -> CAMPO TELLEZ | E10: =IF(Navegación!E10<>"",Navegación!E10,"") | F10: =IF(Navegación!F10<>"",Navegación!F10,"") | G10: =IF(Navegación!G10<>"",Navegación!G10,"") | H10: =IF(Navegación!H10<>"",Navegación!H10,"") | I10: =IF(Navegación!I10<>"",Navegación!I10,"")
B11: Centro de costo | D11: =IF(Navegación!D11<>"",Navegación!D11,"") -> 856 | E11: =IF(Navegación!E11<>"",Navegación!E11,"") | F11: =IF(Navegación!F11<>"",Navegación!F11,"") | G11: =IF(Navegación!G11<>"",Navegación!G11,"") | H11: =IF(Navegación!H11<>"",Navegación!H11,"") | I11: =IF(Navegación!I11<>"",Navegación!I11,"")
B12: Teléfono/Extensión de contacto del usuario | D12: =IF(Navegación!D12<>"",Navegación!D12,"") | E12: =IF(Navegación!E12<>"",Navegación!E12,"") | F12: =IF(Navegación!F12<>"",Navegación!F12,"") | G12: =IF(Navegación!G12<>"",Navegación!G12,"") | H12: =IF(Navegación!H12<>"",Navegación!H12,"") | I12: =IF(Navegación!I12<>"",Navegación!I12,"")
B13: Celular | D13: =IF(Navegación!D13<>"",Navegación!D13,"") -> 3150727969 | E13: =IF(Navegación!E13<>"",Navegación!E13,"") | F13: =IF(Navegación!F13<>"",Navegación!F13,"") | G13: =IF(Navegación!G13<>"",Navegación!G13,"") | H13: =IF(Navegación!H13<>"",Navegación!H13,"") | I13: =IF(Navegación!I13<>"",Navegación!I13,"")
B14: Dependencia | D14: =IF(Navegación!D14<>"",Navegación!D14,"") -> Gobierno | E14: =IF(Navegación!E14<>"",Navegación!E14,"") | F14: =IF(Navegación!F14<>"",Navegación!F14,"") | G14: =IF(Navegación!G14<>"",Navegación!G14,"") | H14: =IF(Navegación!H14<>"",Navegación!H14,"") | I14: =IF(Navegación!I14<>"",Navegación!I14,"")
B15: Cargo | D15: =IF(Navegación!D15<>"",Navegación!D15,"") -> Aprendiz Universitario | E15: =IF(Navegación!E15<>"",Navegación!E15,"") | F15: =IF(Navegación!F15<>"",Navegación!F15,"") | G15: =IF(Navegación!G15<>"",Navegación!G15,"") | H15: =IF(Navegación!H15<>"",Navegación!H15,"") | I15: =IF(Navegación!I15<>"",Navegación!I15,"")
B16: Empleado Cafam o Externo | D16: =IF(Navegación!D16<>"",Navegación!D16,"") -> Empleado CAFAM | E16: =IF(Navegación!E16<>"",Navegación!E16,"") | F16: =IF(Navegación!F16<>"",Navegación!F16,"") | G16: =IF(Navegación!G16<>"",Navegación!G16,"") | H16: =IF(Navegación!H16<>"",Navegación!H16,"") | I16: =IF(Navegación!I16<>"",Navegación!I16,"")
B17: Nombre de la empresa cuando es Externo | D17: =IF(Navegación!D17<>"",Navegación!D17,"") | E17: =IF(Navegación!E17<>"",Navegación!E17,"") | F17: =IF(Navegación!F17<>"",Navegación!F17,"") | G17: =IF(Navegación!G17<>"",Navegación!G17,"") | H17: =IF(Navegación!H17<>"",Navegación!H17,"") | I17: =IF(Navegación!I17<>"",Navegación!I17,"")
B18: Fecha inicio contrato: | D18: =IF(Navegación!D18<>"",Navegación!D18,"") -> 45849 | E18: =IF(Navegación!E18<>"",Navegación!E18,"") | F18: =IF(Navegación!F18<>"",Navegación!F18,"") | G18: =IF(Navegación!G18<>"",Navegación!G18,"") | H18: =IF(Navegación!H18<>"",Navegación!H18,"") | I18: =IF(Navegación!I18<>"",Navegación!I18,"")
B19: Fecha finalización contrato: (Si es indefinido escribir 31.12.9999) | D19: =IF(Navegación!D19<>"",Navegación!D19,"") | E19: =IF(Navegación!E19<>"",Navegación!E19,"") | F19: =IF(Navegación!F19<>"",Navegación!F19,"") | G19: =IF(Navegación!G19<>"",Navegación!G19,"") | H19: =IF(Navegación!H19<>"",Navegación!H19,"") | I19: =IF(Navegación!I19<>"",Navegación!I19,"")
B21: Aplicaciones Recreación y Deportes
B22: NEW PLAN | D22: =IF(DZ24>0,Navegación!$E$56,"")
D23: =ADDRESS(MATCH($B$22,RolesNew[[#All],[Concepto]],0)+249,13,1) -> $M$270 | E23: =D23 -> $M$270 | F23: =E23 -> $M$270 | G23: =F23 -> $M$270 | H23: =G23 -> $M$270 | I23: =H23 -> $M$270
B24: Novedad (Crear/Modificación/Baja): | DZ24: =COUNTIF(D24:I24,"<>") -> 0
B25: Alias Usuario
B26: Nombre del perfil
B27: NEW HOTEL | D27: =IF(DZ29>0,Navegación!$E$56,"")
D28: =ADDRESS(MATCH($B$27,RolesNew[[#All],[Concepto]],0)+249,13,1) -> $M$254 | E28: =D28 -> $M$254 | F28: =E28 -> $M$254 | G28: =F28 -> $M$254 | H28: =G28 -> $M$254 | I28: =H28 -> $M$254
B29: Novedad (Crear/Modificación/Baja): | DZ29: =COUNTIF(D29:I29,"<>") -> 0
B30: Alias Usuario
B31: Nombre del perfil
B32: NEW POS | D32: =IF(DZ34>0,Navegación!$E$56,"")
D33: =ADDRESS(MATCH($B$32,RolesNew[[#All],[Concepto]],0)+249,13,1) -> $M$286 | E33: =D33 -> $M$286 | F33: =E33 -> $M$286 | G33: =F33 -> $M$286 | H33: =G33 -> $M$286 | I33: =H33 -> $M$286
B34: Novedad (Crear/Modificación/Baja): | DZ34: =COUNTIF(D34:I34,"<>") -> 0
B35: Alias Usuario
B36: Nombre del perfil
B37: NEW STOCK | D37: =IF(DZ39>0,Navegación!$E$56,"")
D38: =ADDRESS(MATCH($B$37,RolesNew[[#All],[Concepto]],0)+249,13,1) -> $M$298 | E38: =D38 -> $M$298 | F38: =E38 -> $M$298 | G38: =F38 -> $M$298 | H38: =G38 -> $M$298 | I38: =H38 -> $M$298
B39: Novedad (Crear/Modificación/Baja): | DZ39: =COUNTIF(D39:I39,"<>") -> 0
B40: Alias Usuario
B41: Nombre del perfil
B42: NEW CAJA | D42: =IF(DZ44>0,Navegación!$E$56,"")
D43: =ADDRESS(MATCH($B$42,RolesNew[[#All],[Concepto]],0)+249,13,1) -> $M$251 | E43: =D43 -> $M$251 | F43: =E43 -> $M$251 | G43: =F43 -> $M$251 | H43: =G43 -> $M$251 | I43: =H43 -> $M$251
B44: Novedad (Crear/Modificación/Baja): | DZ44: =COUNTIF(D44:I44,"<>") -> 0
B45: Alias Usuario
B46: Nombre del enlace | D46: =IF('FINANCIERA 2'!D30="Asesor/Cajero",IF(AND('RECREACION 1'!D24<>"",'RECREACION 1'!D29<>""),"Seven-New Plan/NewHotel",IF('RECREACION 1'!D24<>"","Seven-New Plan",IF('RECREACION 1'!D29<>"","Seven-New Hotel",""))),"") | E46: =IF('FINANCIERA 2'!E30="Asesor/Cajero",IF(AND('RECREACION 1'!E24<>"",'RECREACION 1'!E29<>""),"Seven-New Plan/NewHotel",IF('RECREACION 1'!E24<>"","Seven-New Plan",IF('RECREACION 1'!E29<>"","Seven-New Hotel",""))),"") | F46: =IF('FINANCIERA 2'!F30="Asesor/Cajero",IF(AND('RECREACION 1'!F24<>"",'RECREACION 1'!F29<>""),"Seven-New Plan/NewHotel",IF('RECREACION 1'!F24<>"","Seven-New Plan",IF('RECREACION 1'!F29<>"","Seven-New Hotel",""))),"") | G46: =IF('FINANCIERA 2'!G30="Asesor/Cajero",IF(AND('RECREACION 1'!G24<>"",'RECREACION 1'!G29<>""),"Seven-New Plan/NewHotel",IF('RECREACION 1'!G24<>"","Seven-New Plan",IF('RECREACION 1'!G29<>"","Seven-New Hotel",""))),"") | H46: =IF('FINANCIERA 2'!H30="Asesor/Cajero",IF(AND('RECREACION 1'!H24<>"",'RECREACION 1'!H29<>""),"Seven-New Plan/NewHotel",IF('RECREACION 1'!H24<>"","Seven-New Plan",IF('RECREACION 1'!H29<>"","Seven-New Hotel",""))),"") | I46: =IF('FINANCIERA 2'!I30="Asesor/Cajero",IF(AND('RECREACION 1'!I24<>"",'RECREACION 1'!I29<>""),"Seven-New Plan/NewHotel",IF('RECREACION 1'!I24<>"","Seven-New Plan",IF('RECREACION 1'!I29<>"","Seven-New Hotel",""))),"")
B48: Observaciones
B53: ='WINDOWS 1'!$B$37 -> APROBADOR POR: Jefe Dpto. Servicios Compartidos | F53: ='WINDOWS 1'!F37 -> V20 de 26/09/2023 | I53: ="Pág. " &Navegación!B56 & " de " &Navegación!$B$102 -> Pág. 28 de 54
DZ55: =COUNTIF(#REF!,"<>") -> #REF!
DZ60: =COUNTIF(#REF!,"<>") -> #REF!
DZ65: =COUNTIF(#REF!,"<>") -> #REF!
L250: Concepto | M250: Perfil
L251: NEW CAJA | M251: Seven-New Hotel
L252: NEW CAJA | M252: Seven-New Plan
L253: NEW CAJA | M253: Seven-New Hotel/New Plan
L254: NEW HOTEL | M254: Analisis
L255: NEW HOTEL | M255: Asesor de Servicios
L256: NEW HOTEL | M256: Auditor Nocturno
L257: NEW HOTEL | M257: Consulta
L258: NEW HOTEL | M258: Contact Center
L259: NEW HOTEL | M259: Control Información
L260: NEW HOTEL | M260: Coordinador Logistico
L261: NEW HOTEL | M261: EVT
... L385: ZEUS ONLINE | M385: Administradores

Sheet RECREACION 2
K1: 2958465
C2: FORMATO: GESTIÓN DE IDENTIDADES
F3: DOCUMENTO USO INTERNO
B5: Las celdas resaltadas en Naranja son campos obligatorios del Formato.
B6: Información Usuarios | D6: Usuario 1 | E6: Usuario 2 | F6: Usuario 3 | G6: Usuario 4 | H6: Usuario 5 | I6: Usuario 6
B7: Tipo de documento | D7: =IF(Navegación!D7<>"",Navegación!D7,"") -> Cédula Ciudadanía | E7: =IF(Navegación!E7<>"",Navegación!E7,"") | F7: =IF(Navegación!F7<>"",Navegación!F7,"") | G7: =IF(Navegación!G7<>"",Navegación!G7,"") | H7: =IF(Navegación!H7<>"",Navegación!H7,"") | I7: =IF(Navegación!I7<>"",Navegación!I7,"")
B8: Identificación | D8: =IF(Navegación!D8<>"",Navegación!D8,"") -> 1001089595 | E8: =IF(Navegación!E8<>"",Navegación!E8,"") | F8: =IF(Navegación!F8<>"",Navegación!F8,"") | G8: =IF(Navegación!G8<>"",Navegación!G8,"") | H8: =IF(Navegación!H8<>"",Navegación!H8,"") | I8: =IF(Navegación!I8<>"",Navegación!I8,"")
B9: Nombres completos | D9: =IF(Navegación!D9<>"",Navegación!D9,"") -> JUAN PABLO | E9: =IF(Navegación!E9<>"",Navegación!E9,"") | F9: =IF(Navegación!F9<>"",Navegación!F9,"") | G9: =IF(Navegación!G9<>"",Navegación!G9,"") | H9: =IF(Navegación!H9<>"",Navegación!H9,"") | I9: =IF(Navegación!I9<>"",Navegación!I9,"")
B10: Apellidos completos | D10: =IF(Navegación!D10<>"",Navegación!D10,"") -> CAMPO TELLEZ | E10: =IF(Navegación!E10<>"",Navegación!E10,"") | F10: =IF(Navegación!F10<>"",Navegación!F10,"") | G10: =IF(Navegación!G10<>"",Navegación!G10,"") | H10: =IF(Navegación!H10<>"",Navegación!H10,"") | I10: =IF(Navegación!I10<>"",Navegación!I10,"")
B11: Centro de costo | D11: =IF(Navegación!D11<>"",Navegación!D11,"") -> 856 | E11: =IF(Navegación!E11<>"",Navegación!E11,"") | F11: =IF(Navegación!F11<>"",Navegación!F11,"") | G11: =IF(Navegación!G11<>"",Navegación!G11,"") | H11: =IF(Navegación!H11<>"",Navegación!H11,"") | I11: =IF(Navegación!I11<>"",Navegación!I11,"")
B12: Teléfono/Extensión de contacto del usuario | D12: =IF(Navegación!D12<>"",Navegación!D12,"") | E12: =IF(Navegación!E12<>"",Navegación!E12,"") | F12: =IF(Navegación!F12<>"",Navegación!F12,"") | G12: =IF(Navegación!G12<>"",Navegación!G12,"") | H12: =IF(Navegación!H12<>"",Navegación!H12,"") | I12: =IF(Navegación!I12<>"",Navegación!I12,"")
B13: Celular | D13: =IF(Navegación!D13<>"",Navegación!D13,"") -> 3150727969 | E13: =IF(Navegación!E13<>"",Navegación!E13,"") | F13: =IF(Navegación!F13<>"",Navegación!F13,"") | G13: =IF(Navegación!G13<>"",Navegación!G13,"") | H13: =IF(Navegación!H13<>"",Navegación!H13,"") | I13: =IF(Navegación!I13<>"",Navegación!I13,"")
B14: Dependencia | D14: =IF(Navegación!D14<>"",Navegación!D14,"") -> Gobierno | E14: =IF(Navegación!E14<>"",Navegación!E14,"") | F14: =IF(Navegación!F14<>"",Navegación!F14,"") | G14: =IF(Navegación!G14<>"",Navegación!G14,"") | H14: =IF(Navegación!H14<>"",Navegación!H14,"") | I14: =IF(Navegación!I14<>"",Navegación!I14,"")
B15: Cargo | D15: =IF(Navegación!D15<>"",Navegación!D15,"") -> Aprendiz Universitario | E15: =IF(Navegación!E15<>"",Navegación!E15,"") | F15: =IF(Navegación!F15<>"",Navegación!F15,"") | G15: =IF(Navegación!G15<>"",Navegación!G15,"") | H15: =IF(Navegación!H15<>"",Navegación!H15,"") | I15: =IF(Navegación!I15<>"",Navegación!I15,"")
B16: Empleado Cafam o Externo | D16: =IF(Navegación!D16<>"",Navegación!D16,"") -> Empleado CAFAM | E16: =IF(Navegación!E16<>"",Navegación!E16,"") | F16: =IF(Navegación!F16<>"",Navegación!F16,"") | G16: =IF(Navegación!G16<>"",Navegación!G16,"") | H16: =IF(Navegación!H16<>"",Navegación!H16,"") | I16: =IF(Navegación!I16<>"",Navegación!I16,"")
B17: Nombre de la empresa cuando es Externo | D17: =IF(Navegación!D17<>"",Navegación!D17,"") | E17: =IF(Navegación!E17<>"",Navegación!E17,"") | F17: =IF(Navegación!F17<>"",Navegación!F17,"") | G17: =IF(Navegación!G17<>"",Navegación!G17,"") | H17: =IF(Navegación!H17<>"",Navegación!H17,"") | I17: =IF(Navegación!I17<>"",Navegación!I17,"")
B18: Fecha inicio contrato: | D18: =IF(Navegación!D18<>"",Navegación!D18,"") -> 45849 | E18: =IF(Navegación!E18<>"",Navegación!E18,"") | F18: =IF(Navegación!F18<>"",Navegación!F18,"") | G18: =IF(Navegación!G18<>"",Navegación!G18,"") | H18: =IF(Navegación!H18<>"",Navegación!H18,"") | I18: =IF(Navegación!I18<>"",Navegación!I18,"")
B19: Fecha finalización contrato: (Si es indefinido escribir 31.12.9999) | D19: =IF(Navegación!D19<>"",Navegación!D19,"") | E19: =IF(Navegación!E19<>"",Navegación!E19,"") | F19: =IF(Navegación!F19<>"",Navegación!F19,"") | G19: =IF(Navegación!G19<>"",Navegación!G19,"") | H19: =IF(Navegación!H19<>"",Navegación!H19,"") | I19: =IF(Navegación!I19<>"",Navegación!I19,"")
B21: Aplicaciones Recreación y Deportes
B22: SAC -CIAC | D22: =IF(DZ24>0,Navegación!$E$57,"")
D23: =ADDRESS(MATCH($B$22,RolesNew117[[#All],[Concepto]],0)+249,13,1) -> $M$331 | E23: =D23 -> $M$331 | F23: =E23 -> $M$331 | G23: =F23 -> $M$331 | H23: =G23 -> $M$331 | I23: =H23 -> $M$331
B24: Novedad (Modificación/Baja, Reinicio contraseña): | DZ24: =COUNTIF(D24:I24,"<>") -> 0
B25: Alias Usuario
B26: Nombre del perfil
B27: Perfil facturador
B29: Observaciones
B34: ='WINDOWS 1'!$B$37 -> APROBADOR POR: Jefe Dpto. Servicios Compartidos | F34: ='WINDOWS 1'!F37 -> V20 de 26/09/2023 | I34: ="Pág. " &Navegación!B57 & " de " &Navegación!$B$102 -> Pág. 29 de 54
D39: 0 | DZ39: =COUNTIF(#REF!,"<>") -> #REF!
DZ44: =COUNTIF(#REF!,"<>") -> #REF!
DZ49: =COUNTIF(D24:I24,"<>") -> 0
DZ55: =COUNTIF(#REF!,"<>") -> #REF!
DZ60: =COUNTIF(#REF!,"<>") -> #REF!
DZ65: =COUNTIF(#REF!,"<>") -> #REF!
L250: Concepto | M250: Perfil
L251: NEW CAJA | M251: Ama Llaves
L252: NEW CAJA | M252: Analisis
L253: NEW CAJA | M253: Asesor Central Servicios
L254: NEW CAJA | M254: Asesor Movil
L255: NEW CAJA | M255: Asesores Turisticos
L256: NEW CAJA | M256: Auditor Nocturno
L257: NEW CAJA | M257: Consulta
L258: NEW CAJA | M258: Contable
L259: NEW CAJA | M259: Contact Center
L260: NEW CAJA | M260: Coordinador Logistico
L261: NEW CAJA | M261: EVT
... L399: ZEUS ONLINE | M399: Administradores

Sheet RECREACION 3
K1: 2958465
C2: FORMATO: GESTIÓN DE IDENTIDADES
F3: DOCUMENTO USO INTERNO
B5: Las celdas resaltadas en Naranja son campos obligatorios del Formato.
B6: Información Usuarios | D6: Usuario 1 | E6: Usuario 2 | F6: Usuario 3 | G6: Usuario 4 | H6: Usuario 5 | I6: Usuario 6
B7: Tipo de documento | D7: =IF(Navegación!D7<>"",Navegación!D7,"") -> Cédula Ciudadanía | E7: =IF(Navegación!E7<>"",Navegación!E7,"") | F7: =IF(Navegación!F7<>"",Navegación!F7,"") | G7: =IF(Navegación!G7<>"",Navegación!G7,"") | H7: =IF(Navegación!H7<>"",Navegación!H7,"") | I7: =IF(Navegación!I7<>"",Navegación!I7,"")
B8: Identificación | D8: =IF(Navegación!D8<>"",Navegación!D8,"") -> 1001089595 | E8: =IF(Navegación!E8<>"",Navegación!E8,"") | F8: =IF(Navegación!F8<>"",Navegación!F8,"") | G8: =IF(Navegación!G8<>"",Navegación!G8,"") | H8: =IF(Navegación!H8<>"",Navegación!H8,"") | I8: =IF(Navegación!I8<>"",Navegación!I8,"")
B9: Nombres completos | D9: =IF(Navegación!D9<>"",Navegación!D9,"") -> JUAN PABLO | E9: =IF(Navegación!E9<>"",Navegación!E9,"") | F9: =IF(Navegación!F9<>"",Navegación!F9,"") | G9: =IF(Navegación!G9<>"",Navegación!G9,"") | H9: =IF(Navegación!H9<>"",Navegación!H9,"") | I9: =IF(Navegación!I9<>"",Navegación!I9,"")
B10: Apellidos completos | D10: =IF(Navegación!D10<>"",Navegación!D10,"") -> CAMPO TELLEZ | E10: =IF(Navegación!E10<>"",Navegación!E10,"") | F10: =IF(Navegación!F10<>"",Navegación!F10,"") | G10: =IF(Navegación!G10<>"",Navegación!G10,"") | H10: =IF(Navegación!H10<>"",Navegación!H10,"") | I10: =IF(Navegación!I10<>"",Navegación!I10,"")
B11: Centro de costo | D11: =IF(Navegación!D11<>"",Navegación!D11,"") -> 856 | E11: =IF(Navegación!E11<>"",Navegación!E11,"") | F11: =IF(Navegación!F11<>"",Navegación!F11,"") | G11: =IF(Navegación!G11<>"",Navegación!G11,"") | H11: =IF(Navegación!H11<>"",Navegación!H11,"") | I11: =IF(Navegación!I11<>"",Navegación!I11,"")
B12: Teléfono/Extensión de contacto del usuario | D12: =IF(Navegación!D12<>"",Navegación!D12,"") | E12: =IF(Navegación!E12<>"",Navegación!E12,"") | F12: =IF(Navegación!F12<>"",Navegación!F12,"") | G12: =IF(Navegación!G12<>"",Navegación!G12,"") | H12: =IF(Navegación!H12<>"",Navegación!H12,"") | I12: =IF(Navegación!I12<>"",Navegación!I12,"")
B13: Celular | D13: =IF(Navegación!D13<>"",Navegación!D13,"") -> 3150727969 | E13: =IF(Navegación!E13<>"",Navegación!E13,"") | F13: =IF(Navegación!F13<>"",Navegación!F13,"") | G13: =IF(Navegación!G13<>"",Navegación!G13,"") | H13: =IF(Navegación!H13<>"",Navegación!H13,"") | I13: =IF(Navegación!I13<>"",Navegación!I13,"")
B14: Dependencia | D14: =IF(Navegación!D14<>"",Navegación!D14,"") -> Gobierno | E14: =IF(Navegación!E14<>"",Navegación!E14,"") | F14: =IF(Navegación!F14<>"",Navegación!F14,"") | G14: =IF(Navegación!G14<>"",Navegación!G14,"") | H14: =IF(Navegación!H14<>"",Navegación!H14,"") | I14: =IF(Navegación!I14<>"",Navegación!I14,"")
B15: Cargo | D15: =IF(Navegación!D15<>"",Navegación!D15,"") -> Aprendiz Universitario | E15: =IF(Navegación!E15<>"",Navegación!E15,"") | F15: =IF(Navegación!F15<>"",Navegación!F15,"") | G15: =IF(Navegación!G15<>"",Navegación!G15,"") | H15: =IF(Navegación!H15<>"",Navegación!H15,"") | I15: =IF(Navegación!I15<>"",Navegación!I15,"")
B16: Empleado Cafam o Externo | D16: =IF(Navegación!D16<>"",Navegación!D16,"") -> Empleado CAFAM | E16: =IF(Navegación!E16<>"",Navegación!E16,"") | F16: =IF(Navegación!F16<>"",Navegación!F16,"") | G16: =IF(Navegación!G16<>"",Navegación!G16,"") | H16: =IF(Navegación!H16<>"",Navegación!H16,"") | I16: =IF(Navegación!I16<>"",Navegación!I16,"")
B17: Nombre de la empresa cuando es Externo | D17: =IF(Navegación!D17<>"",Navegación!D17,"") | E17: =IF(Navegación!E17<>"",Navegación!E17,"") | F17: =IF(Navegación!F17<>"",Navegación!F17,"") | G17: =IF(Navegación!G17<>"",Navegación!G17,"") | H17: =IF(Navegación!H17<>"",Navegación!H17,"") | I17: =IF(Navegación!I17<>"",Navegación!I17,"")
B18: Fecha inicio contrato: | D18: =IF(Navegación!D18<>"",Navegación!D18,"") -> 45849 | E18: =IF(Navegación!E18<>"",Navegación!E18,"") | F18: =IF(Navegación!F18<>"",Navegación!F18,"") | G18: =IF(Navegación!G18<>"",Navegación!G18,"") | H18: =IF(Navegación!H18<>"",Navegación!H18,"") | I18: =IF(Navegación!I18<>"",Navegación!I18,"")
B19: Fecha finalización contrato: (Si es indefinido escribir 31.12.9999) | D19: =IF(Navegación!D19<>"",Navegación!D19,"") | E19: =IF(Navegación!E19<>"",Navegación!E19,"") | F19: =IF(Navegación!F19<>"",Navegación!F19,"") | G19: =IF(Navegación!G19<>"",Navegación!G19,"") | H19: =IF(Navegación!H19<>"",Navegación!H19,"") | I19: =IF(Navegación!I19<>"",Navegación!I19,"")
B21: Aplicaciones Recreación y Deportes
B22: SILVERNEST | D22: =IF(DZ24>0,Navegación!$E$58,"")
D23: =ADDRESS(MATCH($B$22,RolesNew117118[[#All],[Concepto]],0)+249,13,1) -> $M$384 | E23: =D23 -> $M$384 | F23: =E23 -> $M$384 | G23: =F23 -> $M$384 | H23: =G23 -> $M$384 | I23: =H23 -> $M$384
B24: Novedad (Crear/Modificación/Baja): | DZ24: =COUNTIF(D24:I24,"<>") -> 0
B25: Alias Usuario
B26: Nombre del perfil
B28: Observaciones
B33: ='WINDOWS 1'!$B$37 -> APROBADOR POR: Jefe Dpto. Servicios Compartidos | F33: ='WINDOWS 1'!F37 -> V20 de 26/09/2023 | I33: ="Pág. " &Navegación!B58 & " de " &Navegación!$B$102 -> Pág. 30 de 54
D38: 0
DZ39: =COUNTIF(#REF!,"<>") -> #REF!
DZ44: =COUNTIF(#REF!,"<>") -> #REF!
DZ49: =COUNTIF(#REF!,"<>") -> #REF!
DZ55: =COUNTIF(D24:I24,"<>") -> 0
DZ60: =COUNTIF(#REF!,"<>") -> #REF!
DZ65: =COUNTIF(#REF!,"<>") -> #REF!
L250: Concepto | M250: Perfil
L251: HERCULES | M251: Agente Contact Center
L252: HERCULES | M252: Almacenista
L253: HERCULES | M253: Asesor Comercial I
L254: HERCULES | M254: Asesor Comercial II
L255: HERCULES | M255: Asesor Corporativo II
L256: HERCULES | M256: Asesor Corporativo III
L257: HERCULES | M257: Asesor Reservas Hoteles Cafam
L258: HERCULES | M258: Asesor Turistico
L259: HERCULES | M259: Auxiliar Bodega
L260: HERCULES | M260: Auxiliar C.V.
L261: HERCULES | M261: Auxiliar Centro Recreativo
... L403: ZEUS ONLINE | M403: Supports

Sheet RECREACION 4
K1: 2958465
C2: FORMATO: GESTIÓN DE IDENTIDADES
F3: DOCUMENTO USO INTERNO
B5: Las celdas resaltadas en Naranja son campos obligatorios del Formato.
B6: Información Usuarios | D6: Usuario 1 | E6: Usuario 2 | F6: Usuario 3 | G6: Usuario 4 | H6: Usuario 5 | I6: Usuario 6
B7: Tipo de documento | D7: =IF(Navegación!D7<>"",Navegación!D7,"") -> Cédula Ciudadanía | E7: =IF(Navegación!E7<>"",Navegación!E7,"") | F7: =IF(Navegación!F7<>"",Navegación!F7,"") | G7: =IF(Navegación!G7<>"",Navegación!G7,"") | H7: =IF(Navegación!H7<>"",Navegación!H7,"") | I7: =IF(Navegación!I7<>"",Navegación!I7,"")
B8: Identificación | D8: =IF(Navegación!D8<>"",Navegación!D8,"") -> 1001089595 | E8: =IF(Navegación!E8<>"",Navegación!E8,"") | F8: =IF(Navegación!F8<>"",Navegación!F8,"") | G8: =IF(Navegación!G8<>"",Navegación!G8,"") | H8: =IF(Navegación!H8<>"",Navegación!H8,"") | I8: =IF(Navegación!I8<>"",Navegación!I8,"")
B9: Nombres completos | D9: =IF(Navegación!D9<>"",Navegación!D9,"") -> JUAN PABLO | E9: =IF(Navegación!E9<>"",Navegación!E9,"") | F9: =IF(Navegación!F9<>"",Navegación!F9,"") | G9: =IF(Navegación!G9<>"",Navegación!G9,"") | H9: =IF(Navegación!H9<>"",Navegación!H9,"") | I9: =IF(Navegación!I9<>"",Navegación!I9,"")
